Workbook
Name w_Damage: 'Model'!$B$2
Name w_Heal: 'Model'!$B$3
Name w_Shield: 'Model'!$B$4
Name w_Block: 'Model'!$B$5
Name w_Parry: 'Model'!$B$6
Name w_Poison: 'Model'!$B$7
Name w_Strength: 'Model'!$B$8
Name w_Weaken: 'Model'!$B$9
Name w_Draw: 'Model'!$B$10
Name w_Move: 'Model'!$B$11
Name w_Combo: 'Model'!$B$12
Name w_OccEnemy: 'Model'!$B$13
Name w_OccAlly: 'Model'!$B$14
Name w_MaxEnemies: 'Model'!$B$15
Name w_MaxAllies: 'Model'!$B$16
Name w_Horizon: 'Model'!$B$17
Name curve_Base: 'Model'!$B$18
Name curve_Slope: 'Model'!$B$19
Name tol_Pct: 'Model'!$B$20
Name board_Tiles: 'Model'!$B$21
Name rarity_Mult: 'Model'!$A$25:$B$29
Name list_Class: 'Enums'!$A$2:$A$13
Name list_Rarity: 'Enums'!$B$2:$B$6
Name list_Shape: 'Enums'!$C$2:$C$5
Name list_Aim: 'Enums'!$D$2:$D$3
Name list_Bool: 'Enums'!$E$2:$E$3
Name list_Buildable: 'Enums'!$F$2:$F$6
Name list_Priority: 'Enums'!$G$2:$G$4
Name list_Tag: 'Enums'!$H$2:$H$8
Name list_Keyword: 'Enums'!$I$2:$I$4
Name list_Effect: 'Enums'!$J$2:$J$122
Name list_Folder: 'Enums'!$K$2:$K$35
Name list_Condition: 'Enums'!$L$2:$L$6
Name list_CostCond: 'Enums'!$M$2:$M$6

Sheet README
A1: Card Design Workbook
A3: One button does everything: in Unity, Tools > Sync With Sheet.
A4: It applies your sheet edits to the assets, then rebuilds this workbook so anything you authored in the Inspector appears here. Safe to press whatever you changed and wherever - it works out per column which side moved, and stops rather than guessing when both did.
A6: The tabs
A7: Knight / Mage / Rogue / Cleric / Neutral | B7: THE REAL CARDS. These mirror the .asset files. Everything here syncs to Unity - add a row, change a Description, and it lands in the game.
A8: * Ideas | B8: DESIGN SPACE ONLY. Never imported, whatever the Buildable column says. To build an idea, copy its row onto the matching class tab - the leading columns are identical, so it pastes straight across.
A9: Glossary | B9: Tooltip wording for every status and keyword. Edit Title/Body/Terms and sync to reword what the player reads. Also syncs.
A10: Effects | B10: The shared CardEffect assets under Assets/Data/EffectData. Used By shows how many cards reference each one.
A11: Decks | B11: DeckData contents, one row per (deck, card) with a count.
A12: Model | B12: The balance weights. EDIT THESE - every figure on Balance is a live formula reading this tab.
A13: Balance | B13: One row per card with the derived stats. Never hand-edit; it is rebuilt on every export.
A14: Charts | B14: The four balance charts and their source tables. Also rebuilt every export.
A15: Enums | B15: Sources for the dropdowns. Mirrors the C# enums - change the enum, not this sheet.
A17: Adding a card
A18: 1. | B18: Add a row on a CLASS tab (Knight/Mage/Rogue/Cleric/Neutral) and leave GUID blank. Sync will read NEW. Rows on an Ideas tab are never built.
A19: 2. | B19: Key is the asset filename. Folder decides which sub-folder it lands in.
A20: 3. | B20: Effect 1..3 take the NAME of an effect asset - see the Effects tab. "Damage 7" is fine even if it does not exist yet; the importer creates it.
A21: 4. | B21: Aim is Tile (the clicked tile) or Self (the caster). Area is Single, a radius like "Manhattan 0-2", or "Pattern:Cone3".
A22: 5. | B22: Save and CLOSE the workbook - the sync rewrites this file, so it cannot be open in Excel.
A23: 6. | B23: In Unity: Tools > Sync With Sheet (top of the menu).
A25: Authoring in Unity instead
A26: Just make the asset | B26: Create the CardData in the Inspector as normal. The next sync adds a row for it here - you never add it by hand.
A27: Renaming / refiling | B27: Change Key to rename the .asset, or Folder to move it. Both go through AssetDatabase.MoveAsset, so the GUID survives and decks keep pointing at the card.
A28: Deleting | B28: Deleting a row here does NOT delete the card - it is reported and the asset kept. Delete it in Unity if you mean it.
A30: What the columns mean
A31: Key | B31: Asset filename without extension. The join key - stable even when Card Name changes.
A32: Card Name | B32: The display name shown in game. Often differs from Key.
A33: Class | B33: Which character may hold it. A mask, so Knight+Rogue is legal. Any means everyone.
A34: Cost | B34: Energy. The X axis of the power curve.
A35: Rarity | B35: How good it is as a reward. NotOffered keeps it out of every reward pool.
A36: Range Shape/Min/Max | B36: Which tiles may be clicked, measured from the caster. Chebyshev is a square, Manhattan a diamond.
A37: Area N | B37: The footprint each effect covers around its aim tile. Single is one tile.
A38: Rotatable | B38: TRUE lets the player turn the card's area a quarter turn while aiming (E). Only meaningful with a Pattern area - a Radius area already reads the same after any turn.
A39: Cond N | B39: A board condition on effect N, checked on the caster as the card resolves. "Alone +6" adds 6 to the effect while it holds (Damage 7 with "NextToHero +3" deals 10 next to a hero). "Alone only" makes the effect fire only while it holds. Blank = always. Conditions: NextToTotem, HasShield, HasBlock, NextToHero, Alone (no other hero within 2 tiles).
A40: Cost Cond | B40: A board condition that lowers the whole card's cost while it holds. "NextToHero -1" = costs 1 less next to another hero. Never below 0. Blank = the printed cost always applies.
A41: GUID | B41: Unity asset id. Blank means the card does not exist yet - this is what the importer diffs on.
A42: Buildable | B42: Ideas tabs only, and purely informational now: Yes means the current engine could build it, anything else names what is missing. It does NOT gate anything - Ideas rows are never imported at all.
A43: Quantifiable | B43: Balance tab. Yes = fully scored. Partial = has a numeric core plus an unscored rider (Ice Shard damages AND freezes) - plotted, but Flag reads RIDER because the number is a floor. No = nothing numeric at all, kept off the curve entirely.
A45: Rewording cards and tooltips
A46: Card text | B46: Edit Description on a class tab and sync. The change is written straight to the .asset.
A47: Tooltips | B47: Edit Title/Body/Terms on the Glossary tab the same way. Keep the {stacks} / {amount} / {magnitude} placeholders - they are filled from the live status, so removing one freezes the number at whatever you typed.
A48: If both sides changed | B48: That card is left alone on BOTH sides and named in the Unity console, showing what it was, what Unity says and what the sheet says. Make them agree, or change only one, then sync again. Nothing is overwritten behind your back.
A50: Rules that are easy to trip over
A51: Never reorder an enum | B51: Enum ints are written into .asset files. Appending is safe; reordering silently rewrites every card that used the old value.
A52: AllCards.asset is automatic | B52: CardLibraryEditor rescans on every CardData import. Never add cards to it by hand.
A53: The importer never deletes | B53: A card present as an asset but missing from the sheet is reported, not removed.

Sheet Knight
A1: Card Name | B1: Cost | C1: Rarity | D1: Effect 1 | E1: Effect 2 | F1: Effect 3 | G1: Description | H1: Range Shape | I1: Range Min | J1: Range Max | K1: Key | L1: Class | M1: Folder | N1: Tags | O1: Aim 1 | P1: Area 1 | Q1: Cond 1 | R1: Aim 2 | S1: Area 2 | T1: Cond 2 | U1: Aim 3 | V1: Area 3 | W1: Cond 3 | X1: Cost Cond | Y1: Keywords | Z1: No Reward | AA1: Rotatable | AB1: Animation | AC1: GUID | AD1: Sync | AE1: Notes
A2: Block | B2: 1 | C2: Uncommon | D2: Block 1 | G2: Gain Block. | H2: SelfTile | I2: 0 | J2: 0 | K2: Block | L2: Knight+Rogue | M2: Buff (Defensive) | N2: Defence | O2: Self | P2: Single | Z2: TRUE | AA2: FALSE | AC2: db83bbf36eb240f79a3c309c29ac4ea2 | AD2: =IF($AC2="","NEW","Live")
A3: Brothers in Arms | B3: 1 | C3: Uncommon | D3: Shield 8 | E3: Draw 1 | G3: Gain 8 Shield. Draw 1. Costs 0 next to another hero. | H3: SelfTile | I3: 0 | J3: 0 | K3: Brothers in Arms | L3: Knight | M3: Buff (Defensive) | N3: Defence | O3: Self | P3: Single | R3: Self | S3: Single | X3: NextToHero -1 | Z3: FALSE | AA3: FALSE | AC3: acb8cab12f6147a47bc05d1cc6b132c8 | AD3: =IF($AC3="","NEW","Live")
A4: Bulwark Stance | B4: 1 | C4: Uncommon | D4: Shield 6 | E4: Draw 1 | G4: Gain 6 Shield. Draw 1. Costs 0 while you have Block. | H4: SelfTile | I4: 0 | J4: 0 | K4: Bulwark Stance | L4: Knight | M4: Buff (Defensive) | N4: Defence | O4: Self | P4: Single | R4: Self | S4: Single | X4: HasBlock -1 | Z4: FALSE | AA4: FALSE | AC4: a3c385930ede9634f8443f5f76e4554c | AD4: =IF($AC4="","NEW","Live")
A5: Guard Up | B5: 1 | C5: Uncommon | D5: Shield 6 | G5: Gain 6 Shield. Costs 0 next to a totem. | H5: SelfTile | I5: 0 | J5: 0 | K5: Guard Up | L5: Knight | M5: Buff (Defensive) | N5: Defence | O5: Self | P5: Single | X5: NextToTotem -1 | Z5: FALSE | AA5: FALSE | AC5: 2ae701b8981918a4db193762447f3d09 | AD5: =IF($AC5="","NEW","Live")
A6: Last Bastion | B6: 1 | C6: Rare | D6: Taunt | E6: Shield 6 | F6: Draw 1 | G6: Taunt every enemy within 2. Gain 6 Shield. Alone: gain 12 and draw 1. | H6: SelfTile | I6: 0 | J6: 0 | K6: Last Bastion | L6: Knight | M6: Buff (Defensive) | O6: Self | P6: Chebyshev 1-2 | R6: Self | S6: Single | T6: Alone +6 | U6: Self | V6: Single | W6: Alone only | Z6: FALSE | AA6: FALSE | AC6: d28613fe38df1f7498e6b9630413bdd5 | AD6: =IF($AC6="","NEW","Live")
A7: Lone Stand | B7: 1 | C7: Uncommon | D7: Shield 6 | G7: Gain 6 Shield. Alone: gain 12 instead. | H7: SelfTile | I7: 0 | J7: 0 | K7: Lone Stand | L7: Knight | M7: Buff (Defensive) | N7: Defence | O7: Self | P7: Single | Q7: Alone +6 | Z7: FALSE | AA7: FALSE | AC7: b1cd626d8d06e8a478d67a6d8b23377e | AD7: =IF($AC7="","NEW","Live")
A8: Parry | B8: 1 | C8: Uncommon | D8: Parry 1 | G8: Gain 1 Parry. | H8: SelfTile | I8: 0 | J8: 0 | K8: Parry | L8: Knight | M8: Buff (Defensive) | N8: Defence | O8: Self | P8: Single | Z8: FALSE | AA8: FALSE | AC8: e5962a056448478d8cb8225f4e84306d | AD8: =IF($AC8="","NEW","Live")
A9: Phalanx | B9: 1 | C9: Uncommon | D9: Block 1 | G9: You and allies next to you gain Block. | H9: SelfTile | I9: 0 | J9: 0 | K9: Phalanx | L9: Knight | M9: Buff (Defensive) | N9: Defence | O9: Self | P9: Chebyshev 0-1 | Z9: FALSE | AA9: FALSE | AC9: 3d86e8d90243cd14b8d6ee7739aed90c | AD9: =IF($AC9="","NEW","Live")
A10: Shield | B10: 1 | C10: Common | D10: Shield 7 | G10: Gain 7 Shield. | H10: SelfTile | I10: 0 | J10: 0 | K10: Shield | L10: Knight | M10: Buff (Defensive) | N10: Defence | O10: Self | P10: Single | Z10: TRUE | AA10: FALSE | AC10: 7402495d3e66bfc41b47c4d1fc79004e | AD10: =IF($AC10="","NEW","Live")
A11: Shield Wall | B11: 1 | C11: Rare | D11: Shield 6 | G11: Give 6 Shield to you and allies within 2. | H11: SelfTile | I11: 0 | J11: 0 | K11: Shield Wall | L11: Knight | M11: Buff (Defensive) | N11: Defence | O11: Self | P11: Manhattan 0-2 | Z11: FALSE | AA11: FALSE | AC11: e79ad27300b7c2c45ba217374d91c43d | AD11: =IF($AC11="","NEW","Live")
A12: Shoulder to Shoulder | B12: 1 | C12: Uncommon | D12: Shield 8 | G12: You and allies next to you gain 8 Shield. | H12: SelfTile | I12: 0 | J12: 0 | K12: Shoulder to Shoulder | L12: Knight | M12: Buff (Defensive) | N12: Defence | O12: Self | P12: Chebyshev 0-1 | Z12: FALSE | AA12: FALSE | AC12: 3fde8e39e8151ec4fa50fca0a53d9515 | AD12: =IF($AC12="","NEW","Live")
A13: Solitary Guard | B13: 1 | C13: Uncommon | D13: Block 1 | G13: Gain Block. Alone: gain 2 instead. | H13: SelfTile | I13: 0 | J13: 0 | K13: Solitary Guard | L13: Knight | M13: Buff (Defensive) | N13: Defence | O13: Self | P13: Single | Q13: Alone +1 | Z13: FALSE | AA13: FALSE | AC13: c299cb1c41bf4144bae0fbfb413ac2bf | AD13: =IF($AC13="","NEW","Live")
A14: Steely Resolve | B14: 1 | C14: Uncommon | D14: Shield 5 | E14: Draw 1 | G14: Gain 5 Shield. Draw 1 card. | H14: SelfTile | I14: 0 | J14: 0 | K14: Steely Resolve | L14: Knight | M14: Buff (Defensive) | N14: Defence | O14: Self | P14: Single | R14: Self | S14: Single | Z14: FALSE | AA14: FALSE | AC14: b2d16f22e3045c1baf6d28e51c2f6003 | AD14: =IF($AC14="","NEW","Live")
A15: Taunt | B15: 1 | C15: Uncommon | D15: Taunt | G15: Taunts enemy. | H15: Chebyshev | I15: 1 | J15: 3 | K15: Taunt | L15: Knight | M15: Buff (Defensive) | O15: Tile | P15: Single | Z15: FALSE | AA15: FALSE | AC15: af8bc827dc0c0c043aadfbceb9c91246 | AD15: =IF($AC15="","NEW","Live")
A16: Totem Guard | B16: 1 | C16: Uncommon | D16: Block 1 | E16: Draw 1 | G16: Gain Block. Draw 1. Costs 0 next to a totem. | H16: SelfTile | I16: 0 | J16: 0 | K16: Totem Guard | L16: Knight | M16: Buff (Defensive) | N16: Defence | O16: Self | P16: Single | R16: Self | S16: Single | X16: NextToTotem -1 | Z16: FALSE | AA16: FALSE | AC16: 1a09bbabdf2419140beb812ddc514fc9 | AD16: =IF($AC16="","NEW","Live")
A17: Tower Shield | B17: 1 | C17: Uncommon | D17: Shield 11 | G17: Gain 11 Shield. | H17: SelfTile | I17: 0 | J17: 0 | K17: Tower Shield | L17: Knight | M17: Buff (Defensive) | N17: Defence | O17: Self | P17: Single | Z17: FALSE | AA17: FALSE | AC17: 5b8c141b69b661a47b40f47336b737eb | AD17: =IF($AC17="","NEW","Live")
A18: Guardian's Aegis | B18: 2 | C18: Uncommon | D18: Shield 5 | G18: Give 5 Shield. | H18: SelfTile | I18: 0 | J18: 0 | K18: Guardian's Aegis | L18: Knight | M18: Buff (Defensive) | N18: Defence | O18: Self | P18: Manhattan 0-2 | Z18: TRUE | AA18: FALSE | AC18: 52e101b3e4c5baa4cb2771825ac229a6 | AD18: =IF($AC18="","NEW","Live")
A19: Hold the Line | B19: 2 | C19: Rare | D19: Shield 12 | E19: Draw 1 | G19: You and allies next to you gain 12 Shield. Draw 1. | H19: SelfTile | I19: 0 | J19: 0 | K19: Hold the Line | L19: Knight | M19: Buff (Defensive) | N19: Defence | O19: Self | P19: Chebyshev 0-1 | R19: Self | S19: Single | Z19: FALSE | AA19: FALSE | AC19: d787c8c8eae8ff54a9854dfdca322ce2 | AD19: =IF($AC19="","NEW","Live")
A20: Rally the Line | B20: 2 | C20: Rare | D20: Shield 6 | E20: Draw 1 | G20: Give 6 Shield to you and allies within 2. Draw 1. Costs 1 next to another hero. | H20: SelfTile | I20: 0 | J20: 0 | K20: Rally the Line | L20: Knight | M20: Buff (Defensive) | N20: Defence | O20: Self | P20: Manhattan 0-2 | R20: Self | S20: Single | X20: NextToHero -1 | Z20: FALSE | AA20: FALSE | AC20: 35d0762777460dd43b359e47bbb06133 | AD20: =IF($AC20="","NEW","Live")
A21: Strengthen | B21: 1 | C21: Uncommon | D21: Strength 3 | G21: Gain 3 Strength. | H21: SelfTile | I21: 0 | J21: 0 | K21: Strengthen | L21: Knight | M21: Buff (Offensive) | O21: Tile | P21: Single | Z21: FALSE | AA21: FALSE | AC21: b2d16f22e3045c1baf6d28e51c2f6005 | AD21: =IF($AC21="","NEW","Live")
A22: Buff | B22: 2 | C22: Uncommon | D22: Double Next Attack | G22: Double next attack. | H22: SelfTile | I22: 0 | J22: 0 | K22: Buff | L22: Knight | M22: Buff (Offensive) | O22: Tile | P22: Single | Z22: FALSE | AA22: FALSE | AC22: b2d16f22e3045c1baf6d28e51c2f6006 | AD22: =IF($AC22="","NEW","Live")
A23: Second Wind | B23: 1 | C23: Uncommon | D23: Heal 5 | G23: Heal 5 health. | H23: SelfTile | I23: 0 | J23: 0 | K23: Second Wind | L23: Knight | M23: Heal | O23: Self | P23: Single | Z23: TRUE | AA23: FALSE | AC23: 0a8d0a05e27667d45bd045dcca66021a | AD23: =IF($AC23="","NEW","Live")
A24: Attack and Block | B24: 1 | C24: Uncommon | D24: Damage 5 | E24: Shield 5 | G24: Deal 5 Damage. Gain 5 Shield. | H24: Chebyshev | I24: 1 | J24: 1 | K24: Attack and Block | L24: Knight | M24: Melee Attack | N24: Attack | O24: Tile | P24: Single | R24: Self | S24: Single | Z24: TRUE | AA24: FALSE | AC24: b2d16f22e3045c1baf6d28e51c2f6001 | AD24: =IF($AC24="","NEW","Live")
A25: Cleave | B25: 1 | C25: Uncommon | D25: Damage 5 | G25: Deal 5 Damage. | H25: Manhattan | I25: 1 | J25: 1 | K25: Cleave | L25: Knight | M25: Melee Attack | N25: Attack | O25: Tile | P25: Pattern:Wall3 | Z25: TRUE | AA25: FALSE | AC25: d7c02ed0dade07a49bec6cc971ee05ab | AD25: =IF($AC25="","NEW","Live")
A26: Covering Strike | B26: 1 | C26: Uncommon | D26: Damage 9 | E26: Shield 5 | G26: Deal 9 damage. Allies next to you gain 5 Shield. | H26: Chebyshev | I26: 1 | J26: 1 | K26: Covering Strike | L26: Knight | M26: Melee Attack | N26: Attack | O26: Tile | P26: Single | R26: Self | S26: Chebyshev 1-1 | Z26: FALSE | AA26: FALSE | AC26: 2fa98ecbf47e2584fbadf37aa1be5f83 | AD26: =IF($AC26="","NEW","Live")
A27: Flanking Strike | B27: 1 | C27: Uncommon | D27: Damage 7 | E27: Shield 4 | G27: Deal 7 damage and gain 4 Shield. Next to another hero: deal 11 instead. | H27: Chebyshev | I27: 1 | J27: 1 | K27: Flanking Strike | L27: Knight | M27: Melee Attack | N27: Attack | O27: Tile | P27: Single | Q27: NextToHero +4 | R27: Self | S27: Single | Z27: FALSE | AA27: FALSE | AC27: 6957f431a6921034f8b923e03a242560 | AD27: =IF($AC27="","NEW","Live")
A28: Shield Bash | B28: 1 | C28: Uncommon | D28: Damage 7 | E28: Shield 7 | G28: Deal 7 damage. Gain 7 Shield. | H28: Chebyshev | I28: 1 | J28: 1 | K28: Shield Bash | L28: Knight | M28: Melee Attack | N28: Attack | O28: Tile | P28: Single | R28: Self | S28: Single | Z28: FALSE | AA28: FALSE | AC28: ba1805b5798b8f94fa371b07bdfacf03 | AD28: =IF($AC28="","NEW","Live")
A29: Shield Slam | B29: 1 | C29: Uncommon | D29: Damage 6 | E29: Shield 3 | G29: Deal 6 damage. Gain 3 Shield. Costs 0 while you have Shield. | H29: Chebyshev | I29: 1 | J29: 1 | K29: Shield Slam | L29: Knight | M29: Melee Attack | N29: Attack | O29: Tile | P29: Single | R29: Self | S29: Single | X29: HasShield -1 | Z29: FALSE | AA29: FALSE | AC29: 27e580fcf17bea44b8b94cbb699b7ffe | AD29: =IF($AC29="","NEW","Live")
A30: Shield Strike | B30: 1 | C30: Uncommon | D30: Damage 8 | E30: Draw 1 | G30: Deal 8 damage. Draw 1. Costs 0 while you have Shield. | H30: Chebyshev | I30: 1 | J30: 1 | K30: Shield Strike | L30: Knight | M30: Melee Attack | N30: Attack | O30: Tile | P30: Single | R30: Self | S30: Single | X30: HasShield -1 | Z30: FALSE | AA30: FALSE | AC30: 8dc2760ad1ac66b4994206ef019984f1 | AD30: =IF($AC30="","NEW","Live")
A31: Slash | B31: 1 | C31: Common | D31: Damage 9 | G31: Deals 9 Damage. | H31: Chebyshev | I31: 1 | J31: 1 | K31: Slash | L31: Knight | M31: Melee Attack | N31: Attack | O31: Tile | P31: Single | Z31: TRUE | AA31: FALSE | AC31: d33a9e1db0e9c6e42a163a3bb49dbf0f | AD31: =IF($AC31="","NEW","Live")
A32: Slash+ | B32: 1 | C32: NotOffered | D32: Damage 9 | G32: Deals 3 more damage than Slash. | H32: Chebyshev | I32: 1 | J32: 1 | K32: Slash+ | L32: Knight | M32: Melee Attack | N32: Attack | O32: Tile | P32: Single | Z32: FALSE | AA32: FALSE | AC32: 35c23446db2a2fb42ab67f89753afdbd | AD32: =IF($AC32="","NEW","Live")
A33: Sunder | B33: 1 | C33: Uncommon | D33: Damage 5 | E33: Vulnerable | G33: Deal 5 damage and apply 2 Vulnerable. | H33: Chebyshev | I33: 1 | J33: 1 | K33: Sunder | L33: Knight | M33: Melee Attack | N33: Attack | O33: Tile | P33: Single | R33: Tile | S33: Single | Z33: FALSE | AA33: FALSE | AC33: 473565cf7c9a7a54aa013e0ffab0df43 | AD33: =IF($AC33="","NEW","Live")
A34: Sweeping Blow | B34: 1 | C34: Uncommon | D34: Damage 7 | G34: Deal 7 damage to a line of 3. | H34: Manhattan | I34: 1 | J34: 1 | K34: Sweeping Blow | L34: Knight | M34: Melee Attack | N34: Attack | O34: Tile | P34: Pattern:Wall3 | Z34: FALSE | AA34: FALSE | AC34: 4e721d4776e282b4c811351f74b2281c | AD34: =IF($AC34="","NEW","Live")
A35: Totem Strike | B35: 1 | C35: Uncommon | D35: Damage 12 | E35: Draw 1 | G35: Deal 12 damage. Draw 1. Costs 0 next to a totem. | H35: Chebyshev | I35: 1 | J35: 1 | K35: Totem Strike | L35: Knight | M35: Melee Attack | N35: Attack | O35: Tile | P35: Single | R35: Self | S35: Single | X35: NextToTotem -1 | Z35: FALSE | AA35: FALSE | AC35: 4c61f52b0abbe614ebdc2b6caaa6acb2 | AD35: =IF($AC35="","NEW","Live")
A36: Vanguard's Oath | B36: 1 | C36: Rare | D36: Damage 11 | E36: Draw 1 | G36: Deal 11 damage. Draw 1. Costs 0 next to another hero. | H36: Chebyshev | I36: 1 | J36: 1 | K36: Vanguard's Oath | L36: Knight | M36: Melee Attack | N36: Attack | O36: Tile | P36: Single | R36: Self | S36: Single | X36: NextToHero -1 | Z36: FALSE | AA36: FALSE | AC36: 0bb722efb6adb564ab0b0add2338b868 | AD36: =IF($AC36="","NEW","Live")
A37: Whirlwind | B37: 1 | C37: Rare | D37: Damage 4 | G37: Deal 4 damage. | H37: SelfTile | I37: 0 | J37: 0 | K37: Whirlwind | L37: Knight | M37: Melee Attack | N37: Attack | O37: Self | P37: Chebyshev 0-1 | Z37: FALSE | AA37: FALSE | AC37: 912403e15b047df44945f4d6e0a794b2 | AD37: =IF($AC37="","NEW","Live")
A38: Bloodmoon Totem | B38: 0 | C38: Rare | D38: SummonBloodmoonTotem | G38: Summon Bloodmoon Totem Everyone within 2: +3 damage | H38: Chebyshev | I38: 1 | J38: 3 | K38: Bloodmoon Totem | L38: Knight | M38: Summon | O38: Tile | P38: Single | Z38: FALSE | AA38: FALSE | AC38: 54a4b791120a2294695e570203d59aba | AD38: =IF($AC38="","NEW","Live")
A39: Thornwood Totem | B39: 1 | C39: Uncommon | D39: SummonThornwoodTotem | G39: Summon Thornwood Totem Enemies within 2: take 3 on attack | H39: Chebyshev | I39: 1 | J39: 3 | K39: Thornwood Totem | L39: Knight | M39: Summon | O39: Tile | P39: Single | Z39: FALSE | AA39: FALSE | AC39: 2c52f35d6eee792448391963fba6d347 | AD39: =IF($AC39="","NEW","Live")
A40: Whetstone Totem | B40: 1 | C40: Uncommon | D40: SummonWhetstoneTotem | G40: Summon Whetstone Totem Allies within 2: +3 damage | H40: Chebyshev | I40: 1 | J40: 3 | K40: Whetstone Totem | L40: Knight | M40: Summon | O40: Tile | P40: Single | Z40: FALSE | AA40: FALSE | AC40: 9214dd863c19d7245b675c8862560f40 | AD40: =IF($AC40="","NEW","Live")
A41: Anvil Totem | B41: 2 | C41: Uncommon | D41: SummonAnvilTotem | G41: Summon Anvil Totem Allies within 2: gain 2 Block each turn | H41: Chebyshev | I41: 1 | J41: 3 | K41: Anvil Totem | L41: Knight | M41: Summon | O41: Tile | P41: Single | Z41: FALSE | AA41: FALSE | AC41: 7a653fc08710faf448f81b2f5e947e9a | AD41: =IF($AC41="","NEW","Live")
A42: Fury Totem | B42: 2 | C42: Uncommon | D42: SummonFuryTotem | G42: Summon Fury Totem Allies within 2: +3 damage | H42: Chebyshev | I42: 1 | J42: 3 | K42: Fury Totem | L42: Knight | M42: Summon | O42: Tile | P42: Single | Z42: TRUE | AA42: FALSE | AC42: 9375eb26d7c7bda48a55a8b265cfe56d | AD42: =IF($AC42="","NEW","Live")
A43: Lodestone Totem | B43: 2 | C43: Rare | D43: SummonLodestoneTotem | G43: Summon Lodestone Totem Taunt Enemies within 3 | H43: Chebyshev | I43: 1 | J43: 3 | K43: Lodestone Totem | L43: Knight | M43: Summon | O43: Tile | P43: Single | Z43: FALSE | AA43: FALSE | AC43: 108f62860e4dc1e4686e2e4182941d7d | AD43: =IF($AC43="","NEW","Live")
A44: Momentum Totem | B44: 2 | C44: Uncommon | D44: SummonMomentumTotem | G44: Summon Momentum Totem Allies within 2: 1 Strength on move | H44: Chebyshev | I44: 1 | J44: 3 | K44: Momentum Totem | L44: Knight | M44: Summon | O44: Tile | P44: Single | Z44: TRUE | AA44: FALSE | AC44: 9dedc466c38c81542bf99a3695ddace4 | AD44: =IF($AC44="","NEW","Live")
A45: Rally Totem | B45: 2 | C45: Uncommon | D45: SummonRallyTotem | G45: Summon Rally Totem Allies within 2: gain 2 Strength each turn | H45: Chebyshev | I45: 1 | J45: 3 | K45: Rally Totem | L45: Knight | M45: Summon | O45: Tile | P45: Single | Z45: FALSE | AA45: FALSE | AC45: 0b63e560c22843d4ba7f2d333793b3dd | AD45: =IF($AC45="","NEW","Live")
A46: Shield Totem | B46: 2 | C46: Rare | D46: SummonTotem | G46: Summon Shield Totem Allies within 2: 3 Shield on attack | H46: Chebyshev | I46: 1 | J46: 1 | K46: Shield Totem | L46: Knight | M46: Summon | O46: Tile | P46: Single | Z46: FALSE | AA46: FALSE | AC46: aaaa1118bbbb2229cccc333adddd444b | AD46: =IF($AC46="","NEW","Live")
A47: Tower Totem | B47: 2 | C47: Uncommon | D47: SummonTowerTotem | G47: Summon Tower Totem Allies within 2: +3 to Shield gains | H47: Chebyshev | I47: 1 | J47: 3 | K47: Tower Totem | L47: Knight | M47: Summon | O47: Tile | P47: Single | Z47: FALSE | AA47: FALSE | AC47: 70e2ee5aa2fd4ba448e932a7ae09ed85 | AD47: =IF($AC47="","NEW","Live")
A48: Twin Totem | B48: 2 | C48: Rare | D48: SummonTwinTotem | G48: Summon Twin Totem Allies within 1: double damage | H48: Chebyshev | I48: 1 | J48: 3 | K48: Twin Totem | L48: Knight | M48: Summon | O48: Tile | P48: Single | Z48: FALSE | AA48: FALSE | AC48: 00e24cb4eff97034c9167a24ab3b79ab | AD48: =IF($AC48="","NEW","Live")
A49: Warhorn Totem | B49: 2 | C49: Rare | D49: SummonWarhornTotem | G49: Summon Warhorn Totem Allies within 2: draw on attack | H49: Chebyshev | I49: 1 | J49: 3 | K49: Warhorn Totem | L49: Knight | M49: Summon | O49: Tile | P49: Single | Z49: FALSE | AA49: FALSE | AC49: 1a50d076ef251394db344162cc42eb11 | AD49: =IF($AC49="","NEW","Live")
A50: Adrenaline | B50: 0 | C50: Rare | D50: Energy 1 | E50: Self Damage 5 | G50: Take 5 damage, gain 1 energy. | H50: SelfTile | I50: 0 | J50: 0 | K50: Adrenaline | L50: Knight | M50: Utility | O50: Self | P50: Single | R50: Self | S50: Single | Z50: FALSE | AA50: FALSE | AC50: f6f387ba8aa8eb145a52b1d3bb45bb51 | AD50: =IF($AC50="","NEW","Live")
A51: Bloodied Resolve | B51: 0 | C51: Rare | D51: Draw 1 | E51: Self Damage 5 | G51: Take 5 damage, draw 1 card. | H51: SelfTile | I51: 0 | J51: 0 | K51: Bloodied Resolve | L51: Knight | M51: Utility | O51: Self | P51: Single | R51: Self | S51: Single | Z51: FALSE | AA51: FALSE | AC51: e4cd35c82fe981840bee33089febaac7 | AD51: =IF($AC51="","NEW","Live")

Sheet Mage
A1: Card Name | B1: Cost | C1: Rarity | D1: Effect 1 | E1: Effect 2 | F1: Effect 3 | G1: Description | H1: Range Shape | I1: Range Min | J1: Range Max | K1: Key | L1: Class | M1: Folder | N1: Tags | O1: Aim 1 | P1: Area 1 | Q1: Cond 1 | R1: Aim 2 | S1: Area 2 | T1: Cond 2 | U1: Aim 3 | V1: Area 3 | W1: Cond 3 | X1: Cost Cond | Y1: Keywords | Z1: No Reward | AA1: Rotatable | AB1: Animation | AC1: GUID | AD1: Sync | AE1: Notes
A2: Dull Blade | B2: 1 | C2: Common | D2: Weaken | G2: Apply Weaken. | H2: Chebyshev | I2: 1 | J2: 4 | K2: Dull Blade | L2: Mage | M2: Debuff | N2: Defence | O2: Tile | P2: Single | Z2: FALSE | AA2: FALSE | AB2: Status | AC2: 5838b385efe02534993ebe2518d61ef3 | AD2: =IF($AC2="","NEW","Live")
A3: Entangle | B3: 1 | C3: Uncommon | D3: Root | G3: Root an Enemy. | H3: Chebyshev | I3: 1 | J3: 4 | K3: Entangle | L3: Mage | M3: Debuff | O3: Tile | P3: Single | Z3: FALSE | AA3: FALSE | AB3: Status | AC3: d628843c186f4896abd388b0e0fb081d | AD3: =IF($AC3="","NEW","Live")
A4: Freeze | B4: 1 | C4: Rare | D4: Freeze | G4: Freeze an Enemy. | H4: Chebyshev | I4: 1 | J4: 4 | K4: Freeze | L4: Mage | M4: Debuff | O4: Tile | P4: Single | Z4: FALSE | AA4: FALSE | AB4: Freeze | AC4: b660e3293e8b4225afcfe9a9a4be0f05 | AD4: =IF($AC4="","NEW","Live")
A5: Rust Armor | B5: 1 | C5: Common | D5: Vulnerable | G5: Apply Vulnerable. | H5: Chebyshev | I5: 1 | J5: 4 | K5: Rust Armor | L5: Mage | M5: Debuff | O5: Tile | P5: Single | Z5: FALSE | AA5: FALSE | AC5: d87d584eefa48da429cd46687b4066b4 | AD5: =IF($AC5="","NEW","Live")
A6: Sap Life | B6: 1 | C6: Common | D6: Damage 3 | E6: Heal 3 | G6: Deal 3 damage. Heal 3. | H6: Chebyshev | I6: 1 | J6: 4 | K6: Sap Life | L6: Mage | M6: Heal | N6: Attack, Healing | O6: Tile | P6: Single | R6: Self | S6: Single | Z6: TRUE | AA6: FALSE | AC6: 2f8157e447d75014091a50790b9cf520 | AD6: =IF($AC6="","NEW","Live")
A7: Teleport | B7: 1 | C7: Common | D7: Move | G7: Move to any tile on the board. | H7: Anywhere | I7: 0 | J7: 0 | K7: Teleport | L7: Mage | M7: Movement | N7: Movement | O7: Tile | P7: Single | Z7: FALSE | AA7: FALSE | AC7: aaf80d8da0ea4c228b87cbad0b9af242 | AD7: =IF($AC7="","NEW","Live")
A8: Fireball | B8: 1 | C8: Rare | D8: Damage 5 | G8: Deal 5 damage. | H8: Chebyshev | I8: 1 | J8: 4 | K8: Fireball | L8: Mage | M8: RangedAttack | N8: Fire, Attack | O8: Tile | P8: Chebyshev 0-1 | Z8: FALSE | AA8: FALSE | AC8: 576ab6616f9067d458e6811318815c6c | AD8: =IF($AC8="","NEW","Live")
A9: Firebolt | B9: 1 | C9: Common | D9: Damage 5 | G9: Deal 5 damage. | H9: Chebyshev | I9: 1 | J9: 5 | K9: Firebolt | L9: Mage | M9: RangedAttack | N9: Fire, Attack | O9: Tile | P9: Single | Z9: FALSE | AA9: FALSE | AB9: Fireball | AC9: 000c1f73e085eb64b8d858c64dfdfcda | AD9: =IF($AC9="","NEW","Live")
A10: Flame Cone | B10: 1 | C10: Rare | D10: Damage 4 | G10: Deal 4 damage. | H10: Chebyshev | I10: 1 | J10: 1 | K10: Flame Cone | L10: Mage | M10: RangedAttack | N10: Fire, Attack | O10: Tile | P10: Pattern:Cone3 | Z10: FALSE | AA10: FALSE | AC10: 93cab38da2c31ed409077c18f3807992 | AD10: =IF($AC10="","NEW","Live")
A11: Ice Shard | B11: 1 | C11: Rare | D11: Damage 5 | E11: Freeze | G11: Deals 3 damage and Freezes. | H11: Chebyshev | I11: 1 | J11: 4 | K11: Ice Shard | L11: Mage | M11: RangedAttack | N11: Attack | O11: Tile | P11: Single | R11: Tile | S11: Single | Z11: FALSE | AA11: FALSE | AC11: 36d01c973ac698e428120b185d709229 | AD11: =IF($AC11="","NEW","Live")
A12: X-Burner | B12: 1 | C12: Rare | D12: Damage 5 | G12: Deal 5 damage. | H12: Chebyshev | I12: 1 | J12: 4 | K12: X-Burner | L12: Mage | M12: RangedAttack | N12: Fire, Attack | O12: Tile | P12: Pattern:X-Pattern | Z12: FALSE | AA12: FALSE | AC12: c8319799a424c03478428ce8d28e8e92 | AD12: =IF($AC12="","NEW","Live")
A13: Chaos Totem | B13: 1 | C13: Rare | D13: SummonChaosTotem | G13: Summon Chaos Totem Everyone within 2: take 3 more damage | H13: Chebyshev | I13: 1 | J13: 3 | K13: Chaos Totem | L13: Mage | M13: Summon | O13: Tile | P13: Single | Z13: FALSE | AA13: FALSE | AC13: be9e8db880616e449b7b9cb36178fba1 | AD13: =IF($AC13="","NEW","Live")
A14: Binding Totem | B14: 2 | C14: Uncommon | D14: SummonBindingTotem | G14: Summon Binding Totem Enemies within 2: double Rooted | H14: Chebyshev | I14: 1 | J14: 3 | K14: Binding Totem | L14: Mage | M14: Summon | O14: Tile | P14: Single | Z14: FALSE | AA14: FALSE | AC14: deb322298a9674d469f81de9d4774b0e | AD14: =IF($AC14="","NEW","Live")
A15: Conduit Totem | B15: 2 | C15: Uncommon | D15: SummonConduitTotem | G15: Summon Conduit Totem Allies within 2: draw on applying a status | H15: Chebyshev | I15: 1 | J15: 3 | K15: Conduit Totem | L15: Mage | M15: Summon | O15: Tile | P15: Single | Z15: FALSE | AA15: FALSE | AC15: 7a62a8d9fb25c9a4f8e9fb484cdfa9ff | AD15: =IF($AC15="","NEW","Live")
A16: Curse Totem | B16: 2 | C16: Rare | D16: SummonCurseTotem | G16: Summon Curse Totem Enemies within 2: double Vulnerable | H16: Chebyshev | I16: 1 | J16: 3 | K16: Curse Totem | L16: Mage | M16: Summon | O16: Tile | P16: Single | Z16: FALSE | AA16: FALSE | AC16: f00124f8df6b1c5469473a59ffe0b357 | AD16: =IF($AC16="","NEW","Live")
A17: Enfeeble Totem | B17: 2 | C17: Uncommon | D17: SummonEnfeebleTotem | G17: Summon Enfeeble Totem Enemies within 2: Weaken +3 stronger | H17: Chebyshev | I17: 1 | J17: 3 | K17: Enfeeble Totem | L17: Mage | M17: Summon | O17: Tile | P17: Single | Z17: FALSE | AA17: FALSE | AC17: a34ba9577dc8af24bb92fb81ee235a5d | AD17: =IF($AC17="","NEW","Live")
A18: Fracture Totem | B18: 2 | C18: Uncommon | D18: SummonFractureTotem | G18: Summon Fracture Totem Enemies within 2: take 3 more damage | H18: Chebyshev | I18: 1 | J18: 3 | K18: Fracture Totem | L18: Mage | M18: Summon | O18: Tile | P18: Single | Z18: FALSE | AA18: FALSE | AC18: 234fcf8ff9522344d9d5ee1022be130f | AD18: =IF($AC18="","NEW","Live")
A19: Hex Totem | B19: 2 | C19: Rare | D19: SummonHexTotem | G19: Summon Hex Totem Enemies within 2: double Weaken | H19: Chebyshev | I19: 1 | J19: 3 | K19: Hex Totem | L19: Mage | M19: Summon | O19: Tile | P19: Single | Z19: FALSE | AA19: FALSE | AC19: e5cd6de7d5df0fc44a67a6d1554ac7f4 | AD19: =IF($AC19="","NEW","Live")
A20: Ruin Totem | B20: 2 | C20: Uncommon | D20: SummonRuinTotem | G20: Summon Ruin Totem Enemies within 2: Vulnerable +3 stronger | H20: Chebyshev | I20: 1 | J20: 3 | K20: Ruin Totem | L20: Mage | M20: Summon | O20: Tile | P20: Single | Z20: FALSE | AA20: FALSE | AC20: e76eca70192ea0342abb35761afe55cf | AD20: =IF($AC20="","NEW","Live")
A21: Sap Totem | B21: 2 | C21: Uncommon | D21: SummonSapTotem | G21: Summon Sap Totem Enemies within 2: deal 3 less damage | H21: Chebyshev | I21: 1 | J21: 3 | K21: Sap Totem | L21: Mage | M21: Summon | O21: Tile | P21: Single | Z21: FALSE | AA21: FALSE | AC21: 8b23e21878068f84ca903b21df587219 | AD21: =IF($AC21="","NEW","Live")
A22: Scholar Totem | B22: 2 | C22: Uncommon | D22: SummonScholarTotem | G22: Summon Scholar Totem Allies within 2: +1 energy on draw | H22: Chebyshev | I22: 1 | J22: 3 | K22: Scholar Totem | L22: Mage | M22: Summon | O22: Tile | P22: Single | Z22: FALSE | AA22: FALSE | AC22: a6bec62ba7837e44ca5fe7aac759f0fb | AD22: =IF($AC22="","NEW","Live")
A23: Shackle Totem | B23: 2 | C23: Uncommon | D23: SummonShackleTotem | G23: Summon Shackle Totem Enemies within 2: Rooted each turn | H23: Chebyshev | I23: 1 | J23: 3 | K23: Shackle Totem | L23: Mage | M23: Summon | O23: Tile | P23: Single | Z23: FALSE | AA23: FALSE | AC23: 51c470e5e0a71854fbe33c2a8ac2db09 | AD23: =IF($AC23="","NEW","Live")
A24: Draw Totem | B24: 2 | C24: Uncommon | D24: SummonDrawTotem | G24: Summon Draw Totem Allies within 2: draw on dealing damage | H24: Chebyshev | I24: 1 | J24: 3 | K24: SummonDrawTotem | L24: Mage | M24: Summon | O24: Tile | P24: Single | Z24: FALSE | AA24: FALSE | AC24: 099a2eb5aca856a4d9a8ff396dc45e20 | AD24: =IF($AC24="","NEW","Live")
A25: Wall of Flames | B25: 2 | C25: Rare | D25: Wall of Flames | G25: Create a Wall of Flames, anything standing ontop will take 4 damage. | H25: Chebyshev | I25: 1 | J25: 3 | K25: WallOfFlames | L25: Mage | M25: Summon | N25: Fire | O25: Tile | P25: Pattern:Wall3 | Z25: FALSE | AA25: TRUE | AC25: a68a20cc6a62a794884b25eda9e5a871 | AD25: =IF($AC25="","NEW","Live")
A26: Wall of Force | B26: 2 | C26: Rare | D26: Push | E26: Wall of Force | G26: Create a Wall of Force, stopping all movement through that area. | H26: Chebyshev | I26: 1 | J26: 3 | K26: WallOfForce | L26: Mage | M26: Summon | N26: Defence | O26: Tile | P26: Pattern:Wall3 | R26: Tile | S26: Pattern:Wall3 | Z26: FALSE | AA26: TRUE | AC26: 317ae1a15cf5e44499040e5816fc71aa | AD26: =IF($AC26="","NEW","Live")
A27: Foresight | B27: 0 | C27: Uncommon | D27: Draw 1 | E27: Discard 1 | G27: Draw a card, then discard a card. | H27: SelfTile | I27: 0 | J27: 0 | K27: Foresight | L27: Mage | M27: Utility | O27: Self | P27: Single | R27: Self | S27: Single | Z27: FALSE | AA27: FALSE | AC27: df9e3bce91e2cd14681ef8aa00618104 | AD27: =IF($AC27="","NEW","Live")

Sheet Rogue
A1: Card Name | B1: Cost | C1: Rarity | D1: Effect 1 | E1: Effect 2 | F1: Effect 3 | G1: Description | H1: Range Shape | I1: Range Min | J1: Range Max | K1: Key | L1: Class | M1: Folder | N1: Tags | O1: Aim 1 | P1: Area 1 | Q1: Cond 1 | R1: Aim 2 | S1: Area 2 | T1: Cond 2 | U1: Aim 3 | V1: Area 3 | W1: Cond 3 | X1: Cost Cond | Y1: Keywords | Z1: No Reward | AA1: Rotatable | AB1: Animation | AC1: GUID | AD1: Sync | AE1: Notes
A2: Dodge | B2: 1 | C2: Uncommon | D2: Dodge | G2: Gain 1 stack of Dodge. | H2: SelfTile | I2: 0 | J2: 0 | K2: Dodge | L2: Rogue | M2: Buff (Defensive) | N2: Defence, Movement | O2: Tile | P2: Single | Z2: FALSE | AA2: FALSE | AC2: 1eea8f6c4d1062d4f9a550078d14e259 | AD2: =IF($AC2="","NEW","Live")
A3: Evasion | B3: 1 | C3: Uncommon | D3: Block 2 | G3: Gain 2 stacks of Block. | H3: SelfTile | I3: 0 | J3: 0 | K3: Evasion | L3: Rogue | M3: Buff (Defensive) | N3: Defence | O3: Self | P3: Single | Z3: FALSE | AA3: FALSE | AC3: ea4ea121456773f47b2377471122e93e | AD3: =IF($AC3="","NEW","Live")
A4: Stealth | B4: 1 | C4: Rare | D4: Stealth 2 | G4: For 2 turns, enemies cannot target you. | H4: SelfTile | I4: 0 | J4: 0 | K4: Stealth | L4: Rogue | M4: Buff (Defensive) | N4: Defence | O4: Self | P4: Single | Z4: FALSE | AA4: FALSE | AC4: 3fb463a3a81ff074ab5a518311ca75e2 | AD4: =IF($AC4="","NEW","Live")
A5: Leeching Blade | B5: 1 | C5: Common | D5: Lifesteal 3 | G5: For 3 turns, your attacks heal you for half the damage dealt. | H5: SelfTile | I5: 0 | J5: 0 | K5: Leeching Blade | L5: Rogue | M5: Buff (Offensive) | N5: Attack, Healing | O5: Self | P5: Single | Z5: TRUE | AA5: FALSE | AC5: 56e43cd12f2be6d468cf6827daaed8bb | AD5: =IF($AC5="","NEW","Live")
A6: Poison Blade | B6: 1 | C6: Uncommon | D6: Poison Blade 3 | G6: For 3 turns, your attacks apply 1 Poison. | H6: SelfTile | I6: 0 | J6: 0 | K6: Poison Blade | L6: Rogue | M6: Buff (Offensive) | N6: Attack, Poison | O6: Self | P6: Single | Z6: FALSE | AA6: FALSE | AC6: 8a487f54103a58548956028d93692641 | AD6: =IF($AC6="","NEW","Live")
A7: Panache | B7: 1 | C7: Uncommon | D7: Weaken 2 | G7: Apply 3 stacks of Weaken. | H7: Chebyshev | I7: 1 | J7: 4 | K7: Panache | L7: Rogue | M7: Debuff | O7: Tile | P7: Single | Z7: FALSE | AA7: FALSE | AC7: 4ead4a101ac64ee4a8dbc0d5917ad849 | AD7: =IF($AC7="","NEW","Live")
A8: Quick Attack | B8: 0 | C8: Uncommon | D8: Damage 3 | G8: Deal 3 damage. | H8: Chebyshev | I8: 1 | J8: 1 | K8: Quick Attack | L8: Rogue | M8: Melee Attack | N8: Attack | O8: Tile | P8: Single | Z8: FALSE | AA8: FALSE | AC8: b2d16f22e3045c1baf6d28e51c2f6002 | AD8: =IF($AC8="","NEW","Live")
A9: Poison Dagger | B9: 1 | C9: Uncommon | D9: Damage 4 | E9: Poison 3 | G9: Deal 4 damage and apply 3 Poison. | H9: Chebyshev | I9: 1 | J9: 1 | K9: Poison Dagger | L9: Any | M9: Melee Attack | N9: Attack | O9: Tile | P9: Single | R9: Tile | S9: Single | Z9: FALSE | AA9: FALSE | AC9: 4b1d872acef079b4b9803f32615146d9 | AD9: =IF($AC9="","NEW","Live")
A10: Shambles | B10: 1 | C10: Rare | D10: Swap | G10: Swap places with any character within 3 tiles. | H10: Chebyshev | I10: 1 | J10: 3 | K10: Shambles | L10: Rogue | M10: Movement | N10: Movement | O10: Tile | P10: Single | Z10: FALSE | AA10: FALSE | AC10: ab457316daf03a740aac2696a6bb616b | AD10: =IF($AC10="","NEW","Live")
A11: Poison Dart | B11: 1 | C11: Common | D11: Poison 4 | G11: Apply 4 stacks of Poison. | H11: Chebyshev | I11: 1 | J11: 4 | K11: Poison Dart | L11: Rogue | M11: RangedAttack | O11: Tile | P11: Single | Z11: FALSE | AA11: FALSE | AC11: 0e3798dd733944d180801d6f2263b739 | AD11: =IF($AC11="","NEW","Live")
A12: Decoy Totem | B12: 1 | C12: Uncommon | D12: SummonDecoyTotem | G12: Summon Decoy Totem Taunt Enemies within 3 | H12: Chebyshev | I12: 1 | J12: 3 | K12: Decoy Totem | L12: Rogue | M12: Summon | O12: Tile | P12: Single | Z12: FALSE | AA12: FALSE | AC12: c08631cd0fb101e42a5d73dbd887945a | AD12: =IF($AC12="","NEW","Live")
A13: Contagion Totem | B13: 2 | C13: Uncommon | D13: SummonContagionTotem | G13: Summon Contagion Totem Enemies within 2: double Poison | H13: Chebyshev | I13: 1 | J13: 3 | K13: Contagion Totem | L13: Rogue | M13: Summon | O13: Tile | P13: Single | Z13: FALSE | AA13: FALSE | AC13: 302ebe6cf5deadf468117453ebf7f0d5 | AD13: =IF($AC13="","NEW","Live")
A14: Fortune Totem | B14: 2 | C14: Uncommon | D14: SummonFortuneTotem | G14: Summon Fortune Totem Allies within 2: double Dodge | H14: Chebyshev | I14: 1 | J14: 3 | K14: Fortune Totem | L14: Rogue | M14: Summon | O14: Tile | P14: Single | Z14: FALSE | AA14: FALSE | AC14: 79fb1797bac377241be137dd9d4684cb | AD14: =IF($AC14="","NEW","Live")
A15: Ghoststep Totem | B15: 2 | C15: Uncommon | D15: SummonGhoststepTotem | G15: Summon Ghoststep Totem Allies within 2: gain 1 Dodge each turn | H15: Chebyshev | I15: 1 | J15: 3 | K15: Ghoststep Totem | L15: Rogue | M15: Summon | O15: Tile | P15: Single | Z15: FALSE | AA15: FALSE | AC15: 887c9ea2036e9fa4caafd48965354572 | AD15: =IF($AC15="","NEW","Live")
A16: Leech Totem | B16: 2 | C16: Uncommon | D16: SummonLeechTotem | G16: Summon Leech Totem Allies within 2: heal half damage dealt | H16: Chebyshev | I16: 1 | J16: 3 | K16: Leech Totem | L16: Rogue | M16: Summon | O16: Tile | P16: Single | Z16: FALSE | AA16: FALSE | AC16: 2d814aeedc0b89f4eb207904f83abdf3 | AD16: =IF($AC16="","NEW","Live")
A17: Rot Totem | B17: 2 | C17: Rare | D17: SummonRotTotem | G17: Summon Rot Totem Enemies within 2: gain 4 Poison each turn | H17: Chebyshev | I17: 1 | J17: 3 | K17: Rot Totem | L17: Rogue | M17: Summon | O17: Tile | P17: Single | Z17: FALSE | AA17: FALSE | AC17: 41c8eeed77695c5478e63466cb1992a3 | AD17: =IF($AC17="","NEW","Live")
A18: Spike Totem | B18: 2 | C18: Uncommon | D18: SummonSpikeTotem | G18: Summon Spike Totem Enemies within 2: take 2 on move | H18: Chebyshev | I18: 1 | J18: 3 | K18: Spike Totem | L18: Rogue | M18: Summon | O18: Tile | P18: Single | Z18: FALSE | AA18: FALSE | AC18: 81681948dc874bd4c9ea08e8e8adafb1 | AD18: =IF($AC18="","NEW","Live")
A19: Veil Totem | B19: 2 | C19: Uncommon | D19: SummonVeilTotem | G19: Summon Veil Totem Allies within 2: can't be targeted | H19: Chebyshev | I19: 1 | J19: 3 | K19: Veil Totem | L19: Rogue | M19: Summon | O19: Tile | P19: Single | Z19: FALSE | AA19: FALSE | AC19: c0769be3baf84ac4196889f3113de54a | AD19: =IF($AC19="","NEW","Live")
A20: Venom Totem | B20: 2 | C20: Rare | D20: SummonVenomTotem | G20: Summon Venom Totem Enemies within 2: gain 2 Poison each turn | H20: Chebyshev | I20: 1 | J20: 3 | K20: Venom Totem | L20: Rogue | M20: Summon | N20: Summon, Poison | O20: Tile | P20: Single | Z20: FALSE | AA20: FALSE | AC20: 139ccd0500259c4429836b43f9a7145a | AD20: =IF($AC20="","NEW","Live")
A21: Venomblade Totem | B21: 2 | C21: Uncommon | D21: SummonVenombladeTotem | G21: Summon Venomblade Totem Allies within 2: hits apply 1 Poison | H21: Chebyshev | I21: 1 | J21: 3 | K21: Venomblade Totem | L21: Rogue | M21: Summon | O21: Tile | P21: Single | Z21: FALSE | AA21: FALSE | AC21: cc7ab5e114f35204796b0438e7e5625f | AD21: =IF($AC21="","NEW","Live")

Sheet Cleric
A1: Card Name | B1: Cost | C1: Rarity | D1: Effect 1 | E1: Effect 2 | F1: Effect 3 | G1: Description | H1: Range Shape | I1: Range Min | J1: Range Max | K1: Key | L1: Class | M1: Folder | N1: Tags | O1: Aim 1 | P1: Area 1 | Q1: Cond 1 | R1: Aim 2 | S1: Area 2 | T1: Cond 2 | U1: Aim 3 | V1: Area 3 | W1: Cond 3 | X1: Cost Cond | Y1: Keywords | Z1: No Reward | AA1: Rotatable | AB1: Animation | AC1: GUID | AD1: Sync | AE1: Notes
A2: Blade Ward | B2: 1 | C2: Uncommon | D2: Block 1 | G2: Give Block. | H2: Chebyshev | I2: 0 | J2: 4 | K2: Blade Ward | L2: Cleric | M2: Buff (Defensive) | N2: Defence | O2: Tile | P2: Single | Z2: TRUE | AA2: FALSE | AC2: 0313f5e3f95e9704d8ddff8d29ecefcd | AD2: =IF($AC2="","NEW","Live")
A3: Blessed Shield | B3: 1 | C3: Uncommon | D3: Shield 10 | G3: Give 10 Shield. | H3: Chebyshev | I3: 0 | J3: 4 | K3: Blessed Shield | L3: Cleric | M3: Buff (Defensive) | N3: Defence | O3: Tile | P3: Single | Z3: FALSE | AA3: FALSE | AC3: 175eddf5ef5df5a4ea59b73185ae3cc3 | AD3: =IF($AC3="","NEW","Live")
A4: Distant Grace | B4: 1 | C4: Uncommon | D4: Shield 6 | G4: Give 6 Shield. Alone: give 10 instead. | H4: Chebyshev | I4: 0 | J4: 4 | K4: Distant Grace | L4: Cleric | M4: Buff (Defensive) | N4: Healing | O4: Tile | P4: Single | Q4: Alone +4 | Z4: FALSE | AA4: FALSE | AC4: 04b40add9afb299408a7ee93bfe48bb0 | AD4: =IF($AC4="","NEW","Live")
A5: Shield of Faith | B5: 1 | C5: Uncommon | D5: Shield 5 | E5: Draw 1 | G5: Give 5 Shield. Next to another hero: give 9 and draw 1. | H5: Chebyshev | I5: 0 | J5: 4 | K5: Shield of Faith | L5: Cleric | M5: Buff (Defensive) | N5: Healing | O5: Tile | P5: Single | Q5: NextToHero +4 | R5: Self | S5: Single | T5: NextToHero only | Z5: FALSE | AA5: FALSE | AC5: 74b79ec5f4457e241a83817f4432ff38 | AD5: =IF($AC5="","NEW","Live")
A6: Shrine Blessing | B6: 1 | C6: Uncommon | D6: Shield 9 | E6: Draw 1 | G6: Give 9 Shield. Draw 1. Costs 0 next to a totem. | H6: Chebyshev | I6: 0 | J6: 4 | K6: Shrine Blessing | L6: Cleric | M6: Buff (Defensive) | N6: Defence | O6: Tile | P6: Single | R6: Self | S6: Single | X6: NextToTotem -1 | Z6: FALSE | AA6: FALSE | AC6: a0b3386d15333644380841641a66851f | AD6: =IF($AC6="","NEW","Live")
A7: Ward Blessing | B7: 1 | C7: Uncommon | D7: Shield 5 | G7: Give 5 Shield. Costs 0 next to another hero. | H7: Chebyshev | I7: 0 | J7: 4 | K7: Ward Blessing | L7: Cleric | M7: Buff (Defensive) | N7: Defence | O7: Tile | P7: Single | X7: NextToHero -1 | Z7: FALSE | AA7: FALSE | AC7: 08b2151905b6ded4990637ecbe601221 | AD7: =IF($AC7="","NEW","Live")
A8: Vengeful Vigor | B8: 1 | C8: Uncommon | D8: Lifesteal 1 | G8: Apply Lifesteal 1. | H8: Chebyshev | I8: 0 | J8: 4 | K8: Vengeful Vigor | L8: Cleric | M8: Buff (Offensive) | O8: Tile | P8: Single | Z8: TRUE | AA8: FALSE | AC8: 03b73a23f7ceebf41b9dc0773a7935bc | AD8: =IF($AC8="","NEW","Live")
A9: Purge | B9: 1 | C9: Uncommon | D9: Purge Poison | G9: Remove all Poison from an ally and afflict the nearest enemy with it. | H9: Chebyshev | I9: 1 | J9: 4 | K9: Purge | L9: Cleric | M9: Debuff | O9: Tile | P9: Single | Z9: TRUE | AA9: FALSE | AC9: 0aca4faf7138a9c4db512e6cf3962233 | AD9: =IF($AC9="","NEW","Live")
A10: Benediction | B10: 1 | C10: Uncommon | D10: Heal 4 | E10: Draw 1 | G10: Heal 4 to an ally and every ally next to them. Draw 1. | H10: Chebyshev | I10: 0 | J10: 4 | K10: Benediction | L10: Cleric | M10: Heal | N10: Healing | O10: Tile | P10: Chebyshev 0-1 | R10: Self | S10: Single | Z10: FALSE | AA10: FALSE | AC10: 5fed507f2b9412840b17c166844be387 | AD10: =IF($AC10="","NEW","Live")
A11: Cleansing Light | B11: 1 | C11: Common | D11: Cleanse Curses Heal | G11: Remove all negative effects from an ally and heal them for the stacks removed. | H11: Chebyshev | I11: 0 | J11: 4 | K11: Cleansing Light | L11: Cleric | M11: Heal | O11: Tile | P11: Single | Z11: TRUE | AA11: FALSE | AC11: 09e3ae3a175a86a44b79648130db2fbf | AD11: =IF($AC11="","NEW","Live")
A12: Close Prayer | B12: 1 | C12: Uncommon | D12: Heal 7 | E12: Draw 1 | G12: Heal 7. Next to another hero: draw 1. | H12: Chebyshev | I12: 0 | J12: 4 | K12: Close Prayer | L12: Cleric | M12: Heal | N12: Healing | O12: Tile | P12: Single | R12: Self | S12: Single | T12: NextToHero only | Z12: FALSE | AA12: FALSE | AC12: 4797ff6a48d6489488f7baf2ce20d159 | AD12: =IF($AC12="","NEW","Live")
A13: Touch Heal | B13: 1 | C13: Uncommon | D13: Heal 10 | G13: Heal 10. | H13: Chebyshev | I13: 0 | J13: 4 | K13: Cure Wounds | L13: Cleric | M13: Heal | N13: Healing | O13: Tile | P13: Single | Z13: FALSE | AA13: FALSE | AC13: b2d16f22e3045c1baf6d28e51c2f6004 | AD13: =IF($AC13="","NEW","Live")
A14: Far Mend | B14: 1 | C14: Uncommon | D14: Heal 7 | E14: Draw 1 | G14: Heal 7. Alone: draw 1. | H14: Chebyshev | I14: 0 | J14: 4 | K14: Far Mend | L14: Cleric | M14: Heal | N14: Healing | O14: Tile | P14: Single | R14: Self | S14: Single | T14: Alone only | Z14: FALSE | AA14: FALSE | AC14: 023721848dd82404c87b4d52af1cab73 | AD14: =IF($AC14="","NEW","Live")
A15: Guiding Smite | B15: 1 | C15: Uncommon | D15: Damage 7 | E15: Heal 4 | G15: Deal 7 damage. You and allies next to you heal 4. | H15: Chebyshev | I15: 1 | J15: 4 | K15: Guiding Smite | L15: Cleric | M15: Heal | N15: Attack | O15: Tile | P15: Single | R15: Self | S15: Chebyshev 0-1 | Z15: FALSE | AA15: FALSE | AC15: 532778b466b668342b2043a76e5820d8 | AD15: =IF($AC15="","NEW","Live")
A16: Heal Word | B16: 1 | C16: Common | D16: Heal 5 | G16: Heal 5. | H16: Chebyshev | I16: 0 | J16: 4 | K16: Heal Word | L16: Cleric | M16: Heal | N16: Healing | O16: Tile | P16: Single | Z16: TRUE | AA16: FALSE | AC16: b0de35f4e0b135845b19e60120fd3205 | AD16: =IF($AC16="","NEW","Live")
A17: Hermit's Smite | B17: 1 | C17: Uncommon | D17: Damage 8 | E17: Heal 3 | G17: Deal 8 damage. Heal 3. Alone: deal 12 instead. | H17: Chebyshev | I17: 1 | J17: 4 | K17: Hermit's Smite | L17: Cleric | M17: Heal | N17: Attack | O17: Tile | P17: Single | Q17: Alone +4 | R17: Self | S17: Single | Z17: FALSE | AA17: FALSE | AC17: f484fb35bb9babc4b9415b6cbbbb5c56 | AD17: =IF($AC17="","NEW","Live")
A18: Holy Smite | B18: 1 | C18: Uncommon | D18: Damage 8 | E18: Heal 4 | G18: Deal 8 damage. Heal 4. | H18: Chebyshev | I18: 1 | J18: 4 | K18: Holy Smite | L18: Cleric | M18: Heal | N18: Attack | O18: Tile | P18: Single | R18: Self | S18: Single | Z18: FALSE | AA18: FALSE | AC18: b6b5763536cee8440bf2d3606de913c4 | AD18: =IF($AC18="","NEW","Live")
A19: Judgement | B19: 1 | C19: Rare | D19: Damage 9 | E19: Draw 1 | G19: Deal 9 damage. Alone: costs 0 and draw 1. | H19: Chebyshev | I19: 1 | J19: 4 | K19: Judgement | L19: Cleric | M19: Heal | N19: Attack | O19: Tile | P19: Single | R19: Self | S19: Single | T19: Alone only | X19: Alone -1 | Z19: FALSE | AA19: FALSE | AC19: abaddd2655a840e449884c0c3bbed34a | AD19: =IF($AC19="","NEW","Live")
A20: Lasting Renewal | B20: 1 | C20: Uncommon | D20: Regeneration 4 | G20: Apply Regeneration 4. | H20: Chebyshev | I20: 0 | J20: 4 | K20: Lasting Renewal | L20: Cleric | M20: Heal | O20: Tile | P20: Single | Z20: FALSE | AA20: FALSE | AC20: 37bf83cfbd3d9bd438346a067e59a00c | AD20: =IF($AC20="","NEW","Live")
A21: Laying on of Hands | B21: 1 | C21: Uncommon | D21: Heal 7 | G21: Heal 7 to you and allies next to you. | H21: SelfTile | I21: 0 | J21: 0 | K21: Laying on of Hands | L21: Cleric | M21: Heal | N21: Healing | O21: Self | P21: Chebyshev 0-1 | Z21: FALSE | AA21: FALSE | AC21: 19032b9f33d0ce24bbca258b3ad9dbff | AD21: =IF($AC21="","NEW","Live")
A22: Mending Light | B22: 1 | C22: Uncommon | D22: Heal 4 | G22: Heal 4. Costs 0 next to another hero. | H22: Chebyshev | I22: 0 | J22: 4 | K22: Mending Light | L22: Cleric | M22: Heal | N22: Healing | O22: Tile | P22: Single | X22: NextToHero -1 | Z22: FALSE | AA22: FALSE | AC22: b366fea67432b594c8ec7e726e7152c8 | AD22: =IF($AC22="","NEW","Live")
A23: Prayer Circle | B23: 1 | C23: Uncommon | D23: Heal 5 | E23: Draw 1 | G23: Heal 5. Draw 1. Costs 0 next to another hero. | H23: Chebyshev | I23: 0 | J23: 4 | K23: Prayer Circle | L23: Cleric | M23: Heal | N23: Healing | O23: Tile | P23: Single | R23: Self | S23: Single | X23: NextToHero -1 | Z23: FALSE | AA23: FALSE | AC23: 593c12d96b73d764ea78f7c8bfb89d5d | AD23: =IF($AC23="","NEW","Live")
A24: Radiant Smite | B24: 1 | C24: Uncommon | D24: Damage 6 | E24: Heal 3 | F24: Draw 1 | G24: Deal 6 damage. Heal 3. Draw 1. Costs 0 while you have Shield. | H24: Chebyshev | I24: 1 | J24: 4 | K24: Radiant Smite | L24: Cleric | M24: Heal | N24: Attack | O24: Tile | P24: Single | R24: Self | S24: Single | U24: Self | V24: Single | X24: HasShield -1 | Z24: FALSE | AA24: FALSE | AC24: d87b16954bfa4774da47f6848afc3e36 | AD24: =IF($AC24="","NEW","Live")
A25: Rejuvenate | B25: 1 | C25: Uncommon | D25: Heal 6 | E25: Draw 1 | G25: Heal 6 and draw a card. | H25: Chebyshev | I25: 0 | J25: 4 | K25: Rejuvenate | L25: Cleric | M25: Heal | O25: Tile | P25: Single | R25: Self | S25: Single | Z25: FALSE | AA25: FALSE | AC25: 2cee7221146827246960b805f60da04d | AD25: =IF($AC25="","NEW","Live")
A26: Renew | B26: 1 | C26: Common | D26: Heal 3 | E26: Draw 1 | G26: Heal 3 and draw a card. | H26: Chebyshev | I26: 0 | J26: 4 | K26: Renew | L26: Cleric | M26: Heal | O26: Tile | P26: Single | R26: Tile | S26: Single | Z26: TRUE | AA26: FALSE | AC26: 940d27453c9c1924499110bc2380e444 | AD26: =IF($AC26="","NEW","Live")
A27: Sanctified Ground | B27: 1 | C27: Rare | D27: Shield 5 | E27: Heal 5 | G27: You and allies next to you gain 5 Shield and heal 5. | H27: SelfTile | I27: 0 | J27: 0 | K27: Sanctified Ground | L27: Cleric | M27: Heal | N27: Healing | O27: Self | P27: Chebyshev 0-1 | R27: Self | S27: Chebyshev 0-1 | Z27: FALSE | AA27: FALSE | AC27: aa90828795c6e6542ac261a74bf024ef | AD27: =IF($AC27="","NEW","Live")
A28: Sanctified Guard | B28: 1 | C28: Uncommon | D28: Heal 5 | E28: Block 1 | G28: Heal 5 and give Block. | H28: Chebyshev | I28: 0 | J28: 4 | K28: Sanctified Guard | L28: Cleric | M28: Heal | O28: Tile | P28: Single | R28: Tile | S28: Single | Z28: FALSE | AA28: FALSE | AC28: 1bb8e3ea252264347bbaeb4b919b5c31 | AD28: =IF($AC28="","NEW","Live")
A29: Smite | B29: 1 | C29: Common | D29: Heal 6 | E29: Heal 3 | G29: Deal 4 damage. Heal 3. | H29: Chebyshev | I29: 1 | J29: 4 | K29: Smite | L29: Cleric | M29: Heal | N29: Attack | O29: Tile | P29: Single | R29: Self | S29: Single | Z29: TRUE | AA29: FALSE | AC29: 96e73bab6c061cd49bf0c98a367e781e | AD29: =IF($AC29="","NEW","Live")
A30: Smite Together | B30: 1 | C30: Uncommon | D30: Damage 7 | E30: Heal 3 | G30: Deal 7 damage. Heal 3. Next to another hero: deal 10 instead. | H30: Chebyshev | I30: 1 | J30: 4 | K30: Smite Together | L30: Cleric | M30: Heal | N30: Attack | O30: Tile | P30: Single | Q30: NextToHero +3 | R30: Self | S30: Single | Z30: FALSE | AA30: FALSE | AC30: 3cf49416bcf904842a9f37f5af23af03 | AD30: =IF($AC30="","NEW","Live")
A31: Communion | B31: 2 | C31: Rare | D31: Heal 5 | E31: Draw 1 | G31: Heal 5 to you and allies within 2. Draw 1. Costs 1 next to another hero. | H31: SelfTile | I31: 0 | J31: 0 | K31: Communion | L31: Cleric | M31: Heal | N31: Defence | O31: Self | P31: Manhattan 0-2 | R31: Self | S31: Single | X31: NextToHero -1 | Z31: FALSE | AA31: FALSE | AC31: ccc6b83e3e58748438b980a73eac90bf | AD31: =IF($AC31="","NEW","Live")
A32: Mend and Fortify | B32: 2 | C32: Uncommon | D32: Heal 5 | E32: Strength 3 | G32: Heal 5 and gain 3 Strength. | H32: Chebyshev | I32: 0 | J32: 4 | K32: Mend and Fortify | L32: Cleric | M32: Heal | O32: Tile | P32: Single | R32: Tile | S32: Single | Z32: FALSE | AA32: FALSE | AC32: 31fea6d7f3b17b54fbfee4ce54165c76 | AD32: =IF($AC32="","NEW","Live")
A33: Mend and Guard | B33: 2 | C33: Uncommon | D33: Heal 5 | E33: Block 1 | G33: Heal 5 and gain Block. | H33: Chebyshev | I33: 0 | J33: 4 | K33: Mend and Guard | L33: Cleric | M33: Heal | O33: Tile | P33: Single | R33: Tile | S33: Single | Z33: TRUE | AA33: FALSE | AC33: b463c182abe12924b8bd14a649d2c3a4 | AD33: =IF($AC33="","NEW","Live")
A34: Renewing Touch | B34: 2 | C34: Uncommon | D34: Regeneration 4 | G34: Apply Regeneration 4. | H34: Chebyshev | I34: 0 | J34: 4 | K34: Renewing Touch | L34: Cleric | M34: Heal | O34: Tile | P34: Single | Z34: TRUE | AA34: FALSE | AC34: 25e5a08179ad2a848b8539a19c5bbfa7 | AD34: =IF($AC34="","NEW","Live")
A35: Vigil | B35: 2 | C35: Rare | D35: Heal 12 | E35: Draw 1 | G35: Heal 12. Draw 1. Costs 1 when alone. | H35: Chebyshev | I35: 0 | J35: 4 | K35: Vigil | L35: Cleric | M35: Heal | N35: Healing | O35: Tile | P35: Single | R35: Self | S35: Single | X35: Alone -1 | Z35: FALSE | AA35: FALSE | AC35: 635cd3ef41882ce44b1bfd1a51701478 | AD35: =IF($AC35="","NEW","Live")
A36: Aegis Totem | B36: 1 | C36: Rare | D36: SummonAegisTotem | G36: Summon Aegis Totem Allies within 2: Block +3 stronger | H36: Chebyshev | I36: 1 | J36: 3 | K36: Aegis Totem | L36: Cleric | M36: Summon | O36: Tile | P36: Single | Z36: FALSE | AA36: FALSE | AC36: 01e630d4f30206f499a5038a0e474c92 | AD36: =IF($AC36="","NEW","Live")
A37: Bastion Totem | B37: 1 | C37: Uncommon | D37: SummonBastionTotem | G37: Summon Bastion Totem Allies within 2: gain 5 Shield each turn | H37: Chebyshev | I37: 1 | J37: 3 | K37: Bastion Totem | L37: Cleric | M37: Summon | O37: Tile | P37: Single | Z37: FALSE | AA37: FALSE | AC37: b5992955f6f71d249bd207dc483e4566 | AD37: =IF($AC37="","NEW","Live")
A38: Beacon Totem | B38: 1 | C38: Uncommon | D38: SummonBeaconTotem | G38: Summon Beacon Totem Taunt Enemies within 2 | H38: Chebyshev | I38: 1 | J38: 2 | K38: Beacon Totem | L38: Cleric | M38: Summon | O38: Tile | P38: Single | Z38: TRUE | AA38: FALSE | AC38: f6d1fbe1cfdd0314f9969e1457bfebe1 | AD38: =IF($AC38="","NEW","Live")
A39: Bloodpact Totem | B39: 1 | C39: Uncommon | D39: SummonBloodpactTotem | G39: Summon Bloodpact Totem Allies within 2: heal 3 on attack | H39: Chebyshev | I39: 1 | J39: 3 | K39: Bloodpact Totem | L39: Cleric | M39: Summon | O39: Tile | P39: Single | Z39: FALSE | AA39: FALSE | AC39: b6d8d70794292df43a53dfecffd26dfe | AD39: =IF($AC39="","NEW","Live")
A40: Echo Totem | B40: 1 | C40: Uncommon | D40: SummonEchoTotem | G40: Summon Echo Totem Allies within 2: 5 Shield on summon | H40: Chebyshev | I40: 1 | J40: 3 | K40: Echo Totem | L40: Cleric | M40: Summon | O40: Tile | P40: Single | Z40: FALSE | AA40: FALSE | AC40: f1df2170a944fd34785c7e3569efd815 | AD40: =IF($AC40="","NEW","Live")
A41: Rampart Totem | B41: 1 | C41: Uncommon | D41: SummonRampartTotem | G41: Summon Rampart Totem Allies within 2: take 3 less damage | H41: Chebyshev | I41: 1 | J41: 3 | K41: Rampart Totem | L41: Cleric | M41: Summon | O41: Tile | P41: Single | Z41: FALSE | AA41: FALSE | AC41: ffeb8d4fdf2a22347bff2bd9386b9ad2 | AD41: =IF($AC41="","NEW","Live")
A42: Spring Totem | B42: 1 | C42: Rare | D42: SummonSpringTotem | G42: Summon Spring Totem Allies within 2: heal 5 each turn | H42: Chebyshev | I42: 1 | J42: 3 | K42: Spring Totem | L42: Cleric | M42: Summon | O42: Tile | P42: Single | Z42: TRUE | AA42: FALSE | AC42: 822a45b68cd0cd14696780b9cffe5517 | AD42: =IF($AC42="","NEW","Live")
A43: Warcry Totem | B43: 1 | C43: Rare | D43: SummonWarcryTotem | G43: Summon Warcry Totem Allies within 2: double Strength | H43: Chebyshev | I43: 1 | J43: 3 | K43: Warcry Totem | L43: Cleric | M43: Summon | O43: Tile | P43: Single | Z43: FALSE | AA43: FALSE | AC43: 51382dd5fb68f1c42b8c120d2112eb72 | AD43: =IF($AC43="","NEW","Live")
A44: Bloom Totem | B44: 2 | C44: Uncommon | D44: SummonBloomTotem | G44: Summon Bloom Totem Allies within 2: double Regeneration | H44: Chebyshev | I44: 1 | J44: 3 | K44: Bloom Totem | L44: Cleric | M44: Summon | O44: Tile | P44: Single | Z44: FALSE | AA44: FALSE | AC44: fc0f1d24759b3b14abe50392a23bf382 | AD44: =IF($AC44="","NEW","Live")
A45: Bulwark Totem | B45: 2 | C45: Uncommon | D45: SummonBulwarkTotem | G45: Summon Bulwark Totem Allies within 2: double Block | H45: Chebyshev | I45: 1 | J45: 3 | K45: Bulwark Totem | L45: Cleric | M45: Summon | O45: Tile | P45: Single | Z45: FALSE | AA45: FALSE | AC45: 30dc9807bee5a3a47a453cded652caa6 | AD45: =IF($AC45="","NEW","Live")
A46: Chapel Totem | B46: 2 | C46: Rare | D46: SummonChapelTotem | G46: Summon Chapel Totem Allies within 2: +1 energy on heal | H46: Chebyshev | I46: 1 | J46: 3 | K46: Chapel Totem | L46: Cleric | M46: Summon | O46: Tile | P46: Single | Z46: FALSE | AA46: FALSE | AC46: 988c682b05c59b545b1c87a31c5b090d | AD46: =IF($AC46="","NEW","Live")
A47: Heal Totem | B47: 2 | C47: Uncommon | D47: SummonHealTotem | G47: Summon Heal Totem Allies within 2: heal 5 each turn | H47: Chebyshev | I47: 1 | J47: 3 | K47: Heal Totem | L47: Cleric | M47: Summon | O47: Tile | P47: Single | Z47: TRUE | AA47: FALSE | AC47: 1b8727d4f538799408c987e9f1732674 | AD47: =IF($AC47="","NEW","Live")
... A53: Wellspring Totem | B53: 2 | C53: Uncommon | D53: SummonWellspringTotem | G53: Summon Wellspring Totem Allies within 2: gain 2 Regeneration each turn | H53: Chebyshev | I53: 1 | J53: 3 | K53: Wellspring Totem | L53: Cleric | M53: Summon | O53: Tile | P53: Single | Z53: FALSE | AA53: FALSE | AC53: 6f82a9f8e2605c94a9a47f945999e665 | AD53: =IF($AC53="","NEW","Live")
A54: Summon Skeleton | B54: 3 | C54: Rare | D54: SummonSkeletonAlly | G54: Summon a Skeleton. | H54: Chebyshev | I54: 1 | J54: 3 | K54: SummonSkeleton | L54: Cleric | M54: Summon | N54: Summon | O54: Tile | P54: Single | Z54: FALSE | AA54: FALSE | AC54: c5d25d3eaabd87644b8f9bf160b035f4 | AD54: =IF($AC54="","NEW","Live")

Sheet Neutral
A1: Card Name | B1: Cost | C1: Rarity | D1: Effect 1 | E1: Effect 2 | F1: Effect 3 | G1: Description | H1: Range Shape | I1: Range Min | J1: Range Max | K1: Key | L1: Class | M1: Folder | N1: Tags | O1: Aim 1 | P1: Area 1 | Q1: Cond 1 | R1: Aim 2 | S1: Area 2 | T1: Cond 2 | U1: Aim 3 | V1: Area 3 | W1: Cond 3 | X1: Cost Cond | Y1: Keywords | Z1: No Reward | AA1: Rotatable | AB1: Animation | AC1: GUID | AD1: Sync | AE1: Notes
A2: Overflow | B2: 0 | C2: NotOffered | D2: Energy 3 | G2: Gain 3 energy. Returns to your hand. | H2: SelfTile | I2: 0 | J2: 0 | K2: Overflow | L2: Any | O2: Self | P2: Single | Y2: Innate, Rebound | Z2: TRUE | AA2: FALSE | AC2: 400da0a1fb8039847bb2c4bfc31f38d7 | AD2: =IF($AC2="","NEW","Live")
A3: Summon Skeleton Warrior | B3: 0 | C3: NotOffered | D3: SummonSkeletonWarrior | G3: Summon a Skeleton Warrior. | H3: Chebyshev | I3: 1 | J3: 5 | K3: SummonSkeletonWarrior | L3: Any | O3: Tile | P3: Single | Y3: Dormant 3, Cooldown 4 | Z3: FALSE | AA3: FALSE | AC3: e0f2734ed1017c7419f5d21d3fb737f4 | AD3: =IF($AC3="","NEW","Live")
A4: EnemyArrow | B4: 1 | C4: NotOffered | D4: Damage 3 | E4: Vulnerable | G4: Deal 3 damage and apply Vulnerable to an enemy within 4 tiles. | H4: Chebyshev | I4: 1 | J4: 4 | K4: EnemyArrow | L4: Any | O4: Tile | P4: Single | R4: Tile | S4: Single | Z4: FALSE | AA4: FALSE | AB4: EnemyArrow | AC4: bbde0f0e0cc14d529a5088cf2502a322 | AD4: =IF($AC4="","NEW","Live")
B5: 1 | C5: NotOffered | D5: Damage 8 | G5: Deal 5 damage. | H5: Chebyshev | I5: 1 | J5: 1 | K5: EnemySlash | L5: Any | O5: Tile | P5: Single | Z5: FALSE | AA5: FALSE | AC5: 4e6ad46400a24ad49889dba4ec94d0b6 | AD5: =IF($AC5="","NEW","Live")
A6: Move 1 | B6: 1 | C6: Common | D6: Move | G6: Move one tile in any direction. | H6: Chebyshev | I6: 1 | J6: 1 | K6: Move | L6: Any | N6: Movement | O6: Tile | P6: Single | Z6: TRUE | AA6: FALSE | AC6: be5db39fd599473588c5ca05a015d151 | AD6: =IF($AC6="","NEW","Live")
A7: Move 1 | B7: 1 | C7: NotOffered | D7: Move | G7: Move one tile in any direction. | H7: Chebyshev | I7: 1 | J7: 1 | K7: MoveInnate | L7: Any | O7: Tile | P7: Single | Y7: Innate | Z7: FALSE | AA7: FALSE | AC7: 0c8f3a6d2b4e4f9a8c1d7e5b3a2f6c9d | AD7: =IF($AC7="","NEW","Live")
A8: Move 2 | B8: 1 | C8: NotOffered | D8: Move | G8: Move up to two tiles in any direction. | H8: Chebyshev | I8: 1 | J8: 2 | K8: MoveInnate2 | L8: Any | O8: Tile | P8: Single | Y8: Innate | Z8: FALSE | AA8: FALSE | AC8: 4f7b2c91e6a84d3ab0d5c8e27f1a9b64 | AD8: =IF($AC8="","NEW","Live")
A9: Teleport | B9: 1 | C9: NotOffered | D9: Move | G9: Move up to three tiles in any direction, ignoring walls. | H9: Chebyshev | I9: 1 | J9: 3 | K9: TeleportInnate | L9: Any | O9: Tile | P9: Single | Y9: Innate | Z9: TRUE | AA9: FALSE | AC9: c63bc2ac593efc9409d8b2e2b673a08d | AD9: =IF($AC9="","NEW","Live")
A10: Bite | B10: 1 | C10: NotOffered | D10: Damage 5 | G10: Deal 5 damage. | H10: Chebyshev | I10: 1 | J10: 1 | K10: Bite | L10: Any | M10: Bat | N10: Attack | O10: Tile | P10: Single | Z10: FALSE | AA10: FALSE | AC10: ee373f925ba104f43bcc820881e5a445 | AD10: =IF($AC10="","NEW","Live")
A11: Call the Damned | B11: 0 | C11: NotOffered | D11: SummonSkeletonMinion | G11: Summon a Skeleton. | H11: Chebyshev | I11: 1 | J11: 3 | K11: CallTheDamned | L11: Any | M11: BlackKnight | N11: Summon | O11: Tile | P11: Single | Y11: Cooldown 3 | Z11: FALSE | AA11: FALSE | AC11: da46264a9760d4b499106e4057fe349a | AD11: =IF($AC11="","NEW","Live")
A12: Black Guard | B12: 1 | C12: NotOffered | D12: Damage 5 | G12: Deal 5 damage. | H12: Chebyshev | I12: 1 | J12: 1 | K12: BlackGuard | L12: Any | M12: BlackKnight | N12: Attack | O12: Tile | P12: Single | Z12: FALSE | AA12: FALSE | AC12: 9b2ff5c09da592b4aac092835fb9d5f8 | AD12: =IF($AC12="","NEW","Live")
A13: Dread Cleave | B13: 1 | C13: NotOffered | D13: Damage 8 | G13: Deal 8 damage to everything within 1 tile. | H13: Chebyshev | I13: 1 | J13: 1 | K13: DreadCleave | L13: Any | M13: BlackKnight | N13: Attack | O13: Tile | P13: Chebyshev 0-1 | Z13: FALSE | AA13: FALSE | AC13: 911c7b3450e79a1448f794b46caf54e3 | AD13: =IF($AC13="","NEW","Live")
A14: Claw Attack | B14: 1 | C14: NotOffered | D14: Damage 4 | E14: Shield 4 | G14: Deal 4 damage. Gain 4 Shield | H14: Chebyshev | I14: 1 | J14: 1 | K14: ClawAttack | L14: Any | M14: Crab | N14: Attack | O14: Tile | P14: Single | R14: Self | S14: Single | Z14: FALSE | AA14: FALSE | AC14: 2c191dc4234fac04e8738aabc36b6cee | AD14: =IF($AC14="","NEW","Live")
A15: Royal Command | B15: 0 | C15: NotOffered | D15: SummonLightBanditMinion | G15: Summon a Light Bandit. | H15: Chebyshev | I15: 1 | J15: 3 | K15: RoyalCommand | L15: Any | M15: EvilKing | N15: Summon | O15: Tile | P15: Single | Y15: Cooldown 3 | Z15: FALSE | AA15: FALSE | AC15: a1daffbc393702947b8e63307f588d5d | AD15: =IF($AC15="","NEW","Live")
A16: Executioner's Blow | B16: 1 | C16: NotOffered | D16: Damage 4 | G16: Deal 4 damage. | H16: Chebyshev | I16: 1 | J16: 1 | K16: ExecutionersBlow | L16: Any | M16: EvilKing | N16: Attack | O16: Tile | P16: Single | Z16: FALSE | AA16: FALSE | AC16: 8997d569af1bef44aa831ed6fe2aa939 | AD16: =IF($AC16="","NEW","Live")
A17: Royal Guard | B17: 1 | C17: NotOffered | D17: Damage 3 | G17: Deal 3 damage within 1 tile. | H17: Chebyshev | I17: 1 | J17: 1 | K17: RoyalGuard | L17: Any | M17: EvilKing | N17: Attack | O17: Tile | P17: Chebyshev 0-1 | Z17: FALSE | AA17: FALSE | AC17: c330fc715539b424d876b3642e7c9919 | AD17: =IF($AC17="","NEW","Live")
A18: Rally | B18: 0 | C18: NotOffered | D18: SummonHeavyBanditMinion | G18: Summon a line of Heavy Bandits. | H18: Chebyshev | I18: 1 | J18: 3 | K18: Rally | L18: Any | M18: EvilKnight | N18: Summon | O18: Tile | P18: Pattern:Wall3 | Y18: Cooldown 4, Interruptible 2 | Z18: FALSE | AA18: FALSE | AC18: 43b25c70bde2b7645abfca6e8feac7d4 | AD18: =IF($AC18="","NEW","Live")
A19: Riposte | B19: 1 | C19: NotOffered | D19: Damage 6 | E19: Parry 1 | G19: Deal 6 damage. Gain 1 Parry. | H19: Chebyshev | I19: 1 | J19: 1 | K19: Riposte | L19: Any | M19: EvilKnight | N19: Attack | O19: Tile | P19: Single | R19: Self | S19: Single | Z19: FALSE | AA19: FALSE | AC19: aefe57b35c9afe64ba4eb9112efd9883 | AD19: =IF($AC19="","NEW","Live")
A20: Shield Bash | B20: 1 | C20: NotOffered | D20: Damage 4 | E20: Shield 10 | F20: Block 2 | G20: Deal 4 damage. Gain 10 Shield and 2 Block. | H20: Chebyshev | I20: 1 | J20: 1 | K20: ShieldBash | L20: Any | M20: EvilKnight | N20: Attack | O20: Tile | P20: Single | R20: Self | S20: Single | U20: Self | V20: Single | Z20: FALSE | AA20: FALSE | AC20: 51f29b7e912127f43ad357fd5f12663c | AD20: =IF($AC20="","NEW","Live")
A21: Summon Imp | B21: 0 | C21: NotOffered | D21: SummonGoblinMinion | G21: Summon a Goblin. | H21: Chebyshev | I21: 1 | J21: 3 | K21: SummonImp | L21: Any | M21: EvilWizard | N21: Summon | O21: Tile | P21: Single | Y21: Cooldown 3 | Z21: FALSE | AA21: FALSE | AC21: a88d8789fe23d7b4a8803cfab0721cc0 | AD21: =IF($AC21="","NEW","Live")
A22: Dark Bolt | B22: 1 | C22: NotOffered | D22: Damage 5 | G22: Deal 5 damage to everything within 1 tile. | H22: Chebyshev | I22: 2 | J22: 5 | K22: DarkBolt | L22: Any | M22: EvilWizard | N22: Attack | O22: Tile | P22: Chebyshev 0-1 | Z22: FALSE | AA22: FALSE | AB22: Fireball | AC22: d7683e27219ae7a49bbe364a274bfc22 | AD22: =IF($AC22="","NEW","Live")
A23: Shadow Ward | B23: 1 | C23: NotOffered | D23: Damage 3 | E23: Shield 7 | G23: Deal 3 damage. Gain 7 Shield. | H23: Chebyshev | I23: 1 | J23: 4 | K23: ShadowWard | L23: Any | M23: EvilWizard | N23: Attack | O23: Tile | P23: Single | R23: Self | S23: Single | Z23: FALSE | AA23: FALSE | AB23: Status | AC23: 6f6aee052e565334184d68675bbc9306 | AD23: =IF($AC23="","NEW","Live")
A24: Call the Swarm | B24: 0 | C24: NotOffered | D24: SummonBatMinion | G24: Summon a Bat. | H24: Chebyshev | I24: 1 | J24: 3 | K24: CallTheSwarm | L24: Any | M24: EvilWizard2 | N24: Summon | O24: Tile | P24: Single | Y24: Cooldown 2 | Z24: FALSE | AA24: FALSE | AC24: ece43c6ee0d65dd40b59ed491b201779 | AD24: =IF($AC24="","NEW","Live")
A25: Arcane Lance | B25: 1 | C25: NotOffered | D25: Damage 6 | G25: Deal 6 damage. | H25: Chebyshev | I25: 2 | J25: 5 | K25: ArcaneLance | L25: Any | M25: EvilWizard2 | N25: Attack | O25: Tile | P25: Single | Z25: FALSE | AA25: FALSE | AB25: Status | AC25: c31b41c07840eef46872d698ddd854e5 | AD25: =IF($AC25="","NEW","Live")
A26: Void Barrier | B26: 1 | C26: NotOffered | D26: Damage 3 | E26: Weaken | F26: Vulnerable | G26: Deal 3 damage. Apply Weaken and Vulnerable. | H26: Chebyshev | I26: 1 | J26: 4 | K26: VoidBarrier | L26: Any | M26: EvilWizard2 | N26: Attack | O26: Tile | P26: Single | R26: Tile | S26: Single | U26: Tile | V26: Single | Y26: Interruptible 2 | Z26: FALSE | AA26: FALSE | AB26: Status | AC26: 9b758a484d41478459502850e55de625 | AD26: =IF($AC26="","NEW","Live")
A27: Conjure Ooze | B27: 0 | C27: NotOffered | D27: SummonSlimeMinion | G27: Summon a Slime. | H27: Chebyshev | I27: 1 | J27: 3 | K27: ConjureOoze | L27: Any | M27: EvilWizard3 | N27: Summon | O27: Tile | P27: Single | Y27: Cooldown 3 | Z27: FALSE | AA27: FALSE | AC27: 46914671440488144a08d7e55f93496e | AD27: =IF($AC27="","NEW","Live")
A28: Ember Shroud | B28: 1 | C28: NotOffered | D28: Damage 4 | E28: Shield 7 | G28: Deal 4 damage. Gain 7 Shield. | H28: Chebyshev | I28: 1 | J28: 4 | K28: EmberShroud | L28: Any | M28: EvilWizard3 | N28: Fire | O28: Tile | P28: Single | R28: Self | S28: Single | Z28: FALSE | AA28: FALSE | AB28: Fireball | AC28: 0ae0a9ae1c0ad544897834ac7222f51a | AD28: =IF($AC28="","NEW","Live")
A29: Meteor Fall | B29: 1 | C29: NotOffered | D29: Damage 8 | G29: Deal 12 damage. | H29: Chebyshev | I29: 2 | J29: 5 | K29: MeteorFall | L29: Any | M29: EvilWizard3 | N29: Fire | O29: Tile | P29: Single | Z29: FALSE | AA29: FALSE | AB29: Fireball | AC29: 28c0d441d22ffde47bbdbcd202e0d299 | AD29: =IF($AC29="","NEW","Live")
A30: Withering Gaze | B30: 1 | C30: NotOffered | D30: Damage 3 | G30: Deal 3 damage. | H30: Chebyshev | I30: 2 | J30: 4 | K30: WitheringGaze | L30: Any | M30: FlyingEye | N30: Attack | O30: Tile | P30: Single | Z30: FALSE | AA30: FALSE | AB30: Status | AC30: 07914c39ca22b974e8a5a2e0670dc72c | AD30: =IF($AC30="","NEW","Live")
A31: Backstab | B31: 1 | C31: NotOffered | D31: Damage 5 | G31: Deal 4 damage. | H31: Chebyshev | I31: 1 | J31: 1 | K31: Backstab | L31: Any | M31: Goblin | N31: Attack | O31: Tile | P31: Single | Z31: FALSE | AA31: FALSE | AC31: 538cb111b2eeb4240b4ba7d42cdb3127 | AD31: =IF($AC31="","NEW","Live")
A32: Boulder Smash | B32: 1 | C32: NotOffered | D32: Damage 5 | G32: Deal 5 damage. | H32: Chebyshev | I32: 1 | J32: 1 | K32: BoulderSmash | L32: Any | M32: Golem | N32: Attack | O32: Tile | P32: Single | Z32: FALSE | AA32: FALSE | AC32: cd738dbc70183eb43b9d0f1617e7fccb | AD32: =IF($AC32="","NEW","Live")
A33: Summon Pebble | B33: 1 | C33: NotOffered | D33: SummonPebbleMinion | G33: Summon a Pebble. | H33: Chebyshev | I33: 1 | J33: 1 | K33: SummonPebble | L33: Any | M33: Golem | O33: Tile | P33: Single | Y33: Cooldown 3 | Z33: FALSE | AA33: FALSE | AC33: 714885aed3744e7386c9d3a230330726 | AD33: =IF($AC33="","NEW","Live")
A34: Heavy Swing | B34: 1 | C34: NotOffered | D34: Damage 6 | E34: Shield 5 | F34: Block 2 | G34: Deal 6 damage. Gain 5 Shield. Gain 2 Block. | H34: Chebyshev | I34: 1 | J34: 1 | K34: HeavySwing | L34: Any | M34: HeavyBandit | N34: Attack | O34: Tile | P34: Single | R34: Self | S34: Single | U34: Self | V34: Single | Z34: FALSE | AA34: FALSE | AC34: 07c85180eb038d04abd37cebfdfb4271 | AD34: =IF($AC34="","NEW","Live")
A35: Quick Cut | B35: 1 | C35: NotOffered | D35: Damage 1 | E35: Weaken | G35: Deal 1 damage and apply Weaken to everything within 1 tile. | H35: Chebyshev | I35: 2 | J35: 4 | K35: QuickCut | L35: Any | M35: LightBandit | N35: Attack | O35: Tile | P35: Chebyshev 0-1 | R35: Tile | S35: Chebyshev 0-1 | Z35: FALSE | AA35: FALSE | AC35: 2349e2cdc34243246829058448485960 | AD35: =IF($AC35="","NEW","Live")
A36: Venom Cut | B36: 1 | C36: NotOffered | D36: Damage 1 | E36: Poison 2 | G36: Deal 1 damage and apply 2 Poison. | H36: Chebyshev | I36: 2 | J36: 4 | K36: VenomCut | L36: Any | M36: LightBandit | N36: Attack | O36: Tile | P36: Single | R36: Tile | S36: Single | Z36: FALSE | AA36: FALSE | AC36: 3626a8f71ed84831aaa86517d8531b0b | AD36: =IF($AC36="","NEW","Live")
A37: Chomp | B37: 1 | C37: NotOffered | D37: Damage 7 | E37: Root | G37: Deal 7 damage. Apply Root. | H37: Chebyshev | I37: 1 | J37: 1 | K37: Chomp | L37: Any | M37: Mimic | N37: Attack | O37: Tile | P37: Single | R37: Tile | S37: Single | Z37: FALSE | AA37: FALSE | AC37: 239c09d57f556754db620c1adca26b94 | AD37: =IF($AC37="","NEW","Live")
A38: Spore Cloud | B38: 1 | C38: NotOffered | D38: Poison 3 | G38: Apply 3 Poison to everything within 1 tile. | H38: Chebyshev | I38: 1 | J38: 3 | K38: SporeCloud | L38: Any | M38: Mushroom | N38: Poison | O38: Tile | P38: Chebyshev 0-1 | Z38: FALSE | AA38: FALSE | AC38: 2219d300acbaec4488c053a9324844a7 | AD38: =IF($AC38="","NEW","Live")
A39: Roll | B39: 1 | C39: NotOffered | D39: Damage 2 | G39: Deal 2 damage. | H39: Chebyshev | I39: 1 | J39: 1 | K39: Roll | L39: Any | M39: Pebble | N39: Attack | O39: Tile | P39: Single | Z39: FALSE | AA39: FALSE | AC39: c4116d531ca49814bb08afec090aa2ff | AD39: =IF($AC39="","NEW","Live")
A40: Plague Bite | B40: 1 | C40: NotOffered | D40: Damage 2 | E40: Poison 3 | G40: Deal 2 damage. Apply 3 Poison. | H40: Chebyshev | I40: 1 | J40: 1 | K40: PlagueBite | L40: Any | M40: PlagueRat | N40: Poison | O40: Tile | P40: Single | R40: Tile | S40: Single | Z40: FALSE | AA40: FALSE | AC40: ae3460f6e67545444b30dba2e2091781 | AD40: =IF($AC40="","NEW","Live")
A41: Gnaw | B41: 1 | C41: NotOffered | D41: Damage 4 | G41: Deal 2 damage. Apply 2 Poison. | H41: Chebyshev | I41: 1 | J41: 1 | K41: Gnaw | L41: Any | M41: Rat | N41: Poison | O41: Tile | P41: Single | Z41: FALSE | AA41: FALSE | AC41: df94d1a8e1d8c13448e8720f4acbf71d | AD41: =IF($AC41="","NEW","Live")
A42: Raise Dead | B42: 0 | C42: NotOffered | D42: SummonSkeletonMinion | G42: Summon a Skeleton. | H42: Chebyshev | I42: 1 | J42: 4 | K42: RaiseDead | L42: Any | M42: Reaper | N42: Summon | O42: Tile | P42: Single | Y42: Cooldown 3 | Z42: FALSE | AA42: FALSE | AC42: 12d3f837e6375f046b590dfb06c3b1f0 | AD42: =IF($AC42="","NEW","Live")
A43: Death's Toll | B43: 1 | C43: NotOffered | D43: Damage 4 | E43: Vulnerable | G43: Deal 4 damage and apply Vulnerable within 1 tile. | H43: Chebyshev | I43: 1 | J43: 4 | K43: DeathsToll | L43: Any | M43: Reaper | N43: Attack | O43: Tile | P43: Chebyshev 0-1 | R43: Tile | S43: Chebyshev 0-1 | Y43: Interruptible 3 | Z43: FALSE | AA43: FALSE | AC43: 9aa98cf1d02a0d547ad7499cf286ce22 | AD43: =IF($AC43="","NEW","Live")
A44: Grave Tithe | B44: 1 | C44: NotOffered | D44: Damage 2 | E44: Pilfered 1 | G44: Deal 2 damage. At the start of their next turn, the target discards a card at random. | H44: Chebyshev | I44: 1 | J44: 3 | K44: GraveTithe | L44: Any | M44: Reaper | O44: Tile | P44: Single | R44: Tile | S44: Single | Y44: Cooldown 2, Interruptible 3 | Z44: FALSE | AA44: FALSE | AC44: 4cda4fed035e43f89daae7722563ab98 | AD44: =IF($AC44="","NEW","Live")
A45: Soul Drain | B45: 1 | C45: NotOffered | D45: Damage 2 | E45: Sapped 2 | G45: Deal 2 damage. The target has 1 less energy for 2 turns. | H45: Chebyshev | I45: 1 | J45: 3 | K45: SoulDrain | L45: Any | M45: Reaper | O45: Tile | P45: Single | R45: Tile | S45: Single | Y45: Cooldown 2, Interruptible 3 | Z45: FALSE | AA45: FALSE | AC45: d950b17862b74f29a9116d6e6baf3953 | AD45: =IF($AC45="","NEW","Live")
A46: Soul Reap | B46: 1 | C46: NotOffered | D46: Damage 2 | E46: Weaken | G46: Deal 2 damage. Apply Weaken. | H46: Chebyshev | I46: 1 | J46: 2 | K46: SoulReap | L46: Any | M46: Reaper | N46: Attack | O46: Tile | P46: Single | R46: Tile | S46: Single | Y46: Interruptible 3 | Z46: FALSE | AA46: FALSE | AC46: c90aeb9fd1b522e4e9ceb442096ded71 | AD46: =IF($AC46="","NEW","Live")
A47: Soul Swap | B47: 1 | C47: NotOffered | D47: Swap | G47: Swap places with a hero. | H47: Chebyshev | I47: 1 | J47: 4 | K47: SoulSwap | L47: Any | M47: Reaper | O47: Tile | P47: Single | Y47: Cooldown 2 | Z47: FALSE | AA47: FALSE | AC47: d35efb0a1af04381850353ef70f9f7c3 | AD47: =IF($AC47="","NEW","Live")
A48: Splinter Off | B48: 0 | C48: NotOffered | D48: SummonPebbleMinion | G48: Summon a Pebble. | H48: Chebyshev | I48: 1 | J48: 2 | K48: SplinterOff | L48: Any | M48: ReinforcedGolem | N48: Summon | O48: Tile | P48: Single | Y48: Cooldown 2 | Z48: FALSE | AA48: FALSE | AC48: 6116b877e2e1c1f4abc120a10be8fdc9 | AD48: =IF($AC48="","NEW","Live")
A49: Seismic Slam | B49: 1 | C49: NotOffered | D49: Damage 7 | G49: Deal 7 damage to everything within 1 tile. | H49: Chebyshev | I49: 1 | J49: 1 | K49: SeismicSlam | L49: Any | M49: ReinforcedGolem | N49: Attack | O49: Tile | P49: Chebyshev 0-1 | Z49: FALSE | AA49: FALSE | AC49: b1d01ab28ff9495499af5f2e132fecb3 | AD49: =IF($AC49="","NEW","Live")
A50: Stone Skin | B50: 1 | C50: NotOffered | D50: Damage 4 | E50: Shield 10 | G50: Deal 4 damage. Gain 10 Shield. | H50: Chebyshev | I50: 1 | J50: 1 | K50: StoneSkin | L50: Any | M50: ReinforcedGolem | N50: Attack | O50: Tile | P50: Single | R50: Self | S50: Single | Z50: FALSE | AA50: FALSE | AC50: e2e16c0d28c76d54192dc306b83409e4 | AD50: =IF($AC50="","NEW","Live")
A51: Bone Bulwark | B51: 1 | C51: NotOffered | D51: Damage 3 | E51: Shield 5 | G51: Deal 3 damage. Gain 5 Shield. | H51: Chebyshev | I51: 1 | J51: 1 | K51: BoneBulwark | L51: Any | M51: Skeleton | N51: Attack | O51: Tile | P51: Single | R51: Self | S51: Single | Z51: FALSE | AA51: FALSE | AC51: c605de25d1ddef545ae635249c67fbc3 | AD51: =IF($AC51="","NEW","Live")
A52: Bone Chill | B52: 1 | C52: NotOffered | D52: Damage 3 | E52: Vulnerable | G52: Deal 3 damage. Apply Vulnerable. | H52: Chebyshev | I52: 1 | J52: 3 | K52: BoneChill | L52: Any | M52: Skull | N52: Attack | O52: Tile | P52: Single | R52: Tile | S52: Single | Z52: FALSE | AA52: FALSE | AB52: Status | AC52: ef4c334c610218f46a34acd971f2a448 | AD52: =IF($AC52="","NEW","Live")
A53: Engulf | B53: 1 | C53: NotOffered | D53: Damage 3 | E53: Weaken | G53: Deal 3 damage. Apply Weaken. | H53: Chebyshev | I53: 1 | J53: 1 | K53: Engulf | L53: Any | M53: Slime | N53: Attack | O53: Tile | P53: Single | R53: Tile | S53: Single | Z53: FALSE | AA53: FALSE | AC53: f8ada88cc46e5954d9fee21de35c0055 | AD53: =IF($AC53="","NEW","Live")
A54: Spike Burst | B54: 1 | C54: NotOffered | D54: Damage 3 | E54: Weaken | G54: Deal 3 damage and apply Weaken to everything within 1 tile. | H54: Chebyshev | I54: 1 | J54: 1 | K54: SpikeBurst | L54: Any | M54: SpikedSlime | N54: Attack | O54: Tile | P54: Chebyshev 0-1 | R54: Tile | S54: Chebyshev 0-1 | Z54: FALSE | AA54: FALSE | AC54: 75f20f8d944d59c499e2ca84270e72b2 | AD54: =IF($AC54="","NEW","Live")
A55: Life Leech | B55: 1 | C55: NotOffered | D55: Damage 3 | E55: Heal 3 | G55: Deal 3 damage. Heal 3. | H55: Chebyshev | I55: 1 | J55: 1 | K55: LifeLeech | L55: Any | M55: VampireBat | N55: Attack | O55: Tile | P55: Single | R55: Self | S55: Single | Z55: FALSE | AA55: FALSE | AC55: 74c088f7aa523704380454f17ee28cc5 | AD55: =IF($AC55="","NEW","Live")

Sheet Knight Ideas
A1: Card Name | B1: Cost | C1: Rarity | D1: Effect 1 | E1: Effect 2 | F1: Effect 3 | G1: Description | H1: Range Shape | I1: Range Min | J1: Range Max | K1: Key | L1: Class | M1: Folder | N1: Tags | O1: Aim 1 | P1: Area 1 | Q1: Cond 1 | R1: Aim 2 | S1: Area 2 | T1: Cond 2 | U1: Aim 3 | V1: Area 3 | W1: Cond 3 | X1: Cost Cond | Y1: Keywords | Z1: No Reward | AA1: Rotatable | AB1: Animation | AC1: GUID | AD1: Sync | AE1: Notes | AF1: Buildable | AG1: Engine Work | AH1: Source | AI1: Priority
A2: Cleave | B2: 1 | C2: Uncommon | D2: Damage 4 | G2: Deal 4 damage to every enemy around the target. | H2: Chebyshev | I2: 1 | J2: 1 | K2: Cleave | L2: Knight | M2: Melee Attack | N2: Attack | O2: Tile | P2: Chebyshev 0-1 | Z2: FALSE | AD2: =IF($AC2="","NEW","Live") | AF2: Yes | AH2: D&D / StS | AI2: High
A3: Iron Wall | B3: 2 | C3: Uncommon | D3: Shield 7 | E3: Block 2 | G3: Gain 7 Shield and 2 Block charges. | H3: SelfTile | I3: 0 | J3: 0 | K3: IronWall | L3: Knight | M3: Buff (Defensive) | N3: Defence | O3: Self | P3: Single | R3: Self | S3: Single | Z3: FALSE | AD3: =IF($AC3="","NEW","Live") | AF3: Yes | AH3: StS Barricade | AI3: Med
A4: Bulwark | B4: 1 | C4: Common | D4: Block 2 | G4: Gain 2 Block charges. | H4: SelfTile | I4: 0 | J4: 0 | K4: Bulwark | L4: Knight | M4: Buff (Defensive) | N4: Defence | O4: Self | P4: Single | Z4: FALSE | AD4: =IF($AC4="","NEW","Live") | AF4: Yes | AI4: Med
A5: Riposte | B5: 2 | C5: Rare | D5: Parry 1 | E5: Parry 1 | G5: Gain 2 Parry charges. | H5: SelfTile | I5: 0 | J5: 0 | K5: Riposte | L5: Knight | M5: Buff (Defensive) | N5: Defence | O5: Self | P5: Single | R5: Self | S5: Single | Z5: FALSE | AD5: =IF($AC5="","NEW","Live") | AF5: Yes | AH5: Fencing / FFT | AI5: Med
A6: Heavy Swing | B6: 2 | C6: Common | D6: Damage 12 | G6: Deal 12 damage. | H6: Chebyshev | I6: 1 | J6: 1 | K6: HeavySwing | L6: Knight | M6: Melee Attack | N6: Attack | O6: Tile | P6: Single | Z6: FALSE | AD6: =IF($AC6="","NEW","Live") | AF6: Yes | AI6: Med
A7: Second Wind | B7: 1 | C7: Uncommon | D7: Heal 5 | G7: Heal 5. The Knight has no healing at all today. | H7: SelfTile | I7: 0 | J7: 0 | K7: SecondWind | L7: Knight | M7: Heal | N7: Healing | O7: Self | P7: Single | Z7: FALSE | AD7: =IF($AC7="","NEW","Live") | AE7: Fills a real gap: Knight currently has zero heal cards. | AF7: Yes | AH7: D&D Fighter | AI7: High
A8: Guard Stance | B8: 0 | C8: Common | D8: Shield 3 | E8: Block 1 | G8: Gain 3 Shield and 1 Block charge. | H8: SelfTile | I8: 0 | J8: 0 | K8: GuardStance | L8: Knight | M8: Buff (Defensive) | N8: Defence | O8: Self | P8: Single | R8: Self | S8: Single | Z8: FALSE | AD8: =IF($AC8="","NEW","Live") | AF8: Yes | AI8: Med
A9: Shield Slam | B9: 2 | C9: Uncommon | D9: Damage 5 | E9: Shield 5 | G9: Deal 5 damage and gain 5 Shield. | H9: Chebyshev | I9: 1 | J9: 1 | K9: ShieldSlam | L9: Knight | M9: Melee Attack | N9: Attack, Defence | O9: Tile | P9: Single | R9: Self | S9: Single | Z9: FALSE | AD9: =IF($AC9="","NEW","Live") | AF9: Yes | AH9: WoW | AI9: Med
A10: Last Stand | B10: 3 | C10: Rare | D10: Shield 15 | E10: Block 3 | G10: Gain 15 Shield and 3 Block charges. | H10: SelfTile | I10: 0 | J10: 0 | K10: LastStand | L10: Knight | M10: Buff (Defensive) | N10: Defence | O10: Self | P10: Single | R10: Self | S10: Single | Z10: FALSE | AD10: =IF($AC10="","NEW","Live") | AF10: Yes | AI10: Low
A11: Shield Charge | B11: 2 | C11: Uncommon | D11: Move | E11: Damage 5 | G11: Move to a tile, then deal 5 damage to everything adjacent to where you land. | H11: Chebyshev | I11: 1 | J11: 3 | K11: ShieldCharge | L11: Knight | M11: Melee Attack | N11: Attack, Movement | O11: Tile | P11: Single | R11: Source | S11: Chebyshev 0-1 | Z11: FALSE | AD11: =IF($AC11="","NEW","Live") | AF11: Needs Effect | AG11: A DashAttackEffect: Move and Damage resolve as separate actions today, so the damage lands around the OLD tile. Needs one effect that moves then strikes from the destination. | AH11: Into the Breach | AI11: High
A12: Bull Rush | B12: 1 | C12: Uncommon | D12: Damage 3 | G12: Deal 3 damage and push the target 1 tile away. | H12: Chebyshev | I12: 1 | J12: 1 | K12: BullRush | L12: Knight | M12: Melee Attack | N12: Attack, Movement | O12: Tile | P12: Single | Z12: FALSE | AD12: =IF($AC12="","NEW","Live") | AE12: Push/pull is the single highest-value addition for a grid game. Unlocks a dozen cards across all three classes. | AF12: Needs Effect | AG12: PushEffect : CardEffect - displace the occupant N tiles along the aim direction, via GridManager.MoveCharacter so move rules and tweens still apply. | AH12: Into the Breach | AI12: High
A13: Anchor | B13: 1 | C13: Common | G13: You cannot be pushed or pulled this turn. | H13: SelfTile | I13: 0 | J13: 0 | K13: Anchor | L13: Knight | M13: Buff (Defensive) | N13: Defence | Z13: FALSE | AD13: =IF($AC13="","NEW","Live") | AE13: Only worth building once push exists. | AF13: Needs Status | AG13: ImmovableStatus with a DisplacementRefusal gate, plus StatusType.Immovable appended to the enum. | AH13: Into the Breach | AI13: Low
A14: Grapple | B14: 1 | C14: Uncommon | G14: Pull the target 1 tile toward you. | H14: Chebyshev | I14: 1 | J14: 2 | K14: Grapple | L14: Knight | M14: Melee Attack | N14: Attack, Movement | Z14: FALSE | AD14: =IF($AC14="","NEW","Live") | AF14: Needs Effect | AG14: PullEffect - the inverse of PushEffect; both should share one displacement helper. | AH14: D&D grapple | AI14: High
A15: Zone of Control | B15: 2 | C15: Rare | G15: Summon a totem that deals 3 damage to any enemy standing next to it at end of turn. | H15: Chebyshev | I15: 1 | J15: 2 | K15: ZoneOfControl | L15: Knight | M15: Summon | N15: Defence, Summon | Z15: FALSE | AD15: =IF($AC15="","NEW","Live") | AF15: Needs System | AG15: A second Totem prefab with a damaging AuraReaction on an end-of-turn trigger. TriggeringActionType has no turn-end entry yet. | AH15: Into the Breach / FFT | AI15: Med
A16: Interpose | B16: 1 | C16: Rare | G16: Swap places with an adjacent ally. | H16: Chebyshev | I16: 1 | J16: 1 | K16: Interpose | L16: Knight | M16: Movement | N16: Movement, Defence | Z16: FALSE | AD16: =IF($AC16="","NEW","Live") | AF16: Needs Effect | AG16: SwapEffect - exchange two occupants. Character.MoveTo assumes the destination is empty, so this needs a paired swap on GridManager. | AH16: FFT / Fire Emblem | AI16: Med
A17: Hold the Line | B17: 2 | C17: Uncommon | D17: Taunt | E17: Block 2 | G17: Taunt the target and gain 2 Block charges. | H17: Chebyshev | I17: 1 | J17: 3 | K17: HoldTheLine | L17: Knight | M17: Buff (Defensive) | N17: Defence | O17: Tile | P17: Single | R17: Self | S17: Single | Z17: FALSE | AD17: =IF($AC17="","NEW","Live") | AE17: Taunt has exactly one card today. | AF17: Yes | AI17: High
A18: Fortify Position | B18: 1 | C18: Common | D18: Shield 5 | E18: Root | G18: Gain 5 Shield, but you are Rooted - the cost of digging in. | H18: SelfTile | I18: 0 | J18: 0 | K18: FortifyPosition | L18: Knight | M18: Buff (Defensive) | N18: Defence | O18: Self | P18: Single | R18: Self | S18: Single | Z18: FALSE | AD18: =IF($AC18="","NEW","Live") | AE18: Rooting yourself is already expressible: Root aimed at Self. A genuine drawback card with no new code. | AF18: Yes | AH18: Darkest Dungeon | AI18: High
A19: Vanguard | B19: 2 | C19: Rare | D19: Move | G19: Move, then Taunt every enemy adjacent to where you land. | H19: Chebyshev | I19: 1 | J19: 3 | K19: Vanguard | L19: Knight | M19: Movement | N19: Movement, Defence | O19: Tile | P19: Single | Z19: FALSE | AD19: =IF($AC19="","NEW","Live") | AF19: Needs Effect | AG19: Same DashAttackEffect problem as Shield Charge - the second effect must aim from the destination tile. | AH19: Into the Breach | AI19: Med
A20: Rallying Cry | B20: 2 | C20: Uncommon | D20: Strength 2 | G20: You and every ally within 2 tiles gain 2 Strength. | H20: SelfTile | I20: 0 | J20: 0 | K20: RallyingCry | L20: Knight | M20: Buff (Offensive) | N20: Attack | O20: Self | P20: Manhattan 0-2 | Z20: FALSE | AD20: =IF($AC20="","NEW","Live") | AF20: Yes | AH20: Warcraft | AI20: High
A21: Intimidate | B21: 1 | C21: Common | D21: Weaken 2 | G21: Apply 2 Weaken. | H21: Chebyshev | I21: 1 | J21: 3 | K21: Intimidate | L21: Knight | M21: Debuff | N21: Attack | O21: Tile | P21: Single | Z21: FALSE | AD21: =IF($AC21="","NEW","Live") | AF21: Yes | AI21: Med
A22: Crushing Blow | B22: 2 | C22: Uncommon | D22: Damage 5 | E22: Weaken 3 | G22: Deal 5 damage and apply 3 Weaken. | H22: Chebyshev | I22: 1 | J22: 1 | K22: CrushingBlow | L22: Knight | M22: Melee Attack | N22: Attack | O22: Tile | P22: Single | R22: Tile | S22: Single | Z22: FALSE | AD22: =IF($AC22="","NEW","Live") | AF22: Yes | AI22: Med
A23: Armor Up | B23: 1 | C23: Common | D23: Double Shield | G23: Your next Shield gain is doubled. | H23: SelfTile | I23: 0 | J23: 0 | K23: ArmorUp | L23: Knight | M23: Buff (Defensive) | N23: Defence | O23: Self | P23: Single | Z23: FALSE | AD23: =IF($AC23="","NEW","Live") | AE23: DoubleShield has one card today. | AF23: Yes | AI23: Med
A24: Perfect Guard | B24: 2 | C24: Rare | D24: Block 3 | E24: Double Shield | G24: Gain 3 Block charges. Your next Shield gain is doubled. | H24: SelfTile | I24: 0 | J24: 0 | K24: PerfectGuard | L24: Knight | M24: Buff (Defensive) | N24: Defence | O24: Self | P24: Single | R24: Self | S24: Single | Z24: FALSE | AD24: =IF($AC24="","NEW","Live") | AF24: Yes | AI24: Med
A25: Punish | B25: 1 | C25: Uncommon | D25: Damage 5 | E25: Root | G25: Deal 5 damage and Root the target. | H25: Chebyshev | I25: 1 | J25: 1 | K25: Punish | L25: Knight | M25: Melee Attack | N25: Attack | O25: Tile | P25: Single | R25: Tile | S25: Single | Z25: FALSE | AD25: =IF($AC25="","NEW","Live") | AF25: Yes | AI25: High
A26: Battle Focus | B26: 1 | C26: Uncommon | D26: Double Next Attack | G26: Your next attack deals double damage. | H26: SelfTile | I26: 0 | J26: 0 | K26: BattleFocus | L26: Knight | M26: Buff (Offensive) | N26: Attack | O26: Self | P26: Single | Z26: FALSE | AD26: =IF($AC26="","NEW","Live") | AF26: Yes | AI26: Med
A27: Warcry | B27: 2 | C27: Rare | D27: Strength 3 | E27: Draw 1 | G27: Gain 3 Strength and draw a card. | H27: SelfTile | I27: 0 | J27: 0 | K27: Warcry | L27: Knight | M27: Buff (Offensive) | N27: Attack | O27: Self | P27: Single | R27: Self | S27: Single | Z27: FALSE | AD27: =IF($AC27="","NEW","Live") | AF27: Yes | AI27: Med
A28: Shield of Faith | B28: 1 | C28: Common | D28: Shield 5 | G28: Give an ally 5 Shield. | H28: Manhattan | I28: 1 | J28: 2 | K28: ShieldOfFaith | L28: Knight | M28: Buff (Defensive) | N28: Defence | O28: Tile | P28: Single | Z28: FALSE | AD28: =IF($AC28="","NEW","Live") | AF28: Yes | AH28: D&D | AI28: Med
A29: Unbreakable | B29: 3 | C29: Legendary | D29: Shield 10 | E29: Block 5 | F29: Double Shield | G29: Gain 10 Shield and 5 Block charges. Your next Shield gain is doubled. | H29: SelfTile | I29: 0 | J29: 0 | K29: Unbreakable | L29: Knight | M29: Buff (Defensive) | N29: Defence | O29: Self | P29: Single | R29: Self | S29: Single | U29: Self | V29: Single | Z29: FALSE | AD29: =IF($AC29="","NEW","Live") | AF29: Yes | AI29: Low
A30: Retribution | B30: 2 | C30: Rare | G30: Whenever you take damage this turn, deal 3 back to the attacker. | H30: SelfTile | I30: 0 | J30: 0 | K30: Retribution | L30: Knight | M30: Buff (Defensive) | N30: Defence | Z30: FALSE | AD30: =IF($AC30="","NEW","Live") | AE30: Fits the Knight fantasy better than anything else on this list. | AF30: Needs Status | AG30: ThornsStatus with an OnTakeDamage hook that calls TakeDamage on DamageInfo.Source. MaxParryBounces already shows how to stop the recursion. | AH30: MtG / Diablo | AI30: High
A31: Bastion | B31: 2 | C31: Rare | G31: Your Shield is no longer wiped at the start of your turn. | H31: SelfTile | I31: 0 | J31: 0 | K31: Bastion | L31: Knight | M31: Buff (Defensive) | N31: Defence | Z31: FALSE | AD31: =IF($AC31="","NEW","Live") | AE31: Directly answers the balance note that Shield is worse than Block right now. | AF31: Needs Status | AG31: PersistentShieldStatus, or a flag ShieldStatus checks in its OnTurnStart before clearing. | AH31: StS Barricade | AI31: High
A32: Counterattack | B32: 1 | C32: Rare | G32: The next time you Block an attack, deal 5 damage back. | H32: SelfTile | I32: 0 | J32: 0 | K32: Counterattack | L32: Knight | M32: Buff (Defensive) | N32: Attack, Defence | Z32: FALSE | AD32: =IF($AC32="","NEW","Live") | AF32: Needs Hook | AG32: An OnBlocked notification. BlockStatus currently just reduces DamageInfo and tells nobody. | AH32: FFT Blade Grasp | AI32: Med
A33: Momentum | B33: 1 | C33: Uncommon | G33: Deal 4 damage. Permanently gains +2 damage each time you play it this battle. | H33: Chebyshev | I33: 1 | J33: 1 | K33: Momentum | L33: Knight | M33: Melee Attack | N33: Attack | Z33: FALSE | AD33: =IF($AC33="","NEW","Live") | AE33: The Card/CardData split was built for this - it is cheaper than it looks. | AF33: Needs System | AG33: Per-copy mutable state on Card (CardData is shared, so the counter cannot live there). Card already exists for exactly this. | AH33: StS Ritual Dagger | AI33: High
A34: Oath of Protection | B34: 2 | C34: Rare | G34: Damage dealt to the chosen ally is redirected to you. | H34: Manhattan | I34: 1 | J34: 2 | K34: OathOfProtection | L34: Knight | M34: Buff (Defensive) | N34: Defence | Z34: FALSE | AD34: =IF($AC34="","NEW","Live") | AF34: Needs Status | AG34: RedirectStatus on the ally with an OnTakeDamage hook that forwards to the guardian. Needs a guard against two knights redirecting to each other. | AH34: D&D Paladin | AI34: Med
A35: Exhausting Charge | B35: 1 | C35: Common | D35: Damage 10 | G35: Deal 10 damage. Exhaust. | H35: Chebyshev | I35: 1 | J35: 1 | K35: ExhaustingCharge | L35: Knight | M35: Melee Attack | N35: Attack | O35: Tile | P35: Single | Z35: FALSE | AD35: =IF($AC35="","NEW","Live") | AE35: Cheapest new keyword to add - CardKeywordEntry was designed for it. | AF35: Needs System | AG35: Exhaust as a CardKeywordType plus removal from the pile cycle in Character. The keyword list already exists to be extended. | AH35: Slay the Spire | AI35: High
A36: Shield Throw | B36: 2 | C36: Uncommon | G36: Deal 5 damage to every enemy in a straight line. | H36: Chebyshev | I36: 1 | J36: 3 | K36: ShieldThrow | L36: Knight | M36: RangedAttack | N36: Attack | Z36: FALSE | AD36: =IF($AC36="","NEW","Live") | AE36: Possibly buildable already via a painted EffectPattern. | AF36: Needs Effect | AG36: A line/pierce area. EffectPattern can paint a line, so this may only need a Line pattern asset rather than new code - worth checking first. | AH36: Captain America / Into the Breach | AI36: High
A37: Judgement | B37: 3 | C37: Legendary | G37: Deal damage equal to your current Shield. | H37: Chebyshev | I37: 1 | J37: 1 | K37: Judgement | L37: Knight | M37: Melee Attack | N37: Attack | Z37: FALSE | AD37: =IF($AC37="","NEW","Live") | AE37: Turns the Knight defensive pile into a win condition. | AF37: Needs Effect | AG37: ScalingDamageEffect that reads a stat off the source at resolve time. Actions are stateless, so the value must come from ActionContext. | AH37: StS Body Slam | AI37: High
A38: Fortress | B38: 3 | C38: Legendary | G38: Gain Shield equal to twice your Block charges. | H38: SelfTile | I38: 0 | J38: 0 | K38: Fortress | L38: Knight | M38: Buff (Defensive) | N38: Defence | Z38: FALSE | AD38: =IF($AC38="","NEW","Live") | AF38: Needs Effect | AG38: Same ScalingDamageEffect machinery, reading StatusStacks(StatusType.Block). | AH38: StS | AI38: Low
A39: Reprisal | B39: 2 | C39: Rare | G39: Deal damage equal to what you took last turn. | H39: Chebyshev | I39: 1 | J39: 1 | K39: Reprisal | L39: Knight | M39: Melee Attack | N39: Attack | Z39: FALSE | AD39: =IF($AC39="","NEW","Live") | AF39: Needs System | AG39: A per-turn damage-taken tally on Character, reset on turn start. | AH39: Darkest Dungeon | AI39: Low
A40: Avatar of Steel | B40: 3 | C40: Legendary | D40: Shield 15 | E40: Strength 3 | F40: Draw 1 | G40: Gain 15 Shield and 3 Strength, then draw a card. | H40: SelfTile | I40: 0 | J40: 0 | K40: AvatarOfSteel | L40: Knight | M40: Buff (Defensive) | N40: Defence, Attack | O40: Self | P40: Single | R40: Self | S40: Single | U40: Self | V40: Single | Z40: FALSE | AD40: =IF($AC40="","NEW","Live") | AF40: Yes | AI40: Med
A41: Earthshatter | B41: 3 | C41: Rare | D41: Damage 8 | G41: Deal 8 damage to everything in a 3x3 area. | H41: Chebyshev | I41: 1 | J41: 2 | K41: Earthshatter | L41: Knight | M41: Melee Attack | N41: Attack | O41: Tile | P41: Chebyshev 0-1 | Z41: FALSE | AD41: =IF($AC41="","NEW","Live") | AF41: Yes | AH41: D&D Shatter | AI41: Med
A42: Whirlwind | B42: 2 | C42: Rare | D42: Damage 6 | G42: Deal 6 damage to everything around you. | H42: SelfTile | I42: 0 | J42: 0 | K42: Whirlwind | L42: Knight | M42: Melee Attack | N42: Attack | O42: Self | P42: Chebyshev 0-1 | Z42: FALSE | AD42: =IF($AC42="","NEW","Live") | AF42: Yes | AH42: Diablo | AI42: High
A43: Immovable Object | B43: 3 | C43: Legendary | D43: Taunt | E43: Shield 10 | F43: Block 5 | G43: Taunt the target. Gain 10 Shield and 5 Block charges. | H43: Chebyshev | I43: 1 | J43: 3 | K43: ImmovableObject | L43: Knight | M43: Buff (Defensive) | N43: Defence | O43: Tile | P43: Single | R43: Self | S43: Single | U43: Self | V43: Single | Z43: FALSE | AD43: =IF($AC43="","NEW","Live") | AF43: Yes | AI43: Med
A44: Executioner | B44: 3 | C44: Rare | D44: Damage 15 | G44: Deal 15 damage. | H44: Chebyshev | I44: 1 | J44: 1 | K44: Executioner | L44: Knight | M44: Melee Attack | N44: Attack | O44: Tile | P44: Single | Z44: FALSE | AD44: =IF($AC44="","NEW","Live") | AF44: Yes | AI44: Low
A45: Banner of Valor | B45: 3 | C45: Rare | G45: Summon a banner granting every nearby ally 1 Strength. | H45: Chebyshev | I45: 1 | J45: 2 | K45: BannerOfValor | L45: Knight | M45: Summon | N45: Summon, Attack | Z45: FALSE | AD45: =IF($AC45="","NEW","Live") | AE45: Nearly free: Totem + AuraData already do auras, there is just no prefab using them. | AF45: Needs System | AG45: A Totem prefab with a Strength aura. AuraData already supports this - it needs a prefab authored, not new code. | AH45: Warcraft | AI45: High
A46: Divine Intervention | B46: 3 | C46: Legendary | D46: Heal 10 | E46: Shield 10 | G46: Every ally within 2 tiles heals 10 and gains 10 Shield. | H46: SelfTile | I46: 0 | J46: 0 | K46: DivineIntervention | L46: Knight | M46: Heal | N46: Healing, Defence | O46: Self | P46: Manhattan 0-2 | R46: Self | S46: Manhattan 0-2 | Z46: FALSE | AD46: =IF($AC46="","NEW","Live") | AF46: Yes | AH46: D&D | AI46: Med
A47: Siege Breaker | B47: 3 | C47: Rare | D47: Damage 10 | G47: Deal 10 damage to every enemy within 2 tiles. | H47: SelfTile | I47: 0 | J47: 0 | K47: SiegeBreaker | L47: Knight | M47: Melee Attack | N47: Attack | O47: Self | P47: Manhattan 0-2 | Z47: FALSE | AD47: =IF($AC47="","NEW","Live") | AF47: Yes | AI47: Med
A48: Final Bulwark | B48: 3 | C48: Legendary | D48: Block 5 | E48: Parry 1 | G48: Gain 5 Block charges and 3 Parry charges. | H48: SelfTile | I48: 0 | J48: 0 | K48: FinalBulwark | L48: Knight | M48: Buff (Defensive) | N48: Defence | O48: Self | P48: Single | R48: Self | S48: Single | Z48: FALSE | AD48: =IF($AC48="","NEW","Live") | AE48: Parry 3 would need a Parry 3 effect asset; two entries is the buildable version. | AF48: Yes | AI48: Low
A49: Heroic Sacrifice | B49: 2 | C49: Legendary | G49: Lose half your health. Deal that much to every enemy within 2 tiles. | H49: SelfTile | I49: 0 | J49: 0 | K49: HeroicSacrifice | L49: Knight | M49: Melee Attack | N49: Attack | Z49: FALSE | AD49: =IF($AC49="","NEW","Live") | AF49: Needs Effect | AG49: SelfDamageEffect plus the same scaling-damage machinery as Judgement. | AH49: Darkest Dungeon | AI49: Low

Sheet Mage Ideas
A1: Card Name | B1: Cost | C1: Rarity | D1: Effect 1 | E1: Effect 2 | F1: Effect 3 | G1: Description | H1: Range Shape | I1: Range Min | J1: Range Max | K1: Key | L1: Class | M1: Folder | N1: Tags | O1: Aim 1 | P1: Area 1 | Q1: Cond 1 | R1: Aim 2 | S1: Area 2 | T1: Cond 2 | U1: Aim 3 | V1: Area 3 | W1: Cond 3 | X1: Cost Cond | Y1: Keywords | Z1: No Reward | AA1: Rotatable | AB1: Animation | AC1: GUID | AD1: Sync | AE1: Notes | AF1: Buildable | AG1: Engine Work | AH1: Source | AI1: Priority
A2: Frostbolt | B2: 1 | C2: Common | D2: Damage 6 | G2: Deal 6 damage at range. | H2: Chebyshev | I2: 1 | J2: 4 | K2: Frostbolt | L2: Mage | M2: RangedAttack | N2: Attack | O2: Tile | P2: Single | Z2: FALSE | AD2: =IF($AC2="","NEW","Live") | AF2: Yes | AI2: Med
A3: Arcane Missile | B3: 0 | C3: Common | D3: Damage 3 | G3: Deal 3 damage at range. | H3: Chebyshev | I3: 1 | J3: 4 | K3: ArcaneMissile | L3: Mage | M3: RangedAttack | N3: Attack | O3: Tile | P3: Single | Z3: FALSE | AD3: =IF($AC3="","NEW","Live") | AE3: The game has almost no 0-cost cards; the curve needs a floor. | AF3: Yes | AH3: D&D | AI3: High
A4: Scorch | B4: 1 | C4: Common | D4: Damage 5 | G4: Deal 5 damage. | H4: Chebyshev | I4: 1 | J4: 3 | K4: Scorch | L4: Mage | M4: RangedAttack | N4: Attack, Fire | O4: Tile | P4: Single | Z4: FALSE | AD4: =IF($AC4="","NEW","Live") | AF4: Yes | AI4: Med
A5: Chain Lightning | B5: 2 | C5: Rare | D5: Damage 4 | G5: Deal 4 damage to everything within 2 tiles of the target. | H5: Chebyshev | I5: 1 | J5: 3 | K5: ChainLightning | L5: Mage | M5: RangedAttack | N5: Attack | O5: Tile | P5: Manhattan 0-2 | Z5: FALSE | AD5: =IF($AC5="","NEW","Live") | AF5: Yes | AH5: D&D | AI5: Med
A6: Meteor | B6: 3 | C6: Rare | D6: Damage 12 | G6: Deal 12 damage in a 3x3 area. | H6: Chebyshev | I6: 1 | J6: 4 | K6: Meteor | L6: Mage | M6: RangedAttack | N6: Attack, Fire | O6: Tile | P6: Chebyshev 0-1 | Z6: FALSE | AD6: =IF($AC6="","NEW","Live") | AF6: Yes | AH6: D&D Meteor Swarm | AI6: Med
A7: Mana Shield | B7: 1 | C7: Uncommon | D7: Shield 7 | G7: Gain 7 Shield. | H7: SelfTile | I7: 0 | J7: 0 | K7: ManaShield | L7: Mage | M7: Buff (Defensive) | N7: Defence | O7: Self | P7: Single | Z7: FALSE | AD7: =IF($AC7="","NEW","Live") | AF7: Yes | AI7: Med
A8: Greater Heal | B8: 2 | C8: Uncommon | D8: Heal 15 | G8: Heal an ally for 15. | H8: Manhattan | I8: 1 | J8: 2 | K8: GreaterHeal | L8: Mage | M8: Heal | N8: Healing | O8: Tile | P8: Single | Z8: FALSE | AD8: =IF($AC8="","NEW","Live") | AF8: Yes | AI8: Med
A9: Blizzard | B9: 3 | C9: Rare | D9: Damage 6 | G9: Deal 6 damage to everything within 3 tiles of the target. | H9: Chebyshev | I9: 1 | J9: 4 | K9: Blizzard | L9: Mage | M9: RangedAttack | N9: Attack | O9: Tile | P9: Manhattan 0-3 | Z9: FALSE | AD9: =IF($AC9="","NEW","Live") | AF9: Yes | AH9: D&D / WoW | AI9: Med
A10: Magic Missile | B10: 1 | C10: Common | G10: Deal 3 damage to each of three different enemies. | H10: Chebyshev | I10: 1 | J10: 4 | K10: MagicMissile | L10: Mage | M10: RangedAttack | N10: Attack | Z10: FALSE | AD10: =IF($AC10="","NEW","Live") | AF10: Needs Effect | AG10: Multi-target selection. Every effect today lands on one aim tile plus an area; picking N separate tiles is a different targeting model. | AH10: D&D | AI10: Low
A11: Prismatic Ward | B11: 2 | C11: Rare | D11: Shield 5 | E11: Block 2 | F11: Parry 1 | G11: Gain 5 Shield, 2 Block charges and 1 Parry charge. | H11: SelfTile | I11: 0 | J11: 0 | K11: PrismaticWard | L11: Mage | M11: Buff (Defensive) | N11: Defence | O11: Self | P11: Single | R11: Self | S11: Single | U11: Self | V11: Single | Z11: FALSE | AD11: =IF($AC11="","NEW","Live") | AF11: Yes | AH11: D&D | AI11: Med
A12: Blink | B12: 0 | C12: Uncommon | D12: Move | G12: Teleport up to 3 tiles. | H12: Chebyshev | I12: 1 | J12: 3 | K12: Blink | L12: Mage | M12: Movement | N12: Movement | O12: Tile | P12: Single | Z12: FALSE | AD12: =IF($AC12="","NEW","Live") | AF12: Yes | AH12: D&D Misty Step | AI12: High
A13: Force Push | B13: 1 | C13: Uncommon | G13: Push the target 2 tiles away. | H13: Chebyshev | I13: 1 | J13: 3 | K13: ForcePush | L13: Mage | M13: Debuff | N13: Movement | Z13: FALSE | AD13: =IF($AC13="","NEW","Live") | AF13: Needs Effect | AG13: PushEffect - shared with the Knight cards above. | AH13: Into the Breach | AI13: High
A14: Wall of Fire | B14: 2 | C14: Rare | G14: Set three tiles alight. Anything standing there at end of turn takes 4 damage. | H14: Chebyshev | I14: 1 | J14: 3 | K14: WallOfFire | L14: Mage | M14: Summon | N14: Fire, Summon | Z14: FALSE | AD14: =IF($AC14="","NEW","Live") | AE14: The pitch is "tiles mutate the characters standing on them" - hazards are the most on-theme thing missing. | AF14: Needs System | AG14: Persistent tile hazards - a tile that carries an effect with no character on it. GridTile has no such concept yet. | AH14: D&D | AI14: High
A15: Repulsion Ward | B15: 2 | C15: Rare | G15: Push every adjacent enemy 2 tiles away. | H15: SelfTile | I15: 0 | J15: 0 | K15: RepulsionWard | L15: Mage | M15: Debuff | N15: Defence, Movement | Z15: FALSE | AD15: =IF($AC15="","NEW","Live") | AF15: Needs Effect | AG15: PushEffect with an area, pushing outward from the caster rather than along one aim direction. | AH15: Into the Breach | AI15: Med
A16: Grease | B16: 1 | C16: Common | D16: Root | G16: Root everything in a 3x3 area. | H16: Chebyshev | I16: 1 | J16: 3 | K16: Grease | L16: Mage | M16: Debuff | N16: Movement | O16: Tile | P16: Manhattan 0-1 | Z16: FALSE | AD16: =IF($AC16="","NEW","Live") | AF16: Yes | AH16: D&D | AI16: High
A17: Dimension Door | B17: 1 | C17: Rare | G17: Swap places with any character on the board. | H17: Chebyshev | I17: 1 | J17: 4 | K17: DimensionDoor | L17: Mage | M17: Movement | N17: Movement | Z17: FALSE | AD17: =IF($AC17="","NEW","Live") | AF17: Needs Effect | AG17: SwapEffect - shared with Interpose. | AH17: D&D | AI17: Med
A18: Web | B18: 1 | C18: Uncommon | D18: Root | E18: Weaken 2 | G18: Root and apply 2 Weaken in a 3x3 area. | H18: Chebyshev | I18: 1 | J18: 3 | K18: Web | L18: Mage | M18: Debuff | N18: Movement | O18: Tile | P18: Manhattan 0-1 | R18: Tile | S18: Manhattan 0-1 | Z18: FALSE | AD18: =IF($AC18="","NEW","Live") | AF18: Yes | AH18: D&D | AI18: Med
A19: Levitate | B19: 1 | C19: Uncommon | G19: An ally may move again this turn. | H19: Manhattan | I19: 1 | J19: 2 | K19: Levitate | L19: Mage | M19: Movement | N19: Movement | Z19: FALSE | AD19: =IF($AC19="","NEW","Live") | AF19: Needs Effect | AG19: GrantMoveEffect - hand a free move to another character. MoveEffect always moves the source. | AH19: D&D | AI19: Low
A20: Thunderwave | B20: 2 | C20: Uncommon | D20: Damage 5 | G20: Deal 5 damage in a cone and push everything it hits. | H20: Chebyshev | I20: 1 | J20: 1 | K20: Thunderwave | L20: Mage | M20: RangedAttack | N20: Attack | O20: Tile | P20: Pattern:Cone3 | Z20: FALSE | AD20: =IF($AC20="","NEW","Live") | AE20: Half of this is buildable today - drop the push and it ships. | AF20: Needs Effect | AG20: The damage half already works via the Cone3 pattern; only the push is missing. | AH20: D&D | AI20: High
A21: Misty Step | B21: 1 | C21: Common | D21: Move | E21: Dodge | G21: Teleport 2 tiles and gain Dodge. | H21: Chebyshev | I21: 1 | J21: 2 | K21: MistyStep | L21: Mage | M21: Movement | N21: Movement, Defence | O21: Tile | P21: Single | R21: Self | S21: Single | Z21: FALSE | AD21: =IF($AC21="","NEW","Live") | AF21: Yes | AH21: D&D | AI21: Med
A22: Curse | B22: 1 | C22: Common | D22: Weaken 3 | G22: Apply 3 Weaken. | H22: Chebyshev | I22: 1 | J22: 3 | K22: Curse | L22: Mage | M22: Debuff | N22: Attack | O22: Tile | P22: Single | Z22: FALSE | AD22: =IF($AC22="","NEW","Live") | AF22: Yes | AI22: Med
A23: Hex | B23: 2 | C23: Uncommon | D23: Weaken 3 | E23: Poison 3 | G23: Apply 3 Weaken and 3 Poison. | H23: Chebyshev | I23: 1 | J23: 3 | K23: Hex | L23: Mage | M23: Debuff | N23: Poison | O23: Tile | P23: Single | R23: Tile | S23: Single | Z23: FALSE | AD23: =IF($AC23="","NEW","Live") | AF23: Yes | AH23: D&D | AI23: Med
A24: Slow | B24: 1 | C24: Uncommon | D24: Root | E24: Weaken 2 | G24: Root the target and apply 2 Weaken. | H24: Chebyshev | I24: 1 | J24: 3 | K24: Slow | L24: Mage | M24: Debuff | N24: Movement | O24: Tile | P24: Single | R24: Tile | S24: Single | Z24: FALSE | AD24: =IF($AC24="","NEW","Live") | AF24: Yes | AH24: D&D | AI24: Med
A25: Deep Freeze | B25: 2 | C25: Rare | D25: Damage 5 | E25: Freeze | G25: Deal 5 damage and Freeze the target. | H25: Chebyshev | I25: 1 | J25: 3 | K25: DeepFreeze | L25: Mage | M25: Debuff | N25: Attack | O25: Tile | P25: Single | R25: Tile | S25: Single | Z25: FALSE | AD25: =IF($AC25="","NEW","Live") | AF25: Yes | AI25: Med
A26: Haste | B26: 2 | C26: Rare | D26: Double Next Attack | E26: Draw 1 | G26: Your next attack is doubled. Draw a card. | H26: SelfTile | I26: 0 | J26: 0 | K26: Haste | L26: Mage | M26: Buff (Offensive) | N26: Attack | O26: Self | P26: Single | R26: Self | S26: Single | Z26: FALSE | AD26: =IF($AC26="","NEW","Live") | AF26: Yes | AH26: D&D | AI26: Med
A27: Bless | B27: 1 | C27: Uncommon | D27: Strength 2 | G27: Give an ally 2 Strength. | H27: Manhattan | I27: 1 | J27: 2 | K27: Bless | L27: Mage | M27: Buff (Offensive) | N27: Attack | O27: Tile | P27: Single | Z27: FALSE | AD27: =IF($AC27="","NEW","Live") | AF27: Yes | AH27: D&D | AI27: Med
A28: Mass Curse | B28: 3 | C28: Rare | D28: Weaken 3 | G28: Apply 3 Weaken to everything within 2 tiles of the target. | H28: Chebyshev | I28: 1 | J28: 4 | K28: MassCurse | L28: Mage | M28: Debuff | N28: Attack | O28: Tile | P28: Manhattan 0-2 | Z28: FALSE | AD28: =IF($AC28="","NEW","Live") | AF28: Yes | AI28: Med
A29: Mirror Image | B29: 2 | C29: Rare | D29: Dodge 2 | G29: Gain 2 Dodge charges. | H29: SelfTile | I29: 0 | J29: 0 | K29: MirrorImage | L29: Mage | M29: Buff (Defensive) | N29: Defence | O29: Self | P29: Single | Z29: FALSE | AD29: =IF($AC29="","NEW","Live") | AF29: Yes | AH29: D&D | AI29: Med
A30: Stoneskin | B30: 2 | C30: Uncommon | D30: Block 3 | G30: Give an ally 3 Block charges. | H30: Manhattan | I30: 1 | J30: 2 | K30: Stoneskin | L30: Mage | M30: Buff (Defensive) | N30: Defence | O30: Tile | P30: Single | Z30: FALSE | AD30: =IF($AC30="","NEW","Live") | AF30: Yes | AH30: D&D | AI30: Med
A31: Contagion | B31: 3 | C31: Rare | D31: Poison 4 | G31: Apply 4 Poison to everything within 2 tiles of the target. | H31: Chebyshev | I31: 1 | J31: 4 | K31: Contagion | L31: Mage | M31: Debuff | N31: Poison | O31: Tile | P31: Manhattan 0-2 | Z31: FALSE | AD31: =IF($AC31="","NEW","Live") | AF31: Yes | AI31: Med
A32: Immolate | B32: 2 | C32: Rare | G32: Deal 4 damage and set the target Burning for 3. | H32: Chebyshev | I32: 1 | J32: 3 | K32: Immolate | L32: Mage | M32: RangedAttack | N32: Fire | Z32: FALSE | AD32: =IF($AC32="","NEW","Live") | AE32: The Fire tag exists on CardTag with nothing behind it. | AF32: Needs Status | AG32: BurnStatus plus StatusType.Burn appended. Nearly a copy of PoisonStatus but unblockable-on-hit rather than at turn end - which is exactly why it should reuse the same shape. | AH32: WoW / MtG | AI32: High
A33: Counterspell | B33: 1 | C33: Rare | G33: Negate the next card that enemy plays. | H33: Chebyshev | I33: 1 | J33: 4 | K33: Counterspell | L33: Mage | M33: Debuff | N33: Defence | Z33: FALSE | AD33: =IF($AC33="","NEW","Live") | AF33: Needs Hook | AG33: An OnCardPlayed gate. ActRefusal already denies actions - this is the same idea aimed at one card rather than the turn. | AH33: MtG / D&D | AI33: Med
A34: Time Stop | B34: 3 | C34: Legendary | G34: Take another turn. | H34: SelfTile | I34: 0 | J34: 0 | K34: TimeStop | L34: Mage | M34: Buff (Offensive) | N34: Attack | Z34: FALSE | AD34: =IF($AC34="","NEW","Live") | AE34: Cheap to describe, expensive to define. Park it. | AF34: Needs System | AG34: Turn economy. There is deliberately no turn order today - clicking a character makes it active - so "another turn" needs defining first. | AH34: D&D | AI34: Low
A35: Arcane Recovery | B35: 1 | C35: Rare | G35: Gain 2 energy. | H35: SelfTile | I35: 0 | J35: 0 | K35: ArcaneRecovery | L35: Mage | M35: Buff (Offensive) | N35: Attack | Z35: FALSE | AD35: =IF($AC35="","NEW","Live") | AF35: Needs Effect | AG35: EnergyEffect. Energy lives on Character, so the effect is small - the balance risk is not. | AH35: StS | AI35: Med
A36: Spell Echo | B36: 2 | C36: Rare | G36: The next card you play resolves twice. | H36: SelfTile | I36: 0 | J36: 0 | K36: SpellEcho | L36: Mage | M36: Buff (Offensive) | N36: Attack | Z36: FALSE | AD36: =IF($AC36="","NEW","Live") | AF36: Needs System | AG36: Re-running a card's actions needs CardPlayManager to keep the last play around. DoubleNextAttack is the narrow version that already works. | AH36: StS Amplify | AI36: Med
A37: Polymorph | B37: 2 | C37: Legendary | G37: The target cannot act or be acted upon for 2 turns. | H37: Chebyshev | I37: 1 | J37: 3 | K37: Polymorph | L37: Mage | M37: Debuff | N37: Attack | Z37: FALSE | AD37: =IF($AC37="","NEW","Live") | AF37: Needs Status | AG37: A stronger Frozen - ActRefusal plus a targeting refusal. TargetSelector has no concept of an untargetable character. | AH37: D&D / Hearthstone | AI37: Low
A38: Wall of Force | B38: 2 | C38: Rare | G38: Three tiles become impassable for 2 turns. | H38: Chebyshev | I38: 1 | J38: 3 | K38: WallOfForce | L38: Mage | M38: Summon | N38: Defence | Z38: FALSE | AD38: =IF($AC38="","NEW","Live") | AE38: Build alongside Wall of Fire; one system covers both. | AF38: Needs System | AG38: Tile blocking - same tile-state system as Wall of Fire, minus the damage. | AH38: D&D / Into the Breach | AI38: High
A39: Scorching Ray | B39: 1 | C39: Uncommon | G39: Deal 3 damage three times. | H39: Chebyshev | I39: 1 | J39: 3 | K39: ScorchingRay | L39: Mage | M39: RangedAttack | N39: Fire | Z39: FALSE | AD39: =IF($AC39="","NEW","Live") | AE39: Interacts with Block in a way the game has no card for yet. | AF39: Needs Effect | AG39: A repeat count on an effect entry. Matters because Block reduces each hit separately - three small hits beat one big one into Block. | AH39: D&D | AI39: High
A40: Arcane Intellect | B40: 1 | C40: Uncommon | D40: Draw 2 | G40: Draw 2 cards. | H40: SelfTile | I40: 0 | J40: 0 | K40: ArcaneIntellect | L40: Mage | M40: Buff (Offensive) | N40: Attack | O40: Self | P40: Single | Z40: FALSE | AD40: =IF($AC40="","NEW","Live") | AE40: DrawEffect is used by exactly one totem right now. | AF40: Yes | AH40: WoW | AI40: High
A41: Sacrifice | B41: 0 | C41: Rare | G41: Lose 5 health. Draw 2 cards. | H41: SelfTile | I41: 0 | J41: 0 | K41: Sacrifice | L41: Mage | M41: Buff (Offensive) | N41: Attack | Z41: FALSE | AD41: =IF($AC41="","NEW","Live") | AF41: Needs Effect | AG41: SelfDamageEffect - HealEffect with a negative amount would work but reads badly and skips the damage hooks. | AH41: StS Bloodletting | AI41: Med
A42: Sunburst | B42: 3 | C42: Legendary | D42: Damage 10 | G42: Deal 10 damage to everything within 3 tiles of the target. | H42: Chebyshev | I42: 1 | J42: 4 | K42: Sunburst | L42: Mage | M42: RangedAttack | N42: Attack, Fire | O42: Tile | P42: Manhattan 0-3 | Z42: FALSE | AD42: =IF($AC42="","NEW","Live") | AF42: Yes | AH42: D&D | AI42: Med
A43: Cataclysm | B43: 3 | C43: Legendary | D43: Damage 20 | G43: Deal 20 damage to one target. | H43: Chebyshev | I43: 1 | J43: 4 | K43: Cataclysm | L43: Mage | M43: RangedAttack | N43: Attack, Fire | O43: Tile | P43: Single | Z43: FALSE | AD43: =IF($AC43="","NEW","Live") | AF43: Yes | AI43: Low
A44: Mass Healing Word | B44: 3 | C44: Rare | D44: Heal 10 | G44: Every ally within 2 tiles heals 10. | H44: SelfTile | I44: 0 | J44: 0 | K44: MassHealingWord | L44: Mage | M44: Heal | N44: Healing | O44: Self | P44: Manhattan 0-2 | Z44: FALSE | AD44: =IF($AC44="","NEW","Live") | AF44: Yes | AH44: D&D | AI44: Med
A45: Summon Elemental | B45: 3 | C45: Rare | G45: Summon an elemental that fights for you. | H45: Chebyshev | I45: 1 | J45: 2 | K45: SummonElemental | L45: Mage | M45: Summon | N45: Summon | Z45: FALSE | AD45: =IF($AC45="","NEW","Live") | AE45: Check SummonSkeletonWarrior first; this may be mostly authored already. | AF45: Needs System | AG45: A summoned character with its own deck and turn. SummonSkeletonWarrior already exists for enemies - this is the player-side version and may be closer than it looks. | AH45: D&D | AI45: High
A46: Ice Age | B46: 3 | C46: Legendary | D46: Freeze | G46: Freeze everything within 2 tiles of the target. | H46: Chebyshev | I46: 1 | J46: 4 | K46: IceAge | L46: Mage | M46: Debuff | N46: Attack | O46: Tile | P46: Manhattan 0-2 | Z46: FALSE | AD46: =IF($AC46="","NEW","Live") | AF46: Yes | AI46: Med
A47: Arcane Totem | B47: 2 | C47: Uncommon | D47: SummonTotem | G47: Summon a totem that shields nearby allies when they attack. | H47: Chebyshev | I47: 1 | J47: 3 | K47: ArcaneTotem | L47: Mage | M47: Summon | N47: Summon, Defence | O47: Tile | P47: Single | Z47: FALSE | AD47: =IF($AC47="","NEW","Live") | AE47: Reuses the existing Totem prefab as-is. | AF47: Yes | AI47: Med
A48: Chain Heal | B48: 2 | C48: Uncommon | D48: Heal 5 | G48: Heal everything within 2 tiles of the target for 5. | H48: Chebyshev | I48: 1 | J48: 3 | K48: ChainHeal | L48: Mage | M48: Heal | N48: Healing | O48: Tile | P48: Manhattan 0-2 | Z48: FALSE | AD48: =IF($AC48="","NEW","Live") | AF48: Yes | AH48: WoW | AI48: Med
A49: Disintegrate | B49: 3 | C49: Legendary | D49: Damage 25 | G49: Deal 25 damage to one target. | H49: Chebyshev | I49: 1 | J49: 4 | K49: Disintegrate | L49: Mage | M49: RangedAttack | N49: Attack | O49: Tile | P49: Single | Z49: FALSE | AD49: =IF($AC49="","NEW","Live") | AF49: Yes | AH49: D&D | AI49: Low
A50: Prismatic Spray | B50: 3 | C50: Rare | D50: Damage 6 | E50: Weaken 3 | G50: Deal 6 damage in a cone and apply 3 Weaken. | H50: Chebyshev | I50: 1 | J50: 1 | K50: PrismaticSpray | L50: Mage | M50: RangedAttack | N50: Attack | O50: Tile | P50: Pattern:Cone3 | R50: Tile | S50: Pattern:Cone3 | Z50: FALSE | AD50: =IF($AC50="","NEW","Live") | AF50: Yes | AH50: D&D | AI50: Med
A51: Font of Power | B51: 3 | C51: Legendary | D51: Strength 3 | E51: Double Next Attack | F51: Draw 2 | G51: Gain 3 Strength, double your next attack, and draw 2. | H51: SelfTile | I51: 0 | J51: 0 | K51: FontOfPower | L51: Mage | M51: Buff (Offensive) | N51: Attack | O51: Self | P51: Single | R51: Self | S51: Single | U51: Self | V51: Single | Z51: FALSE | AD51: =IF($AC51="","NEW","Live") | AF51: Yes | AI51: Med

Sheet Rogue Ideas
A1: Card Name | B1: Cost | C1: Rarity | D1: Effect 1 | E1: Effect 2 | F1: Effect 3 | G1: Description | H1: Range Shape | I1: Range Min | J1: Range Max | K1: Key | L1: Class | M1: Folder | N1: Tags | O1: Aim 1 | P1: Area 1 | Q1: Cond 1 | R1: Aim 2 | S1: Area 2 | T1: Cond 2 | U1: Aim 3 | V1: Area 3 | W1: Cond 3 | X1: Cost Cond | Y1: Keywords | Z1: No Reward | AA1: Rotatable | AB1: Animation | AC1: GUID | AD1: Sync | AE1: Notes | AF1: Buildable | AG1: Engine Work | AH1: Source | AI1: Priority
A2: Backstab | B2: 1 | C2: Common | D2: Damage 7 | G2: Deal 7 damage. | H2: Chebyshev | I2: 1 | J2: 1 | K2: Backstab | L2: Rogue | M2: Melee Attack | N2: Attack | O2: Tile | P2: Single | Z2: FALSE | AD2: =IF($AC2="","NEW","Live") | AF2: Yes | AH2: StS | AI2: High
A3: Twin Fangs | B3: 1 | C3: Uncommon | D3: Damage 3 | E3: Poison 2 | G3: Deal 3 damage and apply 2 Poison. | H3: Chebyshev | I3: 1 | J3: 1 | K3: TwinFangs | L3: Rogue | M3: Melee Attack | N3: Attack, Poison | O3: Tile | P3: Single | R3: Tile | S3: Single | Z3: FALSE | AD3: =IF($AC3="","NEW","Live") | AF3: Yes | AI3: High
A4: Eviscerate | B4: 2 | C4: Uncommon | D4: Damage 10 | G4: Deal 10 damage. | H4: Chebyshev | I4: 1 | J4: 1 | K4: Eviscerate | L4: Rogue | M4: Melee Attack | N4: Attack | O4: Tile | P4: Single | Z4: FALSE | AD4: =IF($AC4="","NEW","Live") | AF4: Yes | AH4: StS | AI4: Med
A5: Feint | B5: 0 | C5: Common | D5: Dodge | G5: Gain Dodge. | H5: SelfTile | I5: 0 | J5: 0 | K5: Feint | L5: Rogue | M5: Buff (Defensive) | N5: Defence | O5: Self | P5: Single | Z5: FALSE | AD5: =IF($AC5="","NEW","Live") | AF5: Yes | AI5: High
A6: Envenom | B6: 1 | C6: Common | D6: Poison 4 | G6: Apply 4 Poison. | H6: Chebyshev | I6: 1 | J6: 1 | K6: Envenom | L6: Rogue | M6: Debuff | N6: Poison | O6: Tile | P6: Single | Z6: FALSE | AD6: =IF($AC6="","NEW","Live") | AF6: Yes | AI6: Med
A7: Shadow Strike | B7: 2 | C7: Rare | D7: Damage 8 | E7: Weaken 2 | G7: Deal 8 damage and apply 2 Weaken. | H7: Chebyshev | I7: 1 | J7: 1 | K7: ShadowStrike | L7: Rogue | M7: Melee Attack | N7: Attack | O7: Tile | P7: Single | R7: Tile | S7: Single | Z7: FALSE | AD7: =IF($AC7="","NEW","Live") | AF7: Yes | AI7: Med
A8: Bandage | B8: 1 | C8: Uncommon | D8: Heal 5 | G8: Heal 5. | H8: SelfTile | I8: 0 | J8: 0 | K8: Bandage | L8: Rogue | M8: Heal | N8: Healing | O8: Self | P8: Single | Z8: FALSE | AD8: =IF($AC8="","NEW","Live") | AE8: Rogue has an empty Heal folder and no healing at all. | AF8: Yes | AI8: High
A9: Deflect | B9: 1 | C9: Common | D9: Block 2 | G9: Gain 2 Block charges. | H9: SelfTile | I9: 0 | J9: 0 | K9: Deflect | L9: Rogue | M9: Buff (Defensive) | N9: Defence | O9: Self | P9: Single | Z9: FALSE | AD9: =IF($AC9="","NEW","Live") | AF9: Yes | AH9: StS | AI9: Med
A10: Throwing Knife | B10: 0 | C10: Common | D10: Damage 3 | G10: Deal 3 damage at range. | H10: Chebyshev | I10: 1 | J10: 3 | K10: ThrowingKnife | L10: Rogue | M10: RangedAttack | N10: Attack | O10: Tile | P10: Single | Z10: FALSE | AD10: =IF($AC10="","NEW","Live") | AF10: Yes | AI10: High
A11: Fan of Knives | B11: 2 | C11: Uncommon | D11: Damage 4 | G11: Deal 4 damage to everything around you. | H11: SelfTile | I11: 0 | J11: 0 | K11: FanOfKnives | L11: Rogue | M11: Melee Attack | N11: Attack | O11: Self | P11: Chebyshev 0-1 | Z11: FALSE | AD11: =IF($AC11="","NEW","Live") | AF11: Yes | AH11: WoW | AI11: Med
A12: Shadowstep | B12: 0 | C12: Uncommon | D12: Move | G12: Move up to 3 tiles. | H12: Chebyshev | I12: 1 | J12: 3 | K12: Shadowstep | L12: Rogue | M12: Movement | N12: Movement | O12: Tile | P12: Single | Z12: FALSE | AD12: =IF($AC12="","NEW","Live") | AF12: Yes | AI12: High
A13: Vanish | B13: 1 | C13: Rare | D13: Move | E13: Dodge | G13: Move and gain Dodge. | H13: Chebyshev | I13: 1 | J13: 3 | K13: Vanish | L13: Rogue | M13: Movement | N13: Movement, Defence | O13: Tile | P13: Single | R13: Self | S13: Single | Z13: FALSE | AD13: =IF($AC13="","NEW","Live") | AF13: Yes | AH13: WoW | AI13: High
A14: Acrobatics | B14: 1 | C14: Common | D14: Move | E14: Draw 1 | G14: Move 2 tiles and draw a card. | H14: Chebyshev | I14: 1 | J14: 2 | K14: Acrobatics | L14: Rogue | M14: Movement | N14: Movement | O14: Tile | P14: Single | R14: Self | S14: Single | Z14: FALSE | AD14: =IF($AC14="","NEW","Live") | AF14: Yes | AH14: StS | AI14: Med
A15: Hamstring | B15: 1 | C15: Uncommon | D15: Damage 3 | E15: Root | G15: Deal 3 damage and Root the target. | H15: Chebyshev | I15: 1 | J15: 1 | K15: Hamstring | L15: Rogue | M15: Melee Attack | N15: Attack, Movement | O15: Tile | P15: Single | R15: Tile | S15: Single | Z15: FALSE | AD15: =IF($AC15="","NEW","Live") | AF15: Yes | AI15: High
A16: Smoke Bomb | B16: 2 | C16: Rare | D16: Dodge | E16: Weaken 2 | G16: Gain Dodge. Apply 2 Weaken to every adjacent enemy. | H16: SelfTile | I16: 0 | J16: 0 | K16: SmokeBomb | L16: Rogue | M16: Buff (Defensive) | N16: Defence | O16: Self | P16: Single | R16: Self | S16: Manhattan 0-1 | Z16: FALSE | AD16: =IF($AC16="","NEW","Live") | AF16: Yes | AH16: WoW | AI16: Med
A17: Grappling Hook | B17: 1 | C17: Uncommon | G17: Pull yourself to a distant tile. | H17: Chebyshev | I17: 1 | J17: 4 | K17: GrapplingHook | L17: Rogue | M17: Movement | N17: Movement | Z17: FALSE | AD17: =IF($AC17="","NEW","Live") | AE17: May already be expressible as Move with a bigger TargetRange. | AF17: Needs Effect | AG17: A self-pull: MoveEffect with a longer reach would nearly cover it, so check whether range alone is enough before writing anything. | AH17: Into the Breach | AI17: Low
A18: Ambush | B18: 2 | C18: Rare | G18: Move to a tile, then deal 8 damage to an adjacent enemy. | H18: Chebyshev | I18: 1 | J18: 3 | K18: Ambush | L18: Rogue | M18: Melee Attack | N18: Attack, Movement | Z18: FALSE | AD18: =IF($AC18="","NEW","Live") | AF18: Needs Effect | AG18: DashAttackEffect - shared with the Knight's Shield Charge. | AH18: FFT | AI18: High
A19: Caltrops | B19: 2 | C19: Rare | G19: Three tiles damage any enemy that enters them. | H19: Chebyshev | I19: 1 | J19: 3 | K19: Caltrops | L19: Rogue | M19: Debuff | N19: Movement | Z19: FALSE | AD19: =IF($AC19="","NEW","Live") | AF19: Needs System | AG19: Tile hazards - shared with Wall of Fire, but triggered on entry rather than at turn end. | AH19: StS / D&D | AI19: Med
A20: Slip Away | B20: 1 | C20: Common | G20: Move even if Rooted, and gain Dodge. | H20: Chebyshev | I20: 1 | J20: 2 | K20: SlipAway | L20: Rogue | M20: Movement | N20: Movement | Z20: FALSE | AD20: =IF($AC20="","NEW","Live") | AF20: Needs Status | AG20: A status that suppresses MoveRefusal. Rooted returns a reason today and nothing overrides it. | AH20: Darkest Dungeon | AI20: Low
A21: Flanking Strike | B21: 2 | C21: Uncommon | G21: Deal 5 damage, or 10 if an ally is adjacent to the target. | H21: Chebyshev | I21: 1 | J21: 1 | K21: FlankingStrike | L21: Rogue | M21: Melee Attack | N21: Attack | Z21: FALSE | AD21: =IF($AC21="","NEW","Live") | AE21: The most grid-native idea here: it makes positioning pay off directly. | AF21: Needs Effect | AG21: A conditional damage effect reading board state at resolve time - the first card whose value depends on where everyone is standing. | AH21: D&D flanking / FFT | AI21: High
A22: Deadly Poison | B22: 2 | C22: Uncommon | D22: Poison 6 | G22: Apply 6 Poison. | H22: Chebyshev | I22: 1 | J22: 1 | K22: DeadlyPoison | L22: Rogue | M22: Debuff | N22: Poison | O22: Tile | P22: Single | Z22: FALSE | AD22: =IF($AC22="","NEW","Live") | AF22: Yes | AI22: Med
A23: Crippling Toxin | B23: 2 | C23: Rare | D23: Poison 3 | E23: Weaken 3 | G23: Apply 3 Poison and 3 Weaken. | H23: Chebyshev | I23: 1 | J23: 1 | K23: CripplingToxin | L23: Rogue | M23: Debuff | N23: Poison | O23: Tile | P23: Single | R23: Tile | S23: Single | Z23: FALSE | AD23: =IF($AC23="","NEW","Live") | AF23: Yes | AI23: Med
A24: Rupture | B24: 2 | C24: Rare | D24: Damage 5 | E24: Poison 4 | G24: Deal 5 damage and apply 4 Poison. | H24: Chebyshev | I24: 1 | J24: 1 | K24: Rupture | L24: Rogue | M24: Melee Attack | N24: Attack, Poison | O24: Tile | P24: Single | R24: Tile | S24: Single | Z24: FALSE | AD24: =IF($AC24="","NEW","Live") | AF24: Yes | AI24: High
A25: Blade Flurry | B25: 2 | C25: Rare | D25: Damage 3 | E25: Double Next Attack | G25: Deal 3 damage and double your next attack. | H25: SelfTile | I25: 0 | J25: 0 | K25: BladeFlurry | L25: Rogue | M25: Buff (Offensive) | N25: Attack | O25: Tile | P25: Single | R25: Self | S25: Single | Z25: FALSE | AD25: =IF($AC25="","NEW","Live") | AF25: Yes | AI25: Med
A26: Sharpen | B26: 1 | C26: Common | D26: Strength 2 | G26: Gain 2 Strength. | H26: SelfTile | I26: 0 | J26: 0 | K26: Sharpen | L26: Rogue | M26: Buff (Offensive) | N26: Attack | O26: Self | P26: Single | Z26: FALSE | AD26: =IF($AC26="","NEW","Live") | AE26: Rogue has an empty Buff (Offensive) folder. | AF26: Yes | AI26: Med
A27: Adrenaline | B27: 1 | C27: Uncommon | D27: Draw 2 | G27: Draw 2 cards. | H27: SelfTile | I27: 0 | J27: 0 | K27: Adrenaline | L27: Rogue | M27: Buff (Offensive) | N27: Attack | O27: Self | P27: Single | Z27: FALSE | AD27: =IF($AC27="","NEW","Live") | AF27: Yes | AH27: StS | AI27: High
A28: Expose Weakness | B28: 1 | C28: Common | D28: Weaken 4 | G28: Apply 4 Weaken. | H28: Chebyshev | I28: 1 | J28: 2 | K28: ExposeWeakness | L28: Rogue | M28: Debuff | N28: Attack | O28: Tile | P28: Single | Z28: FALSE | AD28: =IF($AC28="","NEW","Live") | AF28: Yes | AI28: Med
A29: Toxic Cloud | B29: 3 | C29: Rare | D29: Poison 3 | G29: Apply 3 Poison to everything within 2 tiles of the target. | H29: Chebyshev | I29: 1 | J29: 3 | K29: ToxicCloud | L29: Rogue | M29: Debuff | N29: Poison | O29: Tile | P29: Manhattan 0-2 | Z29: FALSE | AD29: =IF($AC29="","NEW","Live") | AF29: Yes | AI29: Med
A30: Evasive Maneuvers | B30: 2 | C30: Rare | D30: Dodge 2 | G30: Gain 2 Dodge charges. | H30: SelfTile | I30: 0 | J30: 0 | K30: EvasiveManeuvers | L30: Rogue | M30: Buff (Defensive) | N30: Defence | O30: Self | P30: Single | Z30: FALSE | AD30: =IF($AC30="","NEW","Live") | AF30: Yes | AI30: Med
A31: Preparation | B31: 0 | C31: Rare | D31: Draw 1 | G31: Draw a card. | H31: SelfTile | I31: 0 | J31: 0 | K31: Preparation | L31: Rogue | M31: Buff (Offensive) | N31: Attack | O31: Self | P31: Single | Z31: FALSE | AD31: =IF($AC31="","NEW","Live") | AF31: Yes | AH31: StS | AI31: Med
A32: Combo Strike | B32: 1 | C32: Rare | G32: Deal 4 damage, plus 3 more for each card played before it this turn. | H32: Chebyshev | I32: 1 | J32: 1 | K32: ComboStrike | L32: Rogue | M32: Melee Attack | N32: Attack | Z32: FALSE | AD32: =IF($AC32="","NEW","Live") | AE32: Cheap, and it makes hand order matter for the first time. | AF32: Needs System | AG32: A cards-played-this-turn counter on Character, reset on turn start, read through ActionContext. | AH32: StS / Griftlands | AI32: High
A33: Poisoned Blade | B33: 1 | C33: Rare | G33: Your attacks apply 1 Poison this turn. | H33: SelfTile | I33: 0 | J33: 0 | K33: PoisonedBlade | L33: Rogue | M33: Buff (Offensive) | N33: Poison | Z33: FALSE | AD33: =IF($AC33="","NEW","Live") | AE33: Probably the cheapest new status on this whole list. | AF33: Needs Status | AG33: A status with an OnDealDamage hook that also applies Poison. OnDealDamage exists and already returns DamageInfo, so this is a small addition. | AH33: WoW | AI33: High
A34: Assassinate | B34: 2 | C34: Legendary | G34: Kill a target below 20% health outright. | H34: Chebyshev | I34: 1 | J34: 1 | K34: Assassinate | L34: Rogue | M34: Melee Attack | N34: Attack | Z34: FALSE | AD34: =IF($AC34="","NEW","Live") | AF34: Needs Effect | AG34: An execute effect reading the target's health ratio at resolve time. | AH34: WoW / Hearthstone | AI34: Med
A35: Sleight of Hand | B35: 1 | C35: Uncommon | G35: Discard a card, then draw 2. | H35: SelfTile | I35: 0 | J35: 0 | K35: SleightOfHand | L35: Rogue | M35: Buff (Offensive) | N35: Attack | Z35: FALSE | AD35: =IF($AC35="","NEW","Live") | AF35: Needs Effect | AG35: DiscardEffect plus a way to choose which card - the first card needing a secondary selection UI. | AH35: StS | AI35: Low
A36: Shiv | B36: 0 | C36: Common | D36: Damage 4 | G36: Deal 4 damage. Exhaust. | H36: Chebyshev | I36: 1 | J36: 1 | K36: Shiv | L36: Rogue | M36: Melee Attack | N36: Attack | O36: Tile | P36: Single | Z36: FALSE | AD36: =IF($AC36="","NEW","Live") | AF36: Needs System | AG36: Exhaust keyword - shared with the Knight's Exhausting Charge. | AH36: StS | AI36: High
A37: Deadly Momentum | B37: 2 | C37: Rare | G37: Whenever you kill an enemy this turn, draw a card and gain 1 energy. | H37: SelfTile | I37: 0 | J37: 0 | K37: DeadlyMomentum | L37: Rogue | M37: Buff (Offensive) | N37: Attack | Z37: FALSE | AD37: =IF($AC37="","NEW","Live") | AE37: OnKill unlocks a whole archetype and nothing else provides it. | AF37: Needs Hook | AG37: An OnKill notification. Nothing observes a death today. | AH37: Griftlands | AI37: High
A38: Cloak | B38: 2 | C38: Rare | G38: Enemies cannot target you until you attack. | H38: SelfTile | I38: 0 | J38: 0 | K38: Cloak | L38: Rogue | M38: Buff (Defensive) | N38: Defence | Z38: FALSE | AD38: =IF($AC38="","NEW","Live") | AF38: Needs Status | AG38: An untargetable flag TargetSelector honours. Taunt already proves targeting can be overridden - ForcedQuarry is the hook to mirror. | AH38: WoW | AI38: Med
A39: Bleed | B39: 1 | C39: Uncommon | G39: Deal damage equal to the target's missing health, up to 10. | H39: Chebyshev | I39: 1 | J39: 1 | K39: Bleed | L39: Rogue | M39: Melee Attack | N39: Attack | Z39: FALSE | AD39: =IF($AC39="","NEW","Live") | AF39: Needs Effect | AG39: Scaling damage read off the target - same machinery as the Knight's Judgement, aimed the other way. | AH39: Darkest Dungeon | AI39: Med
A40: Doppelganger | B40: 3 | C40: Legendary | G40: Play a copy of the last card you played this turn. | H40: SelfTile | I40: 0 | J40: 0 | K40: Doppelganger | L40: Rogue | M40: Buff (Offensive) | N40: Attack | Z40: FALSE | AD40: =IF($AC40="","NEW","Live") | AF40: Needs System | AG40: Card-play history plus re-resolution - shared with the Mage's Spell Echo. | AH40: StS | AI40: Low
A41: Nightmare | B41: 2 | C41: Rare | G41: The target attacks its own allies next turn. | H41: Chebyshev | I41: 1 | J41: 3 | K41: Nightmare | L41: Rogue | M41: Debuff | N41: Attack | Z41: FALSE | AD41: =IF($AC41="","NEW","Live") | AF41: Needs Status | AG41: A status that flips ally/enemy in TargetSelector for one character. EnemyBrain picks its own target, so this needs a hook there too. | AH41: Darkest Dungeon / D&D Confusion | AI41: Low
A42: Death Blossom | B42: 3 | C42: Legendary | D42: Damage 8 | E42: Poison 3 | G42: Deal 8 damage and apply 3 Poison to everything within 2 tiles. | H42: SelfTile | I42: 0 | J42: 0 | K42: DeathBlossom | L42: Rogue | M42: Melee Attack | N42: Attack, Poison | O42: Self | P42: Manhattan 0-2 | R42: Self | S42: Manhattan 0-2 | Z42: FALSE | AD42: =IF($AC42="","NEW","Live") | AF42: Yes | AI42: Med
A43: Thousand Cuts | B43: 3 | C43: Rare | D43: Damage 6 | E43: Poison 6 | G43: Deal 6 damage and apply 6 Poison. | H43: Chebyshev | I43: 1 | J43: 1 | K43: ThousandCuts | L43: Rogue | M43: Melee Attack | N43: Attack, Poison | O43: Tile | P43: Single | R43: Tile | S43: Single | Z43: FALSE | AD43: =IF($AC43="","NEW","Live") | AF43: Yes | AI43: Med
A44: Shadow Dance | B44: 3 | C44: Legendary | D44: Move | E44: Dodge 3 | F44: Draw 2 | G44: Move, gain 3 Dodge charges, and draw 2. | H44: Chebyshev | I44: 1 | J44: 3 | K44: ShadowDance | L44: Rogue | M44: Movement | N44: Movement, Defence | O44: Tile | P44: Single | R44: Self | S44: Single | U44: Self | V44: Single | Z44: FALSE | AD44: =IF($AC44="","NEW","Live") | AF44: Yes | AH44: WoW | AI44: Med
A45: Venom Totem | B45: 2 | C45: Rare | G45: Summon a totem that poisons nearby enemies. | H45: Chebyshev | I45: 1 | J45: 3 | K45: VenomTotem | L45: Rogue | M45: Summon | N45: Summon, Poison | Z45: FALSE | AD45: =IF($AC45="","NEW","Live") | AE45: Same near-free win as the Knight's Banner of Valor. | AF45: Needs System | AG45: A Totem prefab with a Poison aura and AuraAudience.Enemies. AuraData supports this already - it needs authoring, not code. | AH45: WoW | AI45: High
A46: Perfect Assassin | B46: 3 | C46: Legendary | D46: Damage 20 | E46: Poison 5 | G46: Deal 20 damage and apply 5 Poison. | H46: Chebyshev | I46: 1 | J46: 1 | K46: PerfectAssassin | L46: Rogue | M46: Melee Attack | N46: Attack, Poison | O46: Tile | P46: Single | R46: Tile | S46: Single | Z46: FALSE | AD46: =IF($AC46="","NEW","Live") | AF46: Yes | AI46: Low
A47: Blade Storm | B47: 3 | C47: Rare | D47: Damage 7 | G47: Deal 7 damage to everything around you. | H47: SelfTile | I47: 0 | J47: 0 | K47: BladeStorm | L47: Rogue | M47: Melee Attack | N47: Attack | O47: Self | P47: Chebyshev 0-1 | Z47: FALSE | AD47: =IF($AC47="","NEW","Live") | AF47: Yes | AI47: Med
A48: Master of Shadows | B48: 3 | C48: Legendary | D48: Strength 3 | E48: Dodge 2 | F48: Draw 2 | G48: Gain 3 Strength and 2 Dodge charges, then draw 2. | H48: SelfTile | I48: 0 | J48: 0 | K48: MasterOfShadows | L48: Rogue | M48: Buff (Offensive) | N48: Attack, Defence | O48: Self | P48: Single | R48: Self | S48: Single | U48: Self | V48: Single | Z48: FALSE | AD48: =IF($AC48="","NEW","Live") | AF48: Yes | AI48: Med
A49: Lethal Dose | B49: 3 | C49: Rare | D49: Poison 10 | G49: Apply 10 Poison. | H49: Chebyshev | I49: 1 | J49: 1 | K49: LethalDose | L49: Rogue | M49: Debuff | N49: Poison | O49: Tile | P49: Single | Z49: FALSE | AD49: =IF($AC49="","NEW","Live") | AE49: Poison decays by 1 a turn, so 10 stacks is 55 damage over 10 turns - check this against the curve before shipping. | AF49: Yes | AI49: Med
A50: Cutthroat | B50: 2 | C50: Rare | D50: Damage 12 | E50: Weaken 3 | G50: Deal 12 damage and apply 3 Weaken. | H50: Chebyshev | I50: 1 | J50: 1 | K50: Cutthroat | L50: Rogue | M50: Melee Attack | N50: Attack | O50: Tile | P50: Single | R50: Tile | S50: Single | Z50: FALSE | AD50: =IF($AC50="","NEW","Live") | AF50: Yes | AI50: Med
A51: Final Act | B51: 3 | C51: Legendary | D51: Damage 15 | E51: Draw 3 | G51: Deal 15 damage and draw 3. | H51: Chebyshev | I51: 1 | J51: 1 | K51: FinalAct | L51: Rogue | M51: Melee Attack | N51: Attack | O51: Tile | P51: Single | R51: Self | S51: Single | Z51: FALSE | AD51: =IF($AC51="","NEW","Live") | AF51: Yes | AI51: Med

Sheet Cleric Ideas
A1: Card Name | B1: Cost | C1: Rarity | D1: Effect 1 | E1: Effect 2 | F1: Effect 3 | G1: Description | H1: Range Shape | I1: Range Min | J1: Range Max | K1: Key | L1: Class | M1: Folder | N1: Tags | O1: Aim 1 | P1: Area 1 | Q1: Cond 1 | R1: Aim 2 | S1: Area 2 | T1: Cond 2 | U1: Aim 3 | V1: Area 3 | W1: Cond 3 | X1: Cost Cond | Y1: Keywords | Z1: No Reward | AA1: Rotatable | AB1: Animation | AC1: GUID | AD1: Sync | AE1: Notes | AF1: Buildable | AG1: Engine Work | AH1: Source | AI1: Priority

Sheet Glossary
A1: Kind | B1: Type | C1: Title | D1: Body | E1: Terms | F1: Default Stacks | G1: Default Amount | I1: Edit Title, Body and Terms here, then run Import-CardSheet.ps1 and sync in Unity.
A2: Status | B2: Strength | C2: STRENGTH | D2: Adds 3 damage to the next {stacks} attacks. | F2: 1 | G2: 1 | I2: Body keeps its {stacks} / {amount} / {magnitude} placeholders - they are filled from the character's live status when the tooltip is drawn, so one sentence reads correctly for Parry 2 and Parry 7 alike. A shaded Body cell has no placeholder left in it.
A3: Status | B3: DoubleNextAttack | C3: DOUBLE ATTACK | D3: The next {stacks} attack this character makes deals double damage. | E3: Double Attack, Double Next Attack | F3: 1 | G3: 1 | I3: Terms are the words that become hoverable inside a card description, comma separated. Leave blank to use the Type name itself. Add variants the name does not cover - "Poisoned" for Poison.
A4: Status | B4: Poison | C4: POISON | D4: Deals damage equal to {stacks} at the end of the turn. | E4: Poison, Poisoned | F4: 1 | G4: 1 | I4: A row with a blank Title and Body has no tooltip authored yet. Fill both in and sync to create one - the importer ignores rows left blank.
A5: Status | B5: Frozen | C5: FROZEN | D5: Cannot act for {stacks} turns. | E5: Frozen, Freeze | F5: 1 | G5: 1
A6: Status | B6: Shield | C6: SHIELD | D6: Absorbs the next {stacks} damage. Only lasts for this turn. | F6: 1 | G6: 1
A7: Status | B7: Block | C7: BLOCK | D7: Reduces damage taken by {amount} for {stacks} turns | F7: 1 | G7: 3
A8: Status | B8: Parry | C8: PARRY | D8: Negates all damage and reflects the damage back for the next {stacks} turns. | F8: 1 | G8: 1
A9: Status | B9: Rooted | C9: ROOTED | D9: This character is unable to use move actions for {stacks} turns. | E9: Rooted, Root | F9: 1 | G9: 1
A10: Status | B10: DoubleShield | C10: DOUBLE SHIELD | D10: The next {stacks} Shields this character gains is doubled. | F10: 1 | G10: 1
A11: Status | B11: Dodge | C11: DODGE | D11: Dodges the next attack and moves away. Lasts for the next {stacks} turns. | F11: 1 | G11: 1
A12: Status | B12: Weaken | C12: WEAKEN | D12: Reduces the damage dealt by this character for the next {stacks} turns. | F12: 1 | G12: 1
A13: Status | B13: Taunt | C13: TAUNT | D13: This character must move toward or attack the source of the Taunt for {stacks} turns. | F13: 1 | G13: 1
A14: Status | B14: PoisonBlade | C14: POISON BLADE | D14: For {stacks} more turns, every attack this character lands also applies {amount} Poison. | F14: 1 | G14: 1
A15: Status | B15: Stealth | C15: STEALTH | D15: Enemies cannot target this character for {stacks} turns. | F15: 1 | G15: 1
A16: Status | B16: Vulnerable | C16: VULNERABLE | D16: Increase the damage taken by 3 for the next {stacks} turns. | F16: 1 | G16: 3
A17: Status | B17: GainMultiplier | C17: EMPOWERED | D17: Multiplies {status} granted to all {targets} in range by {amount}. | F17: 1 | G17: 1
A18: Status | B18: Potency | C18: POTENT | D18: Adds {amount} to the potency of {status} for all {targets} in range. | F18: 1 | G18: 1
A19: Status | B19: TurnTick | C19: STANDING WARD | D19: Grants {amount} {status} to all {targets} in range {timing}. | F19: 1 | G19: 1
A20: Status | B20: Summoned | C20: SUMMONED | D20: Will die in {stacks} turns. | F20: 1 | G20: 1
A21: Status | B21: Regeneration | C21: REGENERATION | D21: Heals {stacks} at the end of each of the carrier's turns, then decays by 1. | F21: 1 | G21: 1
... A35: Keyword | B35: Interruptible | C35: INTERRUPTIBLE | D35: Freezing this character while it is winding this up knocks the card out for {magnitude} turns. | F35: 1 | G35: 1
A36: Keyword | B36: Rebound | F36: 1 | G36: 1

Sheet Effects
A1: Name | B1: Class | C1: Kind | D1: Amount | E1: Detail | F1: Scoreable | G1: Used By | H1: Path | I1: GUID
A2: Dodge | B2: ApplyStatusEffect | C2: Status:Dodge | D2: 1 | E2: turns=-1 | F2: No | G2: 1 | H2: Assets/Data/EffectData/Status/Dodge.asset | I2: 297e32706d67fd44c9bf239d7b885ef8
A3: Double Next Attack | B3: ApplyStatusEffect | C3: Status:DoubleNextAttack | D3: 1 | E3: turns=-1 | F3: Yes | G3: 1 | H3: Assets/Data/EffectData/Status/Double Next Attack.asset | I3: a1c05e11d2f34b0a9e5c17d40b1e5008
A4: Double Shield | B4: ApplyStatusEffect | C4: Status:DoubleShield | D4: 1 | E4: turns=-1 | F4: Yes | G4: 0 | H4: Assets/Data/EffectData/Status/Double Shield.asset | I4: 130a684baa1486a4fb3fe349e9470ff5
A5: Freeze | B5: ApplyStatusEffect | C5: Status:Frozen | D5: 1 | E5: turns=-1 | F5: No | G5: 2 | H5: Assets/Data/EffectData/Status/Freeze.asset | I5: 3580edba556b41dfacf7b14e5dc9d88d
A6: Lifesteal 1 | B6: ApplyStatusEffect | C6: Status:Lifesteal | D6: 1 | E6: turns=-1 | F6: Yes | G6: 1 | H6: Assets/Data/EffectData/Status/Lifesteal 1.asset | I6: b425a39889a3aae4d9201b882b3cce16
A7: Lifesteal 3 | B7: ApplyStatusEffect | C7: Status:Lifesteal | D7: 3 | E7: turns=-1 | F7: Yes | G7: 1 | H7: Assets/Data/EffectData/Status/Lifesteal 3.asset | I7: d923de627cbf8b44597d99bd5e4d399b
A8: Pilfered 1 | B8: ApplyStatusEffect | C8: Status:Unknown(29) | D8: 1 | E8: turns=-1 | F8: Yes | G8: 1 | H8: Assets/Data/EffectData/Status/Pilfered 1.asset | I8: edee9383db4a416b9874e20ac26e3dd4
A9: Poison | B9: ApplyStatusEffect | C9: Status:Poison | D9: 1 | E9: turns=-1 | F9: Yes | G9: 0 | H9: Assets/Data/EffectData/Status/Poison.asset | I9: 8559e2772957a134bab0efb4dee349f7
A10: Poison 2 | B10: ApplyStatusEffect | C10: Status:Poison | D10: 2 | E10: turns=-1 | F10: Yes | G10: 1 | H10: Assets/Data/EffectData/Status/Poison 2.asset | I10: bcae4299ca2f3dc41acf722b1fdc6b13
A11: Poison 3 | B11: ApplyStatusEffect | C11: Status:Poison | D11: 3 | E11: turns=-1 | F11: Yes | G11: 3 | H11: Assets/Data/EffectData/Status/Poison 3.asset | I11: f1f83550d8e0b1349b773e5db3dcacc8
A12: Poison 4 | B12: ApplyStatusEffect | C12: Status:Poison | D12: 4 | E12: turns=-1 | F12: Yes | G12: 1 | H12: Assets/Data/EffectData/Status/Poison 4.asset | I12: bb990246a9e74a9da9818c57770f9e51
A13: Poison Blade 3 | B13: ApplyStatusEffect | C13: Status:PoisonBlade | D13: 3 | E13: turns=-1 | F13: Yes | G13: 1 | H13: Assets/Data/EffectData/Status/Poison Blade 3.asset | I13: c4ef771153264c74986d3776f325b2b9
... A28: Block 4 | B28: BlockEffect | C28: Block | D28: 4 | E28: legacy blockAmount=0 | F28: Yes | G28: 0 | H28: Assets/Data/EffectData/Block/Block 4.asset | I28: a836327bb4d2a2e4484474715888ecb1
A29: Damage 1 | B29: DamageEffect | C29: Damage | D29: 1 | F29: Yes | G29: 2 | H29: Assets/Data/EffectData/Damage/Damage 1.asset | I29: 894788a7c2284a7bbab8841b42d5bfb6
A30: Damage 11 | B30: DamageEffect | C30: Damage | D30: 11 | F30: Yes | G30: 1 | H30: Assets/Data/EffectData/Damage/Damage 11.asset | I30: b9e71ac70ed385e4fb95af962de15f34
A31: Damage 12 | B31: DamageEffect | C31: Damage | D31: 12 | F31: Yes | G31: 1 | H31: Assets/Data/EffectData/Damage/Damage 12.asset | I31: 617d3d1dc022471b961cff06e054c826
A32: Damage 2 | B32: DamageEffect | C32: Damage | D32: 2 | F32: Yes | G32: 5 | H32: Assets/Data/EffectData/Damage/Damage 2.asset | I32: 3d27ea264b552f34f8714152e4dc8b05
A33: Damage 3 | B33: DamageEffect | C33: Damage | D33: 3 | F33: Yes | G33: 12 | H33: Assets/Data/EffectData/Damage/Damage 3.asset | I33: 2b3919664f29705438c0b427d91e208c
A34: Damage 4 | B34: DamageEffect | C34: Damage | D34: 4 | F34: Yes | G34: 10 | H34: Assets/Data/EffectData/Damage/Damage 4.asset | I34: abee4d4f63fb20347a76a5c8221892f2
A35: Damage 5 | B35: DamageEffect | C35: Damage | D35: 5 | F35: Yes | G35: 12 | H35: Assets/Data/EffectData/Damage/Damage 5.asset | I35: a1c05e11d2f34b0a9e5c17d40b1e5001
A36: Damage 6 | B36: DamageEffect | C36: Damage | D36: 6 | F36: Yes | G36: 5 | H36: Assets/Data/EffectData/Damage/Damage 6.asset | I36: 5dd8e966162d47a4b990f67e30ce6ae2
A37: Damage 7 | B37: DamageEffect | C37: Damage | D37: 7 | F37: Yes | G37: 7 | H37: Assets/Data/EffectData/Damage/Damage 7.asset | I37: 5e680a6c51d3ffd428265490d6a1e1d8
A38: Damage 8 | B38: DamageEffect | C38: Damage | D38: 8 | F38: Yes | G38: 6 | H38: Assets/Data/EffectData/Damage/Damage 8.asset | I38: ecb84d8108edde84f8eef282d5a80b23
A39: Damage 9 | B39: DamageEffect | C39: Damage | D39: 9 | F39: Yes | G39: 4 | H39: Assets/Data/EffectData/Damage/Damage 9.asset | I39: a1c05e11d2f34b0a9e5c17d40b1e5002
A40: Draw 1 | B40: DrawEffect | C40: Draw | D40: 1 | F40: Yes | G40: 24 | H40: Assets/Data/EffectData/Draw/Draw 1.asset | I40: a1c05e11d2f34b0a9e5c17d40b1e5005
... A60: Shield 9 | B60: ShieldEffect | C60: Shield | D60: 9 | F60: Yes | G60: 1 | H60: Assets/Data/EffectData/Shield/Shield 9.asset | I60: d5a397987a59a3349a4ea5c2a2e27f07
A61: SummonAegisTotem | B61: SummonEffect | C61: Summon | D61: 1 | E61: 12716135eb9ba744486bb34cd3b576d2 | F61: No | G61: 1 | H61: Assets/Data/EffectData/Summon/SummonAegisTotem.asset | I61: a8621744cbb9c6d47b2aebdc574e5b63
A62: SummonAnvilTotem | B62: SummonEffect | C62: Summon | D62: 1 | E62: aa36caad95167e049a7e31d9cfff36f6 | F62: No | G62: 1 | H62: Assets/Data/EffectData/Summon/SummonAnvilTotem.asset | I62: 11668732e05037344b956762cb9a46d2
A63: SummonBastionTotem | B63: SummonEffect | C63: Summon | D63: 1 | E63: 59df727e2f4fec149bbff1700643786f | F63: No | G63: 1 | H63: Assets/Data/EffectData/Summon/SummonBastionTotem.asset | I63: ad920d8b007cd6f4b8e8aa9f2ceb7c6c
A64: SummonBatMinion | B64: SummonEffect | C64: Summon | D64: 1 | E64: 51cc0c0b40e7b264ebdf1dc4594559a6 | F64: No | G64: 1 | H64: Assets/Data/EffectData/Summon/SummonBatMinion.asset | I64: 78bcfc8f964d598488b7ad9526adb34e
A65: SummonBeaconTotem | B65: SummonEffect | C65: Summon | D65: 1 | E65: 07e8451c51bb65546808aa387bb8bd7e | F65: No | G65: 1 | H65: Assets/Data/EffectData/Summon/SummonBeaconTotem.asset | I65: 704823e45e84b924e9b2278d1c90595f
A66: SummonBindingTotem | B66: SummonEffect | C66: Summon | D66: 1 | E66: 6904b7a67f4703440bbd3dec1c996b20 | F66: No | G66: 1 | H66: Assets/Data/EffectData/Summon/SummonBindingTotem.asset | I66: 928d31f7044a02c4bb19c4e98a82a4bb
A67: SummonBloodmoonTotem | B67: SummonEffect | C67: Summon | D67: 1 | E67: d9bd710eeeb9bf34fa521626fbfdb526 | F67: No | G67: 1 | H67: Assets/Data/EffectData/Summon/SummonBloodmoonTotem.asset | I67: 9912c48d006d97748b7543cce90de911
A68: SummonBloodpactTotem | B68: SummonEffect | C68: Summon | D68: 1 | E68: 867cd3747eb2e3f4686bfffb94e2efcc | F68: No | G68: 1 | H68: Assets/Data/EffectData/Summon/SummonBloodpactTotem.asset | I68: e9fb0ed2c0e4ecb46a71a5a814946157
A69: SummonBloomTotem | B69: SummonEffect | C69: Summon | D69: 1 | E69: e1d4646adb9535041890f40a911cb169 | F69: No | G69: 1 | H69: Assets/Data/EffectData/Summon/SummonBloomTotem.asset | I69: b411bd8d98eae524d8de5274567a3e65
A70: SummonBulwarkTotem | B70: SummonEffect | C70: Summon | D70: 1 | E70: 244f38522011b184a9ac6fa1011c3518 | F70: No | G70: 1 | H70: Assets/Data/EffectData/Summon/SummonBulwarkTotem.asset | I70: 0861a0d7b70789242b177197be7a4c66
A71: SummonChaosTotem | B71: SummonEffect | C71: Summon | D71: 1 | E71: e3fe7596597b2de469dc144ca54bb0d2 | F71: No | G71: 1 | H71: Assets/Data/EffectData/Summon/SummonChaosTotem.asset | I71: dd02906595f5d2a408fe1d50b29dea97
A72: SummonChapelTotem | B72: SummonEffect | C72: Summon | D72: 1 | E72: b0193ce96e424d642880f2ca0a83ed70 | F72: No | G72: 1 | H72: Assets/Data/EffectData/Summon/SummonChapelTotem.asset | I72: d56010c2748f8f94ebd49e93441c6b58
... A121: SummonWhetstoneTotem | B121: SummonEffect | C121: Summon | D121: 1 | E121: d21edbaded8f4a44d89334d8007b14aa | F121: No | G121: 1 | H121: Assets/Data/EffectData/Summon/SummonWhetstoneTotem.asset | I121: 8b48c7703c5acc54685aaaeaacbfb168
A122: Taunt | B122: TauntEffect | C122: Taunt | D122: 2 | F122: No | G122: 2 | H122: Assets/Data/EffectData/Status/Taunt.asset | I122: 7d286e3e54b5ca940b330c157d137531
A123: Cone3 | B123: EffectPattern | C123: Pattern | D123: 5 | E123: 5x3 grid, 5 painted | F123: n/a | G123: 0 | H123: Assets/Data/EffectData/Patterns/Cone3.asset | I123: df31fd0783da2c642bc5ee38e3754ecc
A124: Wall3 | B124: EffectPattern | C124: Pattern | D124: 3 | E124: 3x1 grid, 3 painted | F124: n/a | G124: 0 | H124: Assets/Data/EffectData/Patterns/Wall3.asset | I124: 8f79c6a0cdb32114494d00fc261c76fd
A125: X-Pattern | B125: EffectPattern | C125: Pattern | D125: 8 | E125: 5x5 grid, 8 painted | F125: n/a | G125: 0 | H125: Assets/Data/EffectData/Patterns/X-Pattern.asset | I125: f9590943e326bbd449fee5d0524498a6

Sheet Decks
A1: Deck | B1: For | C1: Card | D1: Count | E1: Locked
A2: ClericStarter | B2: Cleric | C2: Move | D2: 4 | E2: No
A3: ClericStarter | B3: Cleric | C3: Smite | D3: 4 | E3: No
A4: ClericStarter | B4: Cleric | C4: Cleansing Light | D4: 2 | E4: No
A5: ClericStarter | B5: Cleric | C5: Mend and Guard | D5: 2 | E5: No
A6: ClericStarter | B6: Cleric | C6: Spring Totem | D6: 1 | E6: No
A7: ClericStarter | B7: Cleric | C7: Renew | D7: 2 | E7: No
A8: ClericStarter | B8: Cleric | C8: Renewing Touch | D8: 1 | E8: No
A9: ClericTest | B9: Cleric | C9: Move | D9: 1 | E9: No
A10: ClericTest | B10: Cleric | C10: Overflow | D10: 1 | E10: No
A11: ClericTest | B11: Cleric | C11: Heal Word | D11: 1 | E11: No
A12: ClericTutorial | B12: Any | C12: Smite | D12: 1 | E12: No
A13: ClericTutorial | B13: Any | C13: Move | D13: 1 | E13: No
... A40: RogueTest | B40: Rogue | C40: Move | D40: 1 | E40: No

Sheet Model
A1: Term | B1: Value | C1: Why this number
A2: w_Damage | B2: 1 | C2: The numeraire. One point of damage to an enemy = 1 power.
A3: w_Heal | B3: 0.8 | C3: Only useful when already damaged, so worth less than the same damage.
A4: w_Shield | B4: 0.7 | C4: ShieldStatus is wiped on OnTurnStart - it must be spent this round.
A5: w_Block | B5: 0.9 | C5: Charges survive turn start, so a point prevented is worth more than shield.
A6: w_Parry | B6: 5 | C6: Per charge. Negates the hit AND reflects it: prevention plus damage.
A7: w_Poison | B7: 1.2 | C7: Per point of lifetime DoT. Unblockable, but arrives slowly.
A8: w_Strength | B8: 1 | C8: Per stack per future attack. Multiplied by w_Horizon.
A9: w_Weaken | B9: 1 | C9: Per stack per future enemy attack. Symmetric with Strength.
A10: w_Draw | B10: 3 | C10: Per card. Standard deckbuilder rate for raw card advantage.
A11: w_Move | B11: 3 | C11: Repositioning on a grid where range gates every card - worth more than it looks.
A12: w_Combo | B12: 6 | C12: Per stack of Double Next Attack / Double Shield - roughly one extra average payload.
A13: w_OccEnemy | B13: 0.5 | C13: Share of extra AoE tiles expected to actually hold an enemy.
... A21: board_Tiles | B21: 64 | C21: Tile count used when an area is RangeShape.Anywhere.
A23: Rarity multiplier
A24: Rarity | B24: Multiplier
A25: Common | B25: 1
A26: Uncommon | B26: 1.15
A27: Rare | B27: 1.35
A28: Legendary | B28: 1.6
A29: NotOffered | B29: 1
A31: Edit the Value column and every figure on Balance recalculates. Nothing here is baked into the export script.
A32: One exception: a summoned totem's output is pre-multiplied by 3 expected activations in Export-CardSheet.ps1 ($TotemActivations) before it reaches these columns. Change it there, not here.

Sheet Balance
A1: Key | B1: Card Name | C1: Class | D1: Cost | E1: Rarity | F1: Source | G1: Enemy Tiles | H1: Ally Tiles | I1: Damage | J1: Heal | K1: Shield | L1: Block Total | M1: Parry | N1: Poison Total | O1: Strength | P1: Weaken | Q1: Draw | R1: Move | S1: Combo | T1: Summons | U1: Control | V1: Quantifiable | W1: Power | X1: Power/Energy | Y1: Expected | Z1: Delta | AA1: Flag | AB1: Issues | AC1: Pw Common | AD1: Pw Uncommon | AE1: Pw Rare | AF1: Pw Legendary | AG1: Eff Knight | AH1: Eff Mage | AI1: Eff Rogue | AJ1: Exp Plot | AK1: Pw Idea | AL1: Eff Cleric
A2: Block | B2: Block | C2: Knight+Rogue | D2: 1 | E2: Uncommon | F2: Knight | G2: 1 | H2: 1 | I2: 0 | J2: 0 | K2: 0 | L2: 5 | M2: 0 | N2: 0 | O2: 0 | P2: 0 | Q2: 0 | R2: 0 | S2: 0 | V2: Yes | W2: =IF($V2="No","",ROUND((I2*w_Damage + N2*w_Poison + P2*w_Weaken*w_Horizon)*MIN(1+(G2-1)*w_OccEnemy,w_MaxEnemies) + (J2*w_Heal + K2*w_Shield + L2*w_Block + M2*w_Parry + O2*w_Strength*w_Horizon + S2*w_Combo)*MIN(1+(H2-1)*w_OccAlly,w_MaxAllies) + Q2*w_Draw + R2*w_Move,2)) | X2: =IF(W2="","",ROUND(W2/MAX(D2,1),2)) | Y2: =IF($V2="No","",ROUND((curve_Base+curve_Slope*D2)*IFERROR(VLOOKUP(E2,rarity_Mult,2,FALSE),1),2)) | Z2: =IF(OR(W2="",Y2=""),"",ROUND(W2-Y2,2)) | AA2: =IF(Z2="","",IF($V2="Partial","RIDER",IF(ABS(Z2)<=Y2*tol_Pct,"OK",IF(Z2>0,"OVER","UNDER")))) | AC2: =IF(AND($V2<>"No",$E2="Common",NOT(ISNUMBER(SEARCH("Ideas",$F2)))),$W2,NA()) | AD2: =IF(AND($V2<>"No",$E2="Uncommon",NOT(ISNUMBER(SEARCH("Ideas",$F2)))),$W2,NA()) | AE2: =IF(AND($V2<>"No",$E2="Rare",NOT(ISNUMBER(SEARCH("Ideas",$F2)))),$W2,NA()) | AF2: =IF(AND($V2<>"No",$E2="Legendary",NOT(ISNUMBER(SEARCH("Ideas",$F2)))),$W2,NA()) | AG2: =IF(AND($V2<>"No",ISNUMBER(SEARCH("Knight",$C2)),NOT(ISNUMBER(SEARCH("Ideas",$F2)))),$X2,NA()) | AH2: =IF(AND($V2<>"No",ISNUMBER(SEARCH("Mage",$C2)),NOT(ISNUMBER(SEARCH("Ideas",$F2)))),$X2,NA()) | AI2: =IF(AND($V2<>"No",ISNUMBER(SEARCH("Rogue",$C2)),NOT(ISNUMBER(SEARCH("Ideas",$F2)))),$X2,NA()) | AJ2: =IF($V2<>"No",$Y2,NA()) | AK2: =IF(AND($V2<>"No",ISNUMBER(SEARCH("Ideas",$F2))),$W2,NA()) | AL2: =IF(AND($V2<>"No",ISNUMBER(SEARCH("Cleric",$C2)),NOT(ISNUMBER(SEARCH("Ideas",$F2)))),$X2,NA())
A3: Brothers in Arms | B3: Brothers in Arms | C3: Knight | D3: 1 | E3: Uncommon | F3: Knight | G3: 1 | H3: 1 | I3: 0 | J3: 0 | K3: 8 | L3: 0 | M3: 0 | N3: 0 | O3: 0 | P3: 0 | Q3: 1 | R3: 0 | S3: 0 | V3: Yes | W3: =IF($V3="No","",ROUND((I3*w_Damage + N3*w_Poison + P3*w_Weaken*w_Horizon)*MIN(1+(G3-1)*w_OccEnemy,w_MaxEnemies) + (J3*w_Heal + K3*w_Shield + L3*w_Block + M3*w_Parry + O3*w_Strength*w_Horizon + S3*w_Combo)*MIN(1+(H3-1)*w_OccAlly,w_MaxAllies) + Q3*w_Draw + R3*w_Move,2)) | X3: =IF(W3="","",ROUND(W3/MAX(D3,1),2)) | Y3: =IF($V3="No","",ROUND((curve_Base+curve_Slope*D3)*IFERROR(VLOOKUP(E3,rarity_Mult,2,FALSE),1),2)) | Z3: =IF(OR(W3="",Y3=""),"",ROUND(W3-Y3,2)) | AA3: =IF(Z3="","",IF($V3="Partial","RIDER",IF(ABS(Z3)<=Y3*tol_Pct,"OK",IF(Z3>0,"OVER","UNDER")))) | AC3: =IF(AND($V3<>"No",$E3="Common",NOT(ISNUMBER(SEARCH("Ideas",$F3)))),$W3,NA()) | AD3: =IF(AND($V3<>"No",$E3="Uncommon",NOT(ISNUMBER(SEARCH("Ideas",$F3)))),$W3,NA()) | AE3: =IF(AND($V3<>"No",$E3="Rare",NOT(ISNUMBER(SEARCH("Ideas",$F3)))),$W3,NA()) | AF3: =IF(AND($V3<>"No",$E3="Legendary",NOT(ISNUMBER(SEARCH("Ideas",$F3)))),$W3,NA()) | AG3: =IF(AND($V3<>"No",ISNUMBER(SEARCH("Knight",$C3)),NOT(ISNUMBER(SEARCH("Ideas",$F3)))),$X3,NA()) | AH3: =IF(AND($V3<>"No",ISNUMBER(SEARCH("Mage",$C3)),NOT(ISNUMBER(SEARCH("Ideas",$F3)))),$X3,NA()) | AI3: =IF(AND($V3<>"No",ISNUMBER(SEARCH("Rogue",$C3)),NOT(ISNUMBER(SEARCH("Ideas",$F3)))),$X3,NA()) | AJ3: =IF($V3<>"No",$Y3,NA()) | AK3: =IF(AND($V3<>"No",ISNUMBER(SEARCH("Ideas",$F3))),$W3,NA()) | AL3: =IF(AND($V3<>"No",ISNUMBER(SEARCH("Cleric",$C3)),NOT(ISNUMBER(SEARCH("Ideas",$F3)))),$X3,NA())
A4: Bulwark Stance | B4: Bulwark Stance | C4: Knight | D4: 1 | E4: Uncommon | F4: Knight | G4: 1 | H4: 1 | I4: 0 | J4: 0 | K4: 6 | L4: 0 | M4: 0 | N4: 0 | O4: 0 | P4: 0 | Q4: 1 | R4: 0 | S4: 0 | V4: Yes | W4: =IF($V4="No","",ROUND((I4*w_Damage + N4*w_Poison + P4*w_Weaken*w_Horizon)*MIN(1+(G4-1)*w_OccEnemy,w_MaxEnemies) + (J4*w_Heal + K4*w_Shield + L4*w_Block + M4*w_Parry + O4*w_Strength*w_Horizon + S4*w_Combo)*MIN(1+(H4-1)*w_OccAlly,w_MaxAllies) + Q4*w_Draw + R4*w_Move,2)) | X4: =IF(W4="","",ROUND(W4/MAX(D4,1),2)) | Y4: =IF($V4="No","",ROUND((curve_Base+curve_Slope*D4)*IFERROR(VLOOKUP(E4,rarity_Mult,2,FALSE),1),2)) | Z4: =IF(OR(W4="",Y4=""),"",ROUND(W4-Y4,2)) | AA4: =IF(Z4="","",IF($V4="Partial","RIDER",IF(ABS(Z4)<=Y4*tol_Pct,"OK",IF(Z4>0,"OVER","UNDER")))) | AC4: =IF(AND($V4<>"No",$E4="Common",NOT(ISNUMBER(SEARCH("Ideas",$F4)))),$W4,NA()) | AD4: =IF(AND($V4<>"No",$E4="Uncommon",NOT(ISNUMBER(SEARCH("Ideas",$F4)))),$W4,NA()) | AE4: =IF(AND($V4<>"No",$E4="Rare",NOT(ISNUMBER(SEARCH("Ideas",$F4)))),$W4,NA()) | AF4: =IF(AND($V4<>"No",$E4="Legendary",NOT(ISNUMBER(SEARCH("Ideas",$F4)))),$W4,NA()) | AG4: =IF(AND($V4<>"No",ISNUMBER(SEARCH("Knight",$C4)),NOT(ISNUMBER(SEARCH("Ideas",$F4)))),$X4,NA()) | AH4: =IF(AND($V4<>"No",ISNUMBER(SEARCH("Mage",$C4)),NOT(ISNUMBER(SEARCH("Ideas",$F4)))),$X4,NA()) | AI4: =IF(AND($V4<>"No",ISNUMBER(SEARCH("Rogue",$C4)),NOT(ISNUMBER(SEARCH("Ideas",$F4)))),$X4,NA()) | AJ4: =IF($V4<>"No",$Y4,NA()) | AK4: =IF(AND($V4<>"No",ISNUMBER(SEARCH("Ideas",$F4))),$W4,NA()) | AL4: =IF(AND($V4<>"No",ISNUMBER(SEARCH("Cleric",$C4)),NOT(ISNUMBER(SEARCH("Ideas",$F4)))),$X4,NA())
A5: Guard Up | B5: Guard Up | C5: Knight | D5: 1 | E5: Uncommon | F5: Knight | G5: 1 | H5: 1 | I5: 0 | J5: 0 | K5: 6 | L5: 0 | M5: 0 | N5: 0 | O5: 0 | P5: 0 | Q5: 0 | R5: 0 | S5: 0 | V5: Yes | W5: =IF($V5="No","",ROUND((I5*w_Damage + N5*w_Poison + P5*w_Weaken*w_Horizon)*MIN(1+(G5-1)*w_OccEnemy,w_MaxEnemies) + (J5*w_Heal + K5*w_Shield + L5*w_Block + M5*w_Parry + O5*w_Strength*w_Horizon + S5*w_Combo)*MIN(1+(H5-1)*w_OccAlly,w_MaxAllies) + Q5*w_Draw + R5*w_Move,2)) | X5: =IF(W5="","",ROUND(W5/MAX(D5,1),2)) | Y5: =IF($V5="No","",ROUND((curve_Base+curve_Slope*D5)*IFERROR(VLOOKUP(E5,rarity_Mult,2,FALSE),1),2)) | Z5: =IF(OR(W5="",Y5=""),"",ROUND(W5-Y5,2)) | AA5: =IF(Z5="","",IF($V5="Partial","RIDER",IF(ABS(Z5)<=Y5*tol_Pct,"OK",IF(Z5>0,"OVER","UNDER")))) | AC5: =IF(AND($V5<>"No",$E5="Common",NOT(ISNUMBER(SEARCH("Ideas",$F5)))),$W5,NA()) | AD5: =IF(AND($V5<>"No",$E5="Uncommon",NOT(ISNUMBER(SEARCH("Ideas",$F5)))),$W5,NA()) | AE5: =IF(AND($V5<>"No",$E5="Rare",NOT(ISNUMBER(SEARCH("Ideas",$F5)))),$W5,NA()) | AF5: =IF(AND($V5<>"No",$E5="Legendary",NOT(ISNUMBER(SEARCH("Ideas",$F5)))),$W5,NA()) | AG5: =IF(AND($V5<>"No",ISNUMBER(SEARCH("Knight",$C5)),NOT(ISNUMBER(SEARCH("Ideas",$F5)))),$X5,NA()) | AH5: =IF(AND($V5<>"No",ISNUMBER(SEARCH("Mage",$C5)),NOT(ISNUMBER(SEARCH("Ideas",$F5)))),$X5,NA()) | AI5: =IF(AND($V5<>"No",ISNUMBER(SEARCH("Rogue",$C5)),NOT(ISNUMBER(SEARCH("Ideas",$F5)))),$X5,NA()) | AJ5: =IF($V5<>"No",$Y5,NA()) | AK5: =IF(AND($V5<>"No",ISNUMBER(SEARCH("Ideas",$F5))),$W5,NA()) | AL5: =IF(AND($V5<>"No",ISNUMBER(SEARCH("Cleric",$C5)),NOT(ISNUMBER(SEARCH("Ideas",$F5)))),$X5,NA())
A6: Last Bastion | B6: Last Bastion | C6: Knight | D6: 1 | E6: Rare | F6: Knight | G6: 24 | H6: 1 | I6: 0 | J6: 0 | K6: 6 | L6: 0 | M6: 0 | N6: 0 | O6: 0 | P6: 0 | Q6: 1 | R6: 0 | S6: 0 | U6: Taunt | V6: Partial | W6: =IF($V6="No","",ROUND((I6*w_Damage + N6*w_Poison + P6*w_Weaken*w_Horizon)*MIN(1+(G6-1)*w_OccEnemy,w_MaxEnemies) + (J6*w_Heal + K6*w_Shield + L6*w_Block + M6*w_Parry + O6*w_Strength*w_Horizon + S6*w_Combo)*MIN(1+(H6-1)*w_OccAlly,w_MaxAllies) + Q6*w_Draw + R6*w_Move,2)) | X6: =IF(W6="","",ROUND(W6/MAX(D6,1),2)) | Y6: =IF($V6="No","",ROUND((curve_Base+curve_Slope*D6)*IFERROR(VLOOKUP(E6,rarity_Mult,2,FALSE),1),2)) | Z6: =IF(OR(W6="",Y6=""),"",ROUND(W6-Y6,2)) | AA6: =IF(Z6="","",IF($V6="Partial","RIDER",IF(ABS(Z6)<=Y6*tol_Pct,"OK",IF(Z6>0,"OVER","UNDER")))) | AC6: =IF(AND($V6<>"No",$E6="Common",NOT(ISNUMBER(SEARCH("Ideas",$F6)))),$W6,NA()) | AD6: =IF(AND($V6<>"No",$E6="Uncommon",NOT(ISNUMBER(SEARCH("Ideas",$F6)))),$W6,NA()) | AE6: =IF(AND($V6<>"No",$E6="Rare",NOT(ISNUMBER(SEARCH("Ideas",$F6)))),$W6,NA()) | AF6: =IF(AND($V6<>"No",$E6="Legendary",NOT(ISNUMBER(SEARCH("Ideas",$F6)))),$W6,NA()) | AG6: =IF(AND($V6<>"No",ISNUMBER(SEARCH("Knight",$C6)),NOT(ISNUMBER(SEARCH("Ideas",$F6)))),$X6,NA()) | AH6: =IF(AND($V6<>"No",ISNUMBER(SEARCH("Mage",$C6)),NOT(ISNUMBER(SEARCH("Ideas",$F6)))),$X6,NA()) | AI6: =IF(AND($V6<>"No",ISNUMBER(SEARCH("Rogue",$C6)),NOT(ISNUMBER(SEARCH("Ideas",$F6)))),$X6,NA()) | AJ6: =IF($V6<>"No",$Y6,NA()) | AK6: =IF(AND($V6<>"No",ISNUMBER(SEARCH("Ideas",$F6))),$W6,NA()) | AL6: =IF(AND($V6<>"No",ISNUMBER(SEARCH("Cleric",$C6)),NOT(ISNUMBER(SEARCH("Ideas",$F6)))),$X6,NA())
A7: Lone Stand | B7: Lone Stand | C7: Knight | D7: 1 | E7: Uncommon | F7: Knight | G7: 1 | H7: 1 | I7: 0 | J7: 0 | K7: 6 | L7: 0 | M7: 0 | N7: 0 | O7: 0 | P7: 0 | Q7: 0 | R7: 0 | S7: 0 | V7: Yes | W7: =IF($V7="No","",ROUND((I7*w_Damage + N7*w_Poison + P7*w_Weaken*w_Horizon)*MIN(1+(G7-1)*w_OccEnemy,w_MaxEnemies) + (J7*w_Heal + K7*w_Shield + L7*w_Block + M7*w_Parry + O7*w_Strength*w_Horizon + S7*w_Combo)*MIN(1+(H7-1)*w_OccAlly,w_MaxAllies) + Q7*w_Draw + R7*w_Move,2)) | X7: =IF(W7="","",ROUND(W7/MAX(D7,1),2)) | Y7: =IF($V7="No","",ROUND((curve_Base+curve_Slope*D7)*IFERROR(VLOOKUP(E7,rarity_Mult,2,FALSE),1),2)) | Z7: =IF(OR(W7="",Y7=""),"",ROUND(W7-Y7,2)) | AA7: =IF(Z7="","",IF($V7="Partial","RIDER",IF(ABS(Z7)<=Y7*tol_Pct,"OK",IF(Z7>0,"OVER","UNDER")))) | AC7: =IF(AND($V7<>"No",$E7="Common",NOT(ISNUMBER(SEARCH("Ideas",$F7)))),$W7,NA()) | AD7: =IF(AND($V7<>"No",$E7="Uncommon",NOT(ISNUMBER(SEARCH("Ideas",$F7)))),$W7,NA()) | AE7: =IF(AND($V7<>"No",$E7="Rare",NOT(ISNUMBER(SEARCH("Ideas",$F7)))),$W7,NA()) | AF7: =IF(AND($V7<>"No",$E7="Legendary",NOT(ISNUMBER(SEARCH("Ideas",$F7)))),$W7,NA()) | AG7: =IF(AND($V7<>"No",ISNUMBER(SEARCH("Knight",$C7)),NOT(ISNUMBER(SEARCH("Ideas",$F7)))),$X7,NA()) | AH7: =IF(AND($V7<>"No",ISNUMBER(SEARCH("Mage",$C7)),NOT(ISNUMBER(SEARCH("Ideas",$F7)))),$X7,NA()) | AI7: =IF(AND($V7<>"No",ISNUMBER(SEARCH("Rogue",$C7)),NOT(ISNUMBER(SEARCH("Ideas",$F7)))),$X7,NA()) | AJ7: =IF($V7<>"No",$Y7,NA()) | AK7: =IF(AND($V7<>"No",ISNUMBER(SEARCH("Ideas",$F7))),$W7,NA()) | AL7: =IF(AND($V7<>"No",ISNUMBER(SEARCH("Cleric",$C7)),NOT(ISNUMBER(SEARCH("Ideas",$F7)))),$X7,NA())
A8: Parry | B8: Parry | C8: Knight | D8: 1 | E8: Uncommon | F8: Knight | G8: 1 | H8: 1 | I8: 0 | J8: 0 | K8: 0 | L8: 0 | M8: 1 | N8: 0 | O8: 0 | P8: 0 | Q8: 0 | R8: 0 | S8: 0 | V8: Yes | W8: =IF($V8="No","",ROUND((I8*w_Damage + N8*w_Poison + P8*w_Weaken*w_Horizon)*MIN(1+(G8-1)*w_OccEnemy,w_MaxEnemies) + (J8*w_Heal + K8*w_Shield + L8*w_Block + M8*w_Parry + O8*w_Strength*w_Horizon + S8*w_Combo)*MIN(1+(H8-1)*w_OccAlly,w_MaxAllies) + Q8*w_Draw + R8*w_Move,2)) | X8: =IF(W8="","",ROUND(W8/MAX(D8,1),2)) | Y8: =IF($V8="No","",ROUND((curve_Base+curve_Slope*D8)*IFERROR(VLOOKUP(E8,rarity_Mult,2,FALSE),1),2)) | Z8: =IF(OR(W8="",Y8=""),"",ROUND(W8-Y8,2)) | AA8: =IF(Z8="","",IF($V8="Partial","RIDER",IF(ABS(Z8)<=Y8*tol_Pct,"OK",IF(Z8>0,"OVER","UNDER")))) | AC8: =IF(AND($V8<>"No",$E8="Common",NOT(ISNUMBER(SEARCH("Ideas",$F8)))),$W8,NA()) | AD8: =IF(AND($V8<>"No",$E8="Uncommon",NOT(ISNUMBER(SEARCH("Ideas",$F8)))),$W8,NA()) | AE8: =IF(AND($V8<>"No",$E8="Rare",NOT(ISNUMBER(SEARCH("Ideas",$F8)))),$W8,NA()) | AF8: =IF(AND($V8<>"No",$E8="Legendary",NOT(ISNUMBER(SEARCH("Ideas",$F8)))),$W8,NA()) | AG8: =IF(AND($V8<>"No",ISNUMBER(SEARCH("Knight",$C8)),NOT(ISNUMBER(SEARCH("Ideas",$F8)))),$X8,NA()) | AH8: =IF(AND($V8<>"No",ISNUMBER(SEARCH("Mage",$C8)),NOT(ISNUMBER(SEARCH("Ideas",$F8)))),$X8,NA()) | AI8: =IF(AND($V8<>"No",ISNUMBER(SEARCH("Rogue",$C8)),NOT(ISNUMBER(SEARCH("Ideas",$F8)))),$X8,NA()) | AJ8: =IF($V8<>"No",$Y8,NA()) | AK8: =IF(AND($V8<>"No",ISNUMBER(SEARCH("Ideas",$F8))),$W8,NA()) | AL8: =IF(AND($V8<>"No",ISNUMBER(SEARCH("Cleric",$C8)),NOT(ISNUMBER(SEARCH("Ideas",$F8)))),$X8,NA())
A9: Phalanx | B9: Phalanx | C9: Knight | D9: 1 | E9: Uncommon | F9: Knight | G9: 1 | H9: 9 | I9: 0 | J9: 0 | K9: 0 | L9: 5 | M9: 0 | N9: 0 | O9: 0 | P9: 0 | Q9: 0 | R9: 0 | S9: 0 | V9: Yes | W9: =IF($V9="No","",ROUND((I9*w_Damage + N9*w_Poison + P9*w_Weaken*w_Horizon)*MIN(1+(G9-1)*w_OccEnemy,w_MaxEnemies) + (J9*w_Heal + K9*w_Shield + L9*w_Block + M9*w_Parry + O9*w_Strength*w_Horizon + S9*w_Combo)*MIN(1+(H9-1)*w_OccAlly,w_MaxAllies) + Q9*w_Draw + R9*w_Move,2)) | X9: =IF(W9="","",ROUND(W9/MAX(D9,1),2)) | Y9: =IF($V9="No","",ROUND((curve_Base+curve_Slope*D9)*IFERROR(VLOOKUP(E9,rarity_Mult,2,FALSE),1),2)) | Z9: =IF(OR(W9="",Y9=""),"",ROUND(W9-Y9,2)) | AA9: =IF(Z9="","",IF($V9="Partial","RIDER",IF(ABS(Z9)<=Y9*tol_Pct,"OK",IF(Z9>0,"OVER","UNDER")))) | AC9: =IF(AND($V9<>"No",$E9="Common",NOT(ISNUMBER(SEARCH("Ideas",$F9)))),$W9,NA()) | AD9: =IF(AND($V9<>"No",$E9="Uncommon",NOT(ISNUMBER(SEARCH("Ideas",$F9)))),$W9,NA()) | AE9: =IF(AND($V9<>"No",$E9="Rare",NOT(ISNUMBER(SEARCH("Ideas",$F9)))),$W9,NA()) | AF9: =IF(AND($V9<>"No",$E9="Legendary",NOT(ISNUMBER(SEARCH("Ideas",$F9)))),$W9,NA()) | AG9: =IF(AND($V9<>"No",ISNUMBER(SEARCH("Knight",$C9)),NOT(ISNUMBER(SEARCH("Ideas",$F9)))),$X9,NA()) | AH9: =IF(AND($V9<>"No",ISNUMBER(SEARCH("Mage",$C9)),NOT(ISNUMBER(SEARCH("Ideas",$F9)))),$X9,NA()) | AI9: =IF(AND($V9<>"No",ISNUMBER(SEARCH("Rogue",$C9)),NOT(ISNUMBER(SEARCH("Ideas",$F9)))),$X9,NA()) | AJ9: =IF($V9<>"No",$Y9,NA()) | AK9: =IF(AND($V9<>"No",ISNUMBER(SEARCH("Ideas",$F9))),$W9,NA()) | AL9: =IF(AND($V9<>"No",ISNUMBER(SEARCH("Cleric",$C9)),NOT(ISNUMBER(SEARCH("Ideas",$F9)))),$X9,NA())
A10: Shield | B10: Shield | C10: Knight | D10: 1 | E10: Common | F10: Knight | G10: 1 | H10: 1 | I10: 0 | J10: 0 | K10: 7 | L10: 0 | M10: 0 | N10: 0 | O10: 0 | P10: 0 | Q10: 0 | R10: 0 | S10: 0 | V10: Yes | W10: =IF($V10="No","",ROUND((I10*w_Damage + N10*w_Poison + P10*w_Weaken*w_Horizon)*MIN(1+(G10-1)*w_OccEnemy,w_MaxEnemies) + (J10*w_Heal + K10*w_Shield + L10*w_Block + M10*w_Parry + O10*w_Strength*w_Horizon + S10*w_Combo)*MIN(1+(H10-1)*w_OccAlly,w_MaxAllies) + Q10*w_Draw + R10*w_Move,2)) | X10: =IF(W10="","",ROUND(W10/MAX(D10,1),2)) | Y10: =IF($V10="No","",ROUND((curve_Base+curve_Slope*D10)*IFERROR(VLOOKUP(E10,rarity_Mult,2,FALSE),1),2)) | Z10: =IF(OR(W10="",Y10=""),"",ROUND(W10-Y10,2)) | AA10: =IF(Z10="","",IF($V10="Partial","RIDER",IF(ABS(Z10)<=Y10*tol_Pct,"OK",IF(Z10>0,"OVER","UNDER")))) | AC10: =IF(AND($V10<>"No",$E10="Common",NOT(ISNUMBER(SEARCH("Ideas",$F10)))),$W10,NA()) | AD10: =IF(AND($V10<>"No",$E10="Uncommon",NOT(ISNUMBER(SEARCH("Ideas",$F10)))),$W10,NA()) | AE10: =IF(AND($V10<>"No",$E10="Rare",NOT(ISNUMBER(SEARCH("Ideas",$F10)))),$W10,NA()) | AF10: =IF(AND($V10<>"No",$E10="Legendary",NOT(ISNUMBER(SEARCH("Ideas",$F10)))),$W10,NA()) | AG10: =IF(AND($V10<>"No",ISNUMBER(SEARCH("Knight",$C10)),NOT(ISNUMBER(SEARCH("Ideas",$F10)))),$X10,NA()) | AH10: =IF(AND($V10<>"No",ISNUMBER(SEARCH("Mage",$C10)),NOT(ISNUMBER(SEARCH("Ideas",$F10)))),$X10,NA()) | AI10: =IF(AND($V10<>"No",ISNUMBER(SEARCH("Rogue",$C10)),NOT(ISNUMBER(SEARCH("Ideas",$F10)))),$X10,NA()) | AJ10: =IF($V10<>"No",$Y10,NA()) | AK10: =IF(AND($V10<>"No",ISNUMBER(SEARCH("Ideas",$F10))),$W10,NA()) | AL10: =IF(AND($V10<>"No",ISNUMBER(SEARCH("Cleric",$C10)),NOT(ISNUMBER(SEARCH("Ideas",$F10)))),$X10,NA())
A11: Shield Wall | B11: Shield Wall | C11: Knight | D11: 1 | E11: Rare | F11: Knight | G11: 1 | H11: 13 | I11: 0 | J11: 0 | K11: 6 | L11: 0 | M11: 0 | N11: 0 | O11: 0 | P11: 0 | Q11: 0 | R11: 0 | S11: 0 | V11: Yes | W11: =IF($V11="No","",ROUND((I11*w_Damage + N11*w_Poison + P11*w_Weaken*w_Horizon)*MIN(1+(G11-1)*w_OccEnemy,w_MaxEnemies) + (J11*w_Heal + K11*w_Shield + L11*w_Block + M11*w_Parry + O11*w_Strength*w_Horizon + S11*w_Combo)*MIN(1+(H11-1)*w_OccAlly,w_MaxAllies) + Q11*w_Draw + R11*w_Move,2)) | X11: =IF(W11="","",ROUND(W11/MAX(D11,1),2)) | Y11: =IF($V11="No","",ROUND((curve_Base+curve_Slope*D11)*IFERROR(VLOOKUP(E11,rarity_Mult,2,FALSE),1),2)) | Z11: =IF(OR(W11="",Y11=""),"",ROUND(W11-Y11,2)) | AA11: =IF(Z11="","",IF($V11="Partial","RIDER",IF(ABS(Z11)<=Y11*tol_Pct,"OK",IF(Z11>0,"OVER","UNDER")))) | AC11: =IF(AND($V11<>"No",$E11="Common",NOT(ISNUMBER(SEARCH("Ideas",$F11)))),$W11,NA()) | AD11: =IF(AND($V11<>"No",$E11="Uncommon",NOT(ISNUMBER(SEARCH("Ideas",$F11)))),$W11,NA()) | AE11: =IF(AND($V11<>"No",$E11="Rare",NOT(ISNUMBER(SEARCH("Ideas",$F11)))),$W11,NA()) | AF11: =IF(AND($V11<>"No",$E11="Legendary",NOT(ISNUMBER(SEARCH("Ideas",$F11)))),$W11,NA()) | AG11: =IF(AND($V11<>"No",ISNUMBER(SEARCH("Knight",$C11)),NOT(ISNUMBER(SEARCH("Ideas",$F11)))),$X11,NA()) | AH11: =IF(AND($V11<>"No",ISNUMBER(SEARCH("Mage",$C11)),NOT(ISNUMBER(SEARCH("Ideas",$F11)))),$X11,NA()) | AI11: =IF(AND($V11<>"No",ISNUMBER(SEARCH("Rogue",$C11)),NOT(ISNUMBER(SEARCH("Ideas",$F11)))),$X11,NA()) | AJ11: =IF($V11<>"No",$Y11,NA()) | AK11: =IF(AND($V11<>"No",ISNUMBER(SEARCH("Ideas",$F11))),$W11,NA()) | AL11: =IF(AND($V11<>"No",ISNUMBER(SEARCH("Cleric",$C11)),NOT(ISNUMBER(SEARCH("Ideas",$F11)))),$X11,NA())
A12: Shoulder to Shoulder | B12: Shoulder to Shoulder | C12: Knight | D12: 1 | E12: Uncommon | F12: Knight | G12: 1 | H12: 9 | I12: 0 | J12: 0 | K12: 8 | L12: 0 | M12: 0 | N12: 0 | O12: 0 | P12: 0 | Q12: 0 | R12: 0 | S12: 0 | V12: Yes | W12: =IF($V12="No","",ROUND((I12*w_Damage + N12*w_Poison + P12*w_Weaken*w_Horizon)*MIN(1+(G12-1)*w_OccEnemy,w_MaxEnemies) + (J12*w_Heal + K12*w_Shield + L12*w_Block + M12*w_Parry + O12*w_Strength*w_Horizon + S12*w_Combo)*MIN(1+(H12-1)*w_OccAlly,w_MaxAllies) + Q12*w_Draw + R12*w_Move,2)) | X12: =IF(W12="","",ROUND(W12/MAX(D12,1),2)) | Y12: =IF($V12="No","",ROUND((curve_Base+curve_Slope*D12)*IFERROR(VLOOKUP(E12,rarity_Mult,2,FALSE),1),2)) | Z12: =IF(OR(W12="",Y12=""),"",ROUND(W12-Y12,2)) | AA12: =IF(Z12="","",IF($V12="Partial","RIDER",IF(ABS(Z12)<=Y12*tol_Pct,"OK",IF(Z12>0,"OVER","UNDER")))) | AC12: =IF(AND($V12<>"No",$E12="Common",NOT(ISNUMBER(SEARCH("Ideas",$F12)))),$W12,NA()) | AD12: =IF(AND($V12<>"No",$E12="Uncommon",NOT(ISNUMBER(SEARCH("Ideas",$F12)))),$W12,NA()) | AE12: =IF(AND($V12<>"No",$E12="Rare",NOT(ISNUMBER(SEARCH("Ideas",$F12)))),$W12,NA()) | AF12: =IF(AND($V12<>"No",$E12="Legendary",NOT(ISNUMBER(SEARCH("Ideas",$F12)))),$W12,NA()) | AG12: =IF(AND($V12<>"No",ISNUMBER(SEARCH("Knight",$C12)),NOT(ISNUMBER(SEARCH("Ideas",$F12)))),$X12,NA()) | AH12: =IF(AND($V12<>"No",ISNUMBER(SEARCH("Mage",$C12)),NOT(ISNUMBER(SEARCH("Ideas",$F12)))),$X12,NA()) | AI12: =IF(AND($V12<>"No",ISNUMBER(SEARCH("Rogue",$C12)),NOT(ISNUMBER(SEARCH("Ideas",$F12)))),$X12,NA()) | AJ12: =IF($V12<>"No",$Y12,NA()) | AK12: =IF(AND($V12<>"No",ISNUMBER(SEARCH("Ideas",$F12))),$W12,NA()) | AL12: =IF(AND($V12<>"No",ISNUMBER(SEARCH("Cleric",$C12)),NOT(ISNUMBER(SEARCH("Ideas",$F12)))),$X12,NA())
A13: Solitary Guard | B13: Solitary Guard | C13: Knight | D13: 1 | E13: Uncommon | F13: Knight | G13: 1 | H13: 1 | I13: 0 | J13: 0 | K13: 0 | L13: 5 | M13: 0 | N13: 0 | O13: 0 | P13: 0 | Q13: 0 | R13: 0 | S13: 0 | V13: Yes | W13: =IF($V13="No","",ROUND((I13*w_Damage + N13*w_Poison + P13*w_Weaken*w_Horizon)*MIN(1+(G13-1)*w_OccEnemy,w_MaxEnemies) + (J13*w_Heal + K13*w_Shield + L13*w_Block + M13*w_Parry + O13*w_Strength*w_Horizon + S13*w_Combo)*MIN(1+(H13-1)*w_OccAlly,w_MaxAllies) + Q13*w_Draw + R13*w_Move,2)) | X13: =IF(W13="","",ROUND(W13/MAX(D13,1),2)) | Y13: =IF($V13="No","",ROUND((curve_Base+curve_Slope*D13)*IFERROR(VLOOKUP(E13,rarity_Mult,2,FALSE),1),2)) | Z13: =IF(OR(W13="",Y13=""),"",ROUND(W13-Y13,2)) | AA13: =IF(Z13="","",IF($V13="Partial","RIDER",IF(ABS(Z13)<=Y13*tol_Pct,"OK",IF(Z13>0,"OVER","UNDER")))) | AC13: =IF(AND($V13<>"No",$E13="Common",NOT(ISNUMBER(SEARCH("Ideas",$F13)))),$W13,NA()) | AD13: =IF(AND($V13<>"No",$E13="Uncommon",NOT(ISNUMBER(SEARCH("Ideas",$F13)))),$W13,NA()) | AE13: =IF(AND($V13<>"No",$E13="Rare",NOT(ISNUMBER(SEARCH("Ideas",$F13)))),$W13,NA()) | AF13: =IF(AND($V13<>"No",$E13="Legendary",NOT(ISNUMBER(SEARCH("Ideas",$F13)))),$W13,NA()) | AG13: =IF(AND($V13<>"No",ISNUMBER(SEARCH("Knight",$C13)),NOT(ISNUMBER(SEARCH("Ideas",$F13)))),$X13,NA()) | AH13: =IF(AND($V13<>"No",ISNUMBER(SEARCH("Mage",$C13)),NOT(ISNUMBER(SEARCH("Ideas",$F13)))),$X13,NA()) | AI13: =IF(AND($V13<>"No",ISNUMBER(SEARCH("Rogue",$C13)),NOT(ISNUMBER(SEARCH("Ideas",$F13)))),$X13,NA()) | AJ13: =IF($V13<>"No",$Y13,NA()) | AK13: =IF(AND($V13<>"No",ISNUMBER(SEARCH("Ideas",$F13))),$W13,NA()) | AL13: =IF(AND($V13<>"No",ISNUMBER(SEARCH("Cleric",$C13)),NOT(ISNUMBER(SEARCH("Ideas",$F13)))),$X13,NA())
A14: Steely Resolve | B14: Steely Resolve | C14: Knight | D14: 1 | E14: Uncommon | F14: Knight | G14: 1 | H14: 1 | I14: 0 | J14: 0 | K14: 5 | L14: 0 | M14: 0 | N14: 0 | O14: 0 | P14: 0 | Q14: 1 | R14: 0 | S14: 0 | V14: Yes | W14: =IF($V14="No","",ROUND((I14*w_Damage + N14*w_Poison + P14*w_Weaken*w_Horizon)*MIN(1+(G14-1)*w_OccEnemy,w_MaxEnemies) + (J14*w_Heal + K14*w_Shield + L14*w_Block + M14*w_Parry + O14*w_Strength*w_Horizon + S14*w_Combo)*MIN(1+(H14-1)*w_OccAlly,w_MaxAllies) + Q14*w_Draw + R14*w_Move,2)) | X14: =IF(W14="","",ROUND(W14/MAX(D14,1),2)) | Y14: =IF($V14="No","",ROUND((curve_Base+curve_Slope*D14)*IFERROR(VLOOKUP(E14,rarity_Mult,2,FALSE),1),2)) | Z14: =IF(OR(W14="",Y14=""),"",ROUND(W14-Y14,2)) | AA14: =IF(Z14="","",IF($V14="Partial","RIDER",IF(ABS(Z14)<=Y14*tol_Pct,"OK",IF(Z14>0,"OVER","UNDER")))) | AC14: =IF(AND($V14<>"No",$E14="Common",NOT(ISNUMBER(SEARCH("Ideas",$F14)))),$W14,NA()) | AD14: =IF(AND($V14<>"No",$E14="Uncommon",NOT(ISNUMBER(SEARCH("Ideas",$F14)))),$W14,NA()) | AE14: =IF(AND($V14<>"No",$E14="Rare",NOT(ISNUMBER(SEARCH("Ideas",$F14)))),$W14,NA()) | AF14: =IF(AND($V14<>"No",$E14="Legendary",NOT(ISNUMBER(SEARCH("Ideas",$F14)))),$W14,NA()) | AG14: =IF(AND($V14<>"No",ISNUMBER(SEARCH("Knight",$C14)),NOT(ISNUMBER(SEARCH("Ideas",$F14)))),$X14,NA()) | AH14: =IF(AND($V14<>"No",ISNUMBER(SEARCH("Mage",$C14)),NOT(ISNUMBER(SEARCH("Ideas",$F14)))),$X14,NA()) | AI14: =IF(AND($V14<>"No",ISNUMBER(SEARCH("Rogue",$C14)),NOT(ISNUMBER(SEARCH("Ideas",$F14)))),$X14,NA()) | AJ14: =IF($V14<>"No",$Y14,NA()) | AK14: =IF(AND($V14<>"No",ISNUMBER(SEARCH("Ideas",$F14))),$W14,NA()) | AL14: =IF(AND($V14<>"No",ISNUMBER(SEARCH("Cleric",$C14)),NOT(ISNUMBER(SEARCH("Ideas",$F14)))),$X14,NA())
A15: Taunt | B15: Taunt | C15: Knight | D15: 1 | E15: Uncommon | F15: Knight | G15: 1 | H15: 1 | I15: 0 | J15: 0 | K15: 0 | L15: 0 | M15: 0 | N15: 0 | O15: 0 | P15: 0 | Q15: 0 | R15: 0 | S15: 0 | U15: Taunt | V15: No | W15: =IF($V15="No","",ROUND((I15*w_Damage + N15*w_Poison + P15*w_Weaken*w_Horizon)*MIN(1+(G15-1)*w_OccEnemy,w_MaxEnemies) + (J15*w_Heal + K15*w_Shield + L15*w_Block + M15*w_Parry + O15*w_Strength*w_Horizon + S15*w_Combo)*MIN(1+(H15-1)*w_OccAlly,w_MaxAllies) + Q15*w_Draw + R15*w_Move,2)) | X15: =IF(W15="","",ROUND(W15/MAX(D15,1),2)) | Y15: =IF($V15="No","",ROUND((curve_Base+curve_Slope*D15)*IFERROR(VLOOKUP(E15,rarity_Mult,2,FALSE),1),2)) | Z15: =IF(OR(W15="",Y15=""),"",ROUND(W15-Y15,2)) | AA15: =IF(Z15="","",IF($V15="Partial","RIDER",IF(ABS(Z15)<=Y15*tol_Pct,"OK",IF(Z15>0,"OVER","UNDER")))) | AC15: =IF(AND($V15<>"No",$E15="Common",NOT(ISNUMBER(SEARCH("Ideas",$F15)))),$W15,NA()) | AD15: =IF(AND($V15<>"No",$E15="Uncommon",NOT(ISNUMBER(SEARCH("Ideas",$F15)))),$W15,NA()) | AE15: =IF(AND($V15<>"No",$E15="Rare",NOT(ISNUMBER(SEARCH("Ideas",$F15)))),$W15,NA()) | AF15: =IF(AND($V15<>"No",$E15="Legendary",NOT(ISNUMBER(SEARCH("Ideas",$F15)))),$W15,NA()) | AG15: =IF(AND($V15<>"No",ISNUMBER(SEARCH("Knight",$C15)),NOT(ISNUMBER(SEARCH("Ideas",$F15)))),$X15,NA()) | AH15: =IF(AND($V15<>"No",ISNUMBER(SEARCH("Mage",$C15)),NOT(ISNUMBER(SEARCH("Ideas",$F15)))),$X15,NA()) | AI15: =IF(AND($V15<>"No",ISNUMBER(SEARCH("Rogue",$C15)),NOT(ISNUMBER(SEARCH("Ideas",$F15)))),$X15,NA()) | AJ15: =IF($V15<>"No",$Y15,NA()) | AK15: =IF(AND($V15<>"No",ISNUMBER(SEARCH("Ideas",$F15))),$W15,NA()) | AL15: =IF(AND($V15<>"No",ISNUMBER(SEARCH("Cleric",$C15)),NOT(ISNUMBER(SEARCH("Ideas",$F15)))),$X15,NA())
A16: Totem Guard | B16: Totem Guard | C16: Knight | D16: 1 | E16: Uncommon | F16: Knight | G16: 1 | H16: 1 | I16: 0 | J16: 0 | K16: 0 | L16: 5 | M16: 0 | N16: 0 | O16: 0 | P16: 0 | Q16: 1 | R16: 0 | S16: 0 | V16: Yes | W16: =IF($V16="No","",ROUND((I16*w_Damage + N16*w_Poison + P16*w_Weaken*w_Horizon)*MIN(1+(G16-1)*w_OccEnemy,w_MaxEnemies) + (J16*w_Heal + K16*w_Shield + L16*w_Block + M16*w_Parry + O16*w_Strength*w_Horizon + S16*w_Combo)*MIN(1+(H16-1)*w_OccAlly,w_MaxAllies) + Q16*w_Draw + R16*w_Move,2)) | X16: =IF(W16="","",ROUND(W16/MAX(D16,1),2)) | Y16: =IF($V16="No","",ROUND((curve_Base+curve_Slope*D16)*IFERROR(VLOOKUP(E16,rarity_Mult,2,FALSE),1),2)) | Z16: =IF(OR(W16="",Y16=""),"",ROUND(W16-Y16,2)) | AA16: =IF(Z16="","",IF($V16="Partial","RIDER",IF(ABS(Z16)<=Y16*tol_Pct,"OK",IF(Z16>0,"OVER","UNDER")))) | AC16: =IF(AND($V16<>"No",$E16="Common",NOT(ISNUMBER(SEARCH("Ideas",$F16)))),$W16,NA()) | AD16: =IF(AND($V16<>"No",$E16="Uncommon",NOT(ISNUMBER(SEARCH("Ideas",$F16)))),$W16,NA()) | AE16: =IF(AND($V16<>"No",$E16="Rare",NOT(ISNUMBER(SEARCH("Ideas",$F16)))),$W16,NA()) | AF16: =IF(AND($V16<>"No",$E16="Legendary",NOT(ISNUMBER(SEARCH("Ideas",$F16)))),$W16,NA()) | AG16: =IF(AND($V16<>"No",ISNUMBER(SEARCH("Knight",$C16)),NOT(ISNUMBER(SEARCH("Ideas",$F16)))),$X16,NA()) | AH16: =IF(AND($V16<>"No",ISNUMBER(SEARCH("Mage",$C16)),NOT(ISNUMBER(SEARCH("Ideas",$F16)))),$X16,NA()) | AI16: =IF(AND($V16<>"No",ISNUMBER(SEARCH("Rogue",$C16)),NOT(ISNUMBER(SEARCH("Ideas",$F16)))),$X16,NA()) | AJ16: =IF($V16<>"No",$Y16,NA()) | AK16: =IF(AND($V16<>"No",ISNUMBER(SEARCH("Ideas",$F16))),$W16,NA()) | AL16: =IF(AND($V16<>"No",ISNUMBER(SEARCH("Cleric",$C16)),NOT(ISNUMBER(SEARCH("Ideas",$F16)))),$X16,NA())
A17: Tower Shield | B17: Tower Shield | C17: Knight | D17: 1 | E17: Uncommon | F17: Knight | G17: 1 | H17: 1 | I17: 0 | J17: 0 | K17: 11 | L17: 0 | M17: 0 | N17: 0 | O17: 0 | P17: 0 | Q17: 0 | R17: 0 | S17: 0 | V17: Yes | W17: =IF($V17="No","",ROUND((I17*w_Damage + N17*w_Poison + P17*w_Weaken*w_Horizon)*MIN(1+(G17-1)*w_OccEnemy,w_MaxEnemies) + (J17*w_Heal + K17*w_Shield + L17*w_Block + M17*w_Parry + O17*w_Strength*w_Horizon + S17*w_Combo)*MIN(1+(H17-1)*w_OccAlly,w_MaxAllies) + Q17*w_Draw + R17*w_Move,2)) | X17: =IF(W17="","",ROUND(W17/MAX(D17,1),2)) | Y17: =IF($V17="No","",ROUND((curve_Base+curve_Slope*D17)*IFERROR(VLOOKUP(E17,rarity_Mult,2,FALSE),1),2)) | Z17: =IF(OR(W17="",Y17=""),"",ROUND(W17-Y17,2)) | AA17: =IF(Z17="","",IF($V17="Partial","RIDER",IF(ABS(Z17)<=Y17*tol_Pct,"OK",IF(Z17>0,"OVER","UNDER")))) | AC17: =IF(AND($V17<>"No",$E17="Common",NOT(ISNUMBER(SEARCH("Ideas",$F17)))),$W17,NA()) | AD17: =IF(AND($V17<>"No",$E17="Uncommon",NOT(ISNUMBER(SEARCH("Ideas",$F17)))),$W17,NA()) | AE17: =IF(AND($V17<>"No",$E17="Rare",NOT(ISNUMBER(SEARCH("Ideas",$F17)))),$W17,NA()) | AF17: =IF(AND($V17<>"No",$E17="Legendary",NOT(ISNUMBER(SEARCH("Ideas",$F17)))),$W17,NA()) | AG17: =IF(AND($V17<>"No",ISNUMBER(SEARCH("Knight",$C17)),NOT(ISNUMBER(SEARCH("Ideas",$F17)))),$X17,NA()) | AH17: =IF(AND($V17<>"No",ISNUMBER(SEARCH("Mage",$C17)),NOT(ISNUMBER(SEARCH("Ideas",$F17)))),$X17,NA()) | AI17: =IF(AND($V17<>"No",ISNUMBER(SEARCH("Rogue",$C17)),NOT(ISNUMBER(SEARCH("Ideas",$F17)))),$X17,NA()) | AJ17: =IF($V17<>"No",$Y17,NA()) | AK17: =IF(AND($V17<>"No",ISNUMBER(SEARCH("Ideas",$F17))),$W17,NA()) | AL17: =IF(AND($V17<>"No",ISNUMBER(SEARCH("Cleric",$C17)),NOT(ISNUMBER(SEARCH("Ideas",$F17)))),$X17,NA())
A18: Guardian's Aegis | B18: Guardian's Aegis | C18: Knight | D18: 2 | E18: Uncommon | F18: Knight | G18: 1 | H18: 13 | I18: 0 | J18: 0 | K18: 5 | L18: 0 | M18: 0 | N18: 0 | O18: 0 | P18: 0 | Q18: 0 | R18: 0 | S18: 0 | V18: Yes | W18: =IF($V18="No","",ROUND((I18*w_Damage + N18*w_Poison + P18*w_Weaken*w_Horizon)*MIN(1+(G18-1)*w_OccEnemy,w_MaxEnemies) + (J18*w_Heal + K18*w_Shield + L18*w_Block + M18*w_Parry + O18*w_Strength*w_Horizon + S18*w_Combo)*MIN(1+(H18-1)*w_OccAlly,w_MaxAllies) + Q18*w_Draw + R18*w_Move,2)) | X18: =IF(W18="","",ROUND(W18/MAX(D18,1),2)) | Y18: =IF($V18="No","",ROUND((curve_Base+curve_Slope*D18)*IFERROR(VLOOKUP(E18,rarity_Mult,2,FALSE),1),2)) | Z18: =IF(OR(W18="",Y18=""),"",ROUND(W18-Y18,2)) | AA18: =IF(Z18="","",IF($V18="Partial","RIDER",IF(ABS(Z18)<=Y18*tol_Pct,"OK",IF(Z18>0,"OVER","UNDER")))) | AC18: =IF(AND($V18<>"No",$E18="Common",NOT(ISNUMBER(SEARCH("Ideas",$F18)))),$W18,NA()) | AD18: =IF(AND($V18<>"No",$E18="Uncommon",NOT(ISNUMBER(SEARCH("Ideas",$F18)))),$W18,NA()) | AE18: =IF(AND($V18<>"No",$E18="Rare",NOT(ISNUMBER(SEARCH("Ideas",$F18)))),$W18,NA()) | AF18: =IF(AND($V18<>"No",$E18="Legendary",NOT(ISNUMBER(SEARCH("Ideas",$F18)))),$W18,NA()) | AG18: =IF(AND($V18<>"No",ISNUMBER(SEARCH("Knight",$C18)),NOT(ISNUMBER(SEARCH("Ideas",$F18)))),$X18,NA()) | AH18: =IF(AND($V18<>"No",ISNUMBER(SEARCH("Mage",$C18)),NOT(ISNUMBER(SEARCH("Ideas",$F18)))),$X18,NA()) | AI18: =IF(AND($V18<>"No",ISNUMBER(SEARCH("Rogue",$C18)),NOT(ISNUMBER(SEARCH("Ideas",$F18)))),$X18,NA()) | AJ18: =IF($V18<>"No",$Y18,NA()) | AK18: =IF(AND($V18<>"No",ISNUMBER(SEARCH("Ideas",$F18))),$W18,NA()) | AL18: =IF(AND($V18<>"No",ISNUMBER(SEARCH("Cleric",$C18)),NOT(ISNUMBER(SEARCH("Ideas",$F18)))),$X18,NA())
A19: Hold the Line | B19: Hold the Line | C19: Knight | D19: 2 | E19: Rare | F19: Knight | G19: 1 | H19: 9 | I19: 0 | J19: 0 | K19: 12 | L19: 0 | M19: 0 | N19: 0 | O19: 0 | P19: 0 | Q19: 1 | R19: 0 | S19: 0 | V19: Yes | W19: =IF($V19="No","",ROUND((I19*w_Damage + N19*w_Poison + P19*w_Weaken*w_Horizon)*MIN(1+(G19-1)*w_OccEnemy,w_MaxEnemies) + (J19*w_Heal + K19*w_Shield + L19*w_Block + M19*w_Parry + O19*w_Strength*w_Horizon + S19*w_Combo)*MIN(1+(H19-1)*w_OccAlly,w_MaxAllies) + Q19*w_Draw + R19*w_Move,2)) | X19: =IF(W19="","",ROUND(W19/MAX(D19,1),2)) | Y19: =IF($V19="No","",ROUND((curve_Base+curve_Slope*D19)*IFERROR(VLOOKUP(E19,rarity_Mult,2,FALSE),1),2)) | Z19: =IF(OR(W19="",Y19=""),"",ROUND(W19-Y19,2)) | AA19: =IF(Z19="","",IF($V19="Partial","RIDER",IF(ABS(Z19)<=Y19*tol_Pct,"OK",IF(Z19>0,"OVER","UNDER")))) | AC19: =IF(AND($V19<>"No",$E19="Common",NOT(ISNUMBER(SEARCH("Ideas",$F19)))),$W19,NA()) | AD19: =IF(AND($V19<>"No",$E19="Uncommon",NOT(ISNUMBER(SEARCH("Ideas",$F19)))),$W19,NA()) | AE19: =IF(AND($V19<>"No",$E19="Rare",NOT(ISNUMBER(SEARCH("Ideas",$F19)))),$W19,NA()) | AF19: =IF(AND($V19<>"No",$E19="Legendary",NOT(ISNUMBER(SEARCH("Ideas",$F19)))),$W19,NA()) | AG19: =IF(AND($V19<>"No",ISNUMBER(SEARCH("Knight",$C19)),NOT(ISNUMBER(SEARCH("Ideas",$F19)))),$X19,NA()) | AH19: =IF(AND($V19<>"No",ISNUMBER(SEARCH("Mage",$C19)),NOT(ISNUMBER(SEARCH("Ideas",$F19)))),$X19,NA()) | AI19: =IF(AND($V19<>"No",ISNUMBER(SEARCH("Rogue",$C19)),NOT(ISNUMBER(SEARCH("Ideas",$F19)))),$X19,NA()) | AJ19: =IF($V19<>"No",$Y19,NA()) | AK19: =IF(AND($V19<>"No",ISNUMBER(SEARCH("Ideas",$F19))),$W19,NA()) | AL19: =IF(AND($V19<>"No",ISNUMBER(SEARCH("Cleric",$C19)),NOT(ISNUMBER(SEARCH("Ideas",$F19)))),$X19,NA())
A20: Rally the Line | B20: Rally the Line | C20: Knight | D20: 2 | E20: Rare | F20: Knight | G20: 1 | H20: 13 | I20: 0 | J20: 0 | K20: 6 | L20: 0 | M20: 0 | N20: 0 | O20: 0 | P20: 0 | Q20: 1 | R20: 0 | S20: 0 | V20: Yes | W20: =IF($V20="No","",ROUND((I20*w_Damage + N20*w_Poison + P20*w_Weaken*w_Horizon)*MIN(1+(G20-1)*w_OccEnemy,w_MaxEnemies) + (J20*w_Heal + K20*w_Shield + L20*w_Block + M20*w_Parry + O20*w_Strength*w_Horizon + S20*w_Combo)*MIN(1+(H20-1)*w_OccAlly,w_MaxAllies) + Q20*w_Draw + R20*w_Move,2)) | X20: =IF(W20="","",ROUND(W20/MAX(D20,1),2)) | Y20: =IF($V20="No","",ROUND((curve_Base+curve_Slope*D20)*IFERROR(VLOOKUP(E20,rarity_Mult,2,FALSE),1),2)) | Z20: =IF(OR(W20="",Y20=""),"",ROUND(W20-Y20,2)) | AA20: =IF(Z20="","",IF($V20="Partial","RIDER",IF(ABS(Z20)<=Y20*tol_Pct,"OK",IF(Z20>0,"OVER","UNDER")))) | AC20: =IF(AND($V20<>"No",$E20="Common",NOT(ISNUMBER(SEARCH("Ideas",$F20)))),$W20,NA()) | AD20: =IF(AND($V20<>"No",$E20="Uncommon",NOT(ISNUMBER(SEARCH("Ideas",$F20)))),$W20,NA()) | AE20: =IF(AND($V20<>"No",$E20="Rare",NOT(ISNUMBER(SEARCH("Ideas",$F20)))),$W20,NA()) | AF20: =IF(AND($V20<>"No",$E20="Legendary",NOT(ISNUMBER(SEARCH("Ideas",$F20)))),$W20,NA()) | AG20: =IF(AND($V20<>"No",ISNUMBER(SEARCH("Knight",$C20)),NOT(ISNUMBER(SEARCH("Ideas",$F20)))),$X20,NA()) | AH20: =IF(AND($V20<>"No",ISNUMBER(SEARCH("Mage",$C20)),NOT(ISNUMBER(SEARCH("Ideas",$F20)))),$X20,NA()) | AI20: =IF(AND($V20<>"No",ISNUMBER(SEARCH("Rogue",$C20)),NOT(ISNUMBER(SEARCH("Ideas",$F20)))),$X20,NA()) | AJ20: =IF($V20<>"No",$Y20,NA()) | AK20: =IF(AND($V20<>"No",ISNUMBER(SEARCH("Ideas",$F20))),$W20,NA()) | AL20: =IF(AND($V20<>"No",ISNUMBER(SEARCH("Cleric",$C20)),NOT(ISNUMBER(SEARCH("Ideas",$F20)))),$X20,NA())
A21: Strengthen | B21: Strengthen | C21: Knight | D21: 1 | E21: Uncommon | F21: Knight | G21: 1 | H21: 1 | I21: 0 | J21: 0 | K21: 0 | L21: 0 | M21: 0 | N21: 0 | O21: 3 | P21: 0 | Q21: 0 | R21: 0 | S21: 0 | V21: Yes | W21: =IF($V21="No","",ROUND((I21*w_Damage + N21*w_Poison + P21*w_Weaken*w_Horizon)*MIN(1+(G21-1)*w_OccEnemy,w_MaxEnemies) + (J21*w_Heal + K21*w_Shield + L21*w_Block + M21*w_Parry + O21*w_Strength*w_Horizon + S21*w_Combo)*MIN(1+(H21-1)*w_OccAlly,w_MaxAllies) + Q21*w_Draw + R21*w_Move,2)) | X21: =IF(W21="","",ROUND(W21/MAX(D21,1),2)) | Y21: =IF($V21="No","",ROUND((curve_Base+curve_Slope*D21)*IFERROR(VLOOKUP(E21,rarity_Mult,2,FALSE),1),2)) | Z21: =IF(OR(W21="",Y21=""),"",ROUND(W21-Y21,2)) | AA21: =IF(Z21="","",IF($V21="Partial","RIDER",IF(ABS(Z21)<=Y21*tol_Pct,"OK",IF(Z21>0,"OVER","UNDER")))) | AC21: =IF(AND($V21<>"No",$E21="Common",NOT(ISNUMBER(SEARCH("Ideas",$F21)))),$W21,NA()) | AD21: =IF(AND($V21<>"No",$E21="Uncommon",NOT(ISNUMBER(SEARCH("Ideas",$F21)))),$W21,NA()) | AE21: =IF(AND($V21<>"No",$E21="Rare",NOT(ISNUMBER(SEARCH("Ideas",$F21)))),$W21,NA()) | AF21: =IF(AND($V21<>"No",$E21="Legendary",NOT(ISNUMBER(SEARCH("Ideas",$F21)))),$W21,NA()) | AG21: =IF(AND($V21<>"No",ISNUMBER(SEARCH("Knight",$C21)),NOT(ISNUMBER(SEARCH("Ideas",$F21)))),$X21,NA()) | AH21: =IF(AND($V21<>"No",ISNUMBER(SEARCH("Mage",$C21)),NOT(ISNUMBER(SEARCH("Ideas",$F21)))),$X21,NA()) | AI21: =IF(AND($V21<>"No",ISNUMBER(SEARCH("Rogue",$C21)),NOT(ISNUMBER(SEARCH("Ideas",$F21)))),$X21,NA()) | AJ21: =IF($V21<>"No",$Y21,NA()) | AK21: =IF(AND($V21<>"No",ISNUMBER(SEARCH("Ideas",$F21))),$W21,NA()) | AL21: =IF(AND($V21<>"No",ISNUMBER(SEARCH("Cleric",$C21)),NOT(ISNUMBER(SEARCH("Ideas",$F21)))),$X21,NA())
A22: Buff | B22: Buff | C22: Knight | D22: 2 | E22: Uncommon | F22: Knight | G22: 1 | H22: 1 | I22: 0 | J22: 0 | K22: 0 | L22: 0 | M22: 0 | N22: 0 | O22: 0 | P22: 0 | Q22: 0 | R22: 0 | S22: 1 | V22: Yes | W22: =IF($V22="No","",ROUND((I22*w_Damage + N22*w_Poison + P22*w_Weaken*w_Horizon)*MIN(1+(G22-1)*w_OccEnemy,w_MaxEnemies) + (J22*w_Heal + K22*w_Shield + L22*w_Block + M22*w_Parry + O22*w_Strength*w_Horizon + S22*w_Combo)*MIN(1+(H22-1)*w_OccAlly,w_MaxAllies) + Q22*w_Draw + R22*w_Move,2)) | X22: =IF(W22="","",ROUND(W22/MAX(D22,1),2)) | Y22: =IF($V22="No","",ROUND((curve_Base+curve_Slope*D22)*IFERROR(VLOOKUP(E22,rarity_Mult,2,FALSE),1),2)) | Z22: =IF(OR(W22="",Y22=""),"",ROUND(W22-Y22,2)) | AA22: =IF(Z22="","",IF($V22="Partial","RIDER",IF(ABS(Z22)<=Y22*tol_Pct,"OK",IF(Z22>0,"OVER","UNDER")))) | AC22: =IF(AND($V22<>"No",$E22="Common",NOT(ISNUMBER(SEARCH("Ideas",$F22)))),$W22,NA()) | AD22: =IF(AND($V22<>"No",$E22="Uncommon",NOT(ISNUMBER(SEARCH("Ideas",$F22)))),$W22,NA()) | AE22: =IF(AND($V22<>"No",$E22="Rare",NOT(ISNUMBER(SEARCH("Ideas",$F22)))),$W22,NA()) | AF22: =IF(AND($V22<>"No",$E22="Legendary",NOT(ISNUMBER(SEARCH("Ideas",$F22)))),$W22,NA()) | AG22: =IF(AND($V22<>"No",ISNUMBER(SEARCH("Knight",$C22)),NOT(ISNUMBER(SEARCH("Ideas",$F22)))),$X22,NA()) | AH22: =IF(AND($V22<>"No",ISNUMBER(SEARCH("Mage",$C22)),NOT(ISNUMBER(SEARCH("Ideas",$F22)))),$X22,NA()) | AI22: =IF(AND($V22<>"No",ISNUMBER(SEARCH("Rogue",$C22)),NOT(ISNUMBER(SEARCH("Ideas",$F22)))),$X22,NA()) | AJ22: =IF($V22<>"No",$Y22,NA()) | AK22: =IF(AND($V22<>"No",ISNUMBER(SEARCH("Ideas",$F22))),$W22,NA()) | AL22: =IF(AND($V22<>"No",ISNUMBER(SEARCH("Cleric",$C22)),NOT(ISNUMBER(SEARCH("Ideas",$F22)))),$X22,NA())
A23: Second Wind | B23: Second Wind | C23: Knight | D23: 1 | E23: Uncommon | F23: Knight | G23: 1 | H23: 1 | I23: 0 | J23: 5 | K23: 0 | L23: 0 | M23: 0 | N23: 0 | O23: 0 | P23: 0 | Q23: 0 | R23: 0 | S23: 0 | V23: Yes | W23: =IF($V23="No","",ROUND((I23*w_Damage + N23*w_Poison + P23*w_Weaken*w_Horizon)*MIN(1+(G23-1)*w_OccEnemy,w_MaxEnemies) + (J23*w_Heal + K23*w_Shield + L23*w_Block + M23*w_Parry + O23*w_Strength*w_Horizon + S23*w_Combo)*MIN(1+(H23-1)*w_OccAlly,w_MaxAllies) + Q23*w_Draw + R23*w_Move,2)) | X23: =IF(W23="","",ROUND(W23/MAX(D23,1),2)) | Y23: =IF($V23="No","",ROUND((curve_Base+curve_Slope*D23)*IFERROR(VLOOKUP(E23,rarity_Mult,2,FALSE),1),2)) | Z23: =IF(OR(W23="",Y23=""),"",ROUND(W23-Y23,2)) | AA23: =IF(Z23="","",IF($V23="Partial","RIDER",IF(ABS(Z23)<=Y23*tol_Pct,"OK",IF(Z23>0,"OVER","UNDER")))) | AC23: =IF(AND($V23<>"No",$E23="Common",NOT(ISNUMBER(SEARCH("Ideas",$F23)))),$W23,NA()) | AD23: =IF(AND($V23<>"No",$E23="Uncommon",NOT(ISNUMBER(SEARCH("Ideas",$F23)))),$W23,NA()) | AE23: =IF(AND($V23<>"No",$E23="Rare",NOT(ISNUMBER(SEARCH("Ideas",$F23)))),$W23,NA()) | AF23: =IF(AND($V23<>"No",$E23="Legendary",NOT(ISNUMBER(SEARCH("Ideas",$F23)))),$W23,NA()) | AG23: =IF(AND($V23<>"No",ISNUMBER(SEARCH("Knight",$C23)),NOT(ISNUMBER(SEARCH("Ideas",$F23)))),$X23,NA()) | AH23: =IF(AND($V23<>"No",ISNUMBER(SEARCH("Mage",$C23)),NOT(ISNUMBER(SEARCH("Ideas",$F23)))),$X23,NA()) | AI23: =IF(AND($V23<>"No",ISNUMBER(SEARCH("Rogue",$C23)),NOT(ISNUMBER(SEARCH("Ideas",$F23)))),$X23,NA()) | AJ23: =IF($V23<>"No",$Y23,NA()) | AK23: =IF(AND($V23<>"No",ISNUMBER(SEARCH("Ideas",$F23))),$W23,NA()) | AL23: =IF(AND($V23<>"No",ISNUMBER(SEARCH("Cleric",$C23)),NOT(ISNUMBER(SEARCH("Ideas",$F23)))),$X23,NA())
A24: Attack and Block | B24: Attack and Block | C24: Knight | D24: 1 | E24: Uncommon | F24: Knight | G24: 1 | H24: 1 | I24: 5 | J24: 0 | K24: 5 | L24: 0 | M24: 0 | N24: 0 | O24: 0 | P24: 0 | Q24: 0 | R24: 0 | S24: 0 | V24: Yes | W24: =IF($V24="No","",ROUND((I24*w_Damage + N24*w_Poison + P24*w_Weaken*w_Horizon)*MIN(1+(G24-1)*w_OccEnemy,w_MaxEnemies) + (J24*w_Heal + K24*w_Shield + L24*w_Block + M24*w_Parry + O24*w_Strength*w_Horizon + S24*w_Combo)*MIN(1+(H24-1)*w_OccAlly,w_MaxAllies) + Q24*w_Draw + R24*w_Move,2)) | X24: =IF(W24="","",ROUND(W24/MAX(D24,1),2)) | Y24: =IF($V24="No","",ROUND((curve_Base+curve_Slope*D24)*IFERROR(VLOOKUP(E24,rarity_Mult,2,FALSE),1),2)) | Z24: =IF(OR(W24="",Y24=""),"",ROUND(W24-Y24,2)) | AA24: =IF(Z24="","",IF($V24="Partial","RIDER",IF(ABS(Z24)<=Y24*tol_Pct,"OK",IF(Z24>0,"OVER","UNDER")))) | AC24: =IF(AND($V24<>"No",$E24="Common",NOT(ISNUMBER(SEARCH("Ideas",$F24)))),$W24,NA()) | AD24: =IF(AND($V24<>"No",$E24="Uncommon",NOT(ISNUMBER(SEARCH("Ideas",$F24)))),$W24,NA()) | AE24: =IF(AND($V24<>"No",$E24="Rare",NOT(ISNUMBER(SEARCH("Ideas",$F24)))),$W24,NA()) | AF24: =IF(AND($V24<>"No",$E24="Legendary",NOT(ISNUMBER(SEARCH("Ideas",$F24)))),$W24,NA()) | AG24: =IF(AND($V24<>"No",ISNUMBER(SEARCH("Knight",$C24)),NOT(ISNUMBER(SEARCH("Ideas",$F24)))),$X24,NA()) | AH24: =IF(AND($V24<>"No",ISNUMBER(SEARCH("Mage",$C24)),NOT(ISNUMBER(SEARCH("Ideas",$F24)))),$X24,NA()) | AI24: =IF(AND($V24<>"No",ISNUMBER(SEARCH("Rogue",$C24)),NOT(ISNUMBER(SEARCH("Ideas",$F24)))),$X24,NA()) | AJ24: =IF($V24<>"No",$Y24,NA()) | AK24: =IF(AND($V24<>"No",ISNUMBER(SEARCH("Ideas",$F24))),$W24,NA()) | AL24: =IF(AND($V24<>"No",ISNUMBER(SEARCH("Cleric",$C24)),NOT(ISNUMBER(SEARCH("Ideas",$F24)))),$X24,NA())
A25: Cleave | B25: Cleave | C25: Knight | D25: 1 | E25: Uncommon | F25: Knight | G25: 3 | H25: 1 | I25: 5 | J25: 0 | K25: 0 | L25: 0 | M25: 0 | N25: 0 | O25: 0 | P25: 0 | Q25: 0 | R25: 0 | S25: 0 | V25: Yes | W25: =IF($V25="No","",ROUND((I25*w_Damage + N25*w_Poison + P25*w_Weaken*w_Horizon)*MIN(1+(G25-1)*w_OccEnemy,w_MaxEnemies) + (J25*w_Heal + K25*w_Shield + L25*w_Block + M25*w_Parry + O25*w_Strength*w_Horizon + S25*w_Combo)*MIN(1+(H25-1)*w_OccAlly,w_MaxAllies) + Q25*w_Draw + R25*w_Move,2)) | X25: =IF(W25="","",ROUND(W25/MAX(D25,1),2)) | Y25: =IF($V25="No","",ROUND((curve_Base+curve_Slope*D25)*IFERROR(VLOOKUP(E25,rarity_Mult,2,FALSE),1),2)) | Z25: =IF(OR(W25="",Y25=""),"",ROUND(W25-Y25,2)) | AA25: =IF(Z25="","",IF($V25="Partial","RIDER",IF(ABS(Z25)<=Y25*tol_Pct,"OK",IF(Z25>0,"OVER","UNDER")))) | AC25: =IF(AND($V25<>"No",$E25="Common",NOT(ISNUMBER(SEARCH("Ideas",$F25)))),$W25,NA()) | AD25: =IF(AND($V25<>"No",$E25="Uncommon",NOT(ISNUMBER(SEARCH("Ideas",$F25)))),$W25,NA()) | AE25: =IF(AND($V25<>"No",$E25="Rare",NOT(ISNUMBER(SEARCH("Ideas",$F25)))),$W25,NA()) | AF25: =IF(AND($V25<>"No",$E25="Legendary",NOT(ISNUMBER(SEARCH("Ideas",$F25)))),$W25,NA()) | AG25: =IF(AND($V25<>"No",ISNUMBER(SEARCH("Knight",$C25)),NOT(ISNUMBER(SEARCH("Ideas",$F25)))),$X25,NA()) | AH25: =IF(AND($V25<>"No",ISNUMBER(SEARCH("Mage",$C25)),NOT(ISNUMBER(SEARCH("Ideas",$F25)))),$X25,NA()) | AI25: =IF(AND($V25<>"No",ISNUMBER(SEARCH("Rogue",$C25)),NOT(ISNUMBER(SEARCH("Ideas",$F25)))),$X25,NA()) | AJ25: =IF($V25<>"No",$Y25,NA()) | AK25: =IF(AND($V25<>"No",ISNUMBER(SEARCH("Ideas",$F25))),$W25,NA()) | AL25: =IF(AND($V25<>"No",ISNUMBER(SEARCH("Cleric",$C25)),NOT(ISNUMBER(SEARCH("Ideas",$F25)))),$X25,NA())
A26: Covering Strike | B26: Covering Strike | C26: Knight | D26: 1 | E26: Uncommon | F26: Knight | G26: 1 | H26: 8 | I26: 9 | J26: 0 | K26: 5 | L26: 0 | M26: 0 | N26: 0 | O26: 0 | P26: 0 | Q26: 0 | R26: 0 | S26: 0 | V26: Yes | W26: =IF($V26="No","",ROUND((I26*w_Damage + N26*w_Poison + P26*w_Weaken*w_Horizon)*MIN(1+(G26-1)*w_OccEnemy,w_MaxEnemies) + (J26*w_Heal + K26*w_Shield + L26*w_Block + M26*w_Parry + O26*w_Strength*w_Horizon + S26*w_Combo)*MIN(1+(H26-1)*w_OccAlly,w_MaxAllies) + Q26*w_Draw + R26*w_Move,2)) | X26: =IF(W26="","",ROUND(W26/MAX(D26,1),2)) | Y26: =IF($V26="No","",ROUND((curve_Base+curve_Slope*D26)*IFERROR(VLOOKUP(E26,rarity_Mult,2,FALSE),1),2)) | Z26: =IF(OR(W26="",Y26=""),"",ROUND(W26-Y26,2)) | AA26: =IF(Z26="","",IF($V26="Partial","RIDER",IF(ABS(Z26)<=Y26*tol_Pct,"OK",IF(Z26>0,"OVER","UNDER")))) | AC26: =IF(AND($V26<>"No",$E26="Common",NOT(ISNUMBER(SEARCH("Ideas",$F26)))),$W26,NA()) | AD26: =IF(AND($V26<>"No",$E26="Uncommon",NOT(ISNUMBER(SEARCH("Ideas",$F26)))),$W26,NA()) | AE26: =IF(AND($V26<>"No",$E26="Rare",NOT(ISNUMBER(SEARCH("Ideas",$F26)))),$W26,NA()) | AF26: =IF(AND($V26<>"No",$E26="Legendary",NOT(ISNUMBER(SEARCH("Ideas",$F26)))),$W26,NA()) | AG26: =IF(AND($V26<>"No",ISNUMBER(SEARCH("Knight",$C26)),NOT(ISNUMBER(SEARCH("Ideas",$F26)))),$X26,NA()) | AH26: =IF(AND($V26<>"No",ISNUMBER(SEARCH("Mage",$C26)),NOT(ISNUMBER(SEARCH("Ideas",$F26)))),$X26,NA()) | AI26: =IF(AND($V26<>"No",ISNUMBER(SEARCH("Rogue",$C26)),NOT(ISNUMBER(SEARCH("Ideas",$F26)))),$X26,NA()) | AJ26: =IF($V26<>"No",$Y26,NA()) | AK26: =IF(AND($V26<>"No",ISNUMBER(SEARCH("Ideas",$F26))),$W26,NA()) | AL26: =IF(AND($V26<>"No",ISNUMBER(SEARCH("Cleric",$C26)),NOT(ISNUMBER(SEARCH("Ideas",$F26)))),$X26,NA())
A27: Flanking Strike | B27: Flanking Strike | C27: Knight | D27: 1 | E27: Uncommon | F27: Knight | G27: 1 | H27: 1 | I27: 7 | J27: 0 | K27: 4 | L27: 0 | M27: 0 | N27: 0 | O27: 0 | P27: 0 | Q27: 0 | R27: 0 | S27: 0 | V27: Yes | W27: =IF($V27="No","",ROUND((I27*w_Damage + N27*w_Poison + P27*w_Weaken*w_Horizon)*MIN(1+(G27-1)*w_OccEnemy,w_MaxEnemies) + (J27*w_Heal + K27*w_Shield + L27*w_Block + M27*w_Parry + O27*w_Strength*w_Horizon + S27*w_Combo)*MIN(1+(H27-1)*w_OccAlly,w_MaxAllies) + Q27*w_Draw + R27*w_Move,2)) | X27: =IF(W27="","",ROUND(W27/MAX(D27,1),2)) | Y27: =IF($V27="No","",ROUND((curve_Base+curve_Slope*D27)*IFERROR(VLOOKUP(E27,rarity_Mult,2,FALSE),1),2)) | Z27: =IF(OR(W27="",Y27=""),"",ROUND(W27-Y27,2)) | AA27: =IF(Z27="","",IF($V27="Partial","RIDER",IF(ABS(Z27)<=Y27*tol_Pct,"OK",IF(Z27>0,"OVER","UNDER")))) | AC27: =IF(AND($V27<>"No",$E27="Common",NOT(ISNUMBER(SEARCH("Ideas",$F27)))),$W27,NA()) | AD27: =IF(AND($V27<>"No",$E27="Uncommon",NOT(ISNUMBER(SEARCH("Ideas",$F27)))),$W27,NA()) | AE27: =IF(AND($V27<>"No",$E27="Rare",NOT(ISNUMBER(SEARCH("Ideas",$F27)))),$W27,NA()) | AF27: =IF(AND($V27<>"No",$E27="Legendary",NOT(ISNUMBER(SEARCH("Ideas",$F27)))),$W27,NA()) | AG27: =IF(AND($V27<>"No",ISNUMBER(SEARCH("Knight",$C27)),NOT(ISNUMBER(SEARCH("Ideas",$F27)))),$X27,NA()) | AH27: =IF(AND($V27<>"No",ISNUMBER(SEARCH("Mage",$C27)),NOT(ISNUMBER(SEARCH("Ideas",$F27)))),$X27,NA()) | AI27: =IF(AND($V27<>"No",ISNUMBER(SEARCH("Rogue",$C27)),NOT(ISNUMBER(SEARCH("Ideas",$F27)))),$X27,NA()) | AJ27: =IF($V27<>"No",$Y27,NA()) | AK27: =IF(AND($V27<>"No",ISNUMBER(SEARCH("Ideas",$F27))),$W27,NA()) | AL27: =IF(AND($V27<>"No",ISNUMBER(SEARCH("Cleric",$C27)),NOT(ISNUMBER(SEARCH("Ideas",$F27)))),$X27,NA())
... A32: Slash+ | B32: Slash+ | C32: Knight | D32: 1 | E32: NotOffered | F32: Knight | G32: 1 | H32: 1 | I32: 9 | J32: 0 | K32: 0 | L32: 0 | M32: 0 | N32: 0 | O32: 0 | P32: 0 | Q32: 0 | R32: 0 | S32: 0 | V32: Yes | W32: =IF($V32="No","",ROUND((I32*w_Damage + N32*w_Poison + P32*w_Weaken*w_Horizon)*MIN(1+(G32-1)*w_OccEnemy,w_MaxEnemies) + (J32*w_Heal + K32*w_Shield + L32*w_Block + M32*w_Parry + O32*w_Strength*w_Horizon + S32*w_Combo)*MIN(1+(H32-1)*w_OccAlly,w_MaxAllies) + Q32*w_Draw + R32*w_Move,2)) | X32: =IF(W32="","",ROUND(W32/MAX(D32,1),2)) | Y32: =IF($V32="No","",ROUND((curve_Base+curve_Slope*D32)*IFERROR(VLOOKUP(E32,rarity_Mult,2,FALSE),1),2)) | Z32: =IF(OR(W32="",Y32=""),"",ROUND(W32-Y32,2)) | AA32: =IF(Z32="","",IF($V32="Partial","RIDER",IF(ABS(Z32)<=Y32*tol_Pct,"OK",IF(Z32>0,"OVER","UNDER")))) | AC32: =IF(AND($V32<>"No",$E32="Common",NOT(ISNUMBER(SEARCH("Ideas",$F32)))),$W32,NA()) | AD32: =IF(AND($V32<>"No",$E32="Uncommon",NOT(ISNUMBER(SEARCH("Ideas",$F32)))),$W32,NA()) | AE32: =IF(AND($V32<>"No",$E32="Rare",NOT(ISNUMBER(SEARCH("Ideas",$F32)))),$W32,NA()) | AF32: =IF(AND($V32<>"No",$E32="Legendary",NOT(ISNUMBER(SEARCH("Ideas",$F32)))),$W32,NA()) | AG32: =IF(AND($V32<>"No",ISNUMBER(SEARCH("Knight",$C32)),NOT(ISNUMBER(SEARCH("Ideas",$F32)))),$X32,NA()) | AH32: =IF(AND($V32<>"No",ISNUMBER(SEARCH("Mage",$C32)),NOT(ISNUMBER(SEARCH("Ideas",$F32)))),$X32,NA()) | AI32: =IF(AND($V32<>"No",ISNUMBER(SEARCH("Rogue",$C32)),NOT(ISNUMBER(SEARCH("Ideas",$F32)))),$X32,NA()) | AJ32: =IF($V32<>"No",$Y32,NA()) | AK32: =IF(AND($V32<>"No",ISNUMBER(SEARCH("Ideas",$F32))),$W32,NA()) | AL32: =IF(AND($V32<>"No",ISNUMBER(SEARCH("Cleric",$C32)),NOT(ISNUMBER(SEARCH("Ideas",$F32)))),$X32,NA())
A33: Sunder | B33: Sunder | C33: Knight | D33: 1 | E33: Uncommon | F33: Knight | G33: 1 | H33: 1 | I33: 5 | J33: 0 | K33: 0 | L33: 0 | M33: 0 | N33: 0 | O33: 0 | P33: 0 | Q33: 0 | R33: 0 | S33: 0 | U33: Vulnerable | V33: Yes | W33: =IF($V33="No","",ROUND((I33*w_Damage + N33*w_Poison + P33*w_Weaken*w_Horizon)*MIN(1+(G33-1)*w_OccEnemy,w_MaxEnemies) + (J33*w_Heal + K33*w_Shield + L33*w_Block + M33*w_Parry + O33*w_Strength*w_Horizon + S33*w_Combo)*MIN(1+(H33-1)*w_OccAlly,w_MaxAllies) + Q33*w_Draw + R33*w_Move,2)) | X33: =IF(W33="","",ROUND(W33/MAX(D33,1),2)) | Y33: =IF($V33="No","",ROUND((curve_Base+curve_Slope*D33)*IFERROR(VLOOKUP(E33,rarity_Mult,2,FALSE),1),2)) | Z33: =IF(OR(W33="",Y33=""),"",ROUND(W33-Y33,2)) | AA33: =IF(Z33="","",IF($V33="Partial","RIDER",IF(ABS(Z33)<=Y33*tol_Pct,"OK",IF(Z33>0,"OVER","UNDER")))) | AC33: =IF(AND($V33<>"No",$E33="Common",NOT(ISNUMBER(SEARCH("Ideas",$F33)))),$W33,NA()) | AD33: =IF(AND($V33<>"No",$E33="Uncommon",NOT(ISNUMBER(SEARCH("Ideas",$F33)))),$W33,NA()) | AE33: =IF(AND($V33<>"No",$E33="Rare",NOT(ISNUMBER(SEARCH("Ideas",$F33)))),$W33,NA()) | AF33: =IF(AND($V33<>"No",$E33="Legendary",NOT(ISNUMBER(SEARCH("Ideas",$F33)))),$W33,NA()) | AG33: =IF(AND($V33<>"No",ISNUMBER(SEARCH("Knight",$C33)),NOT(ISNUMBER(SEARCH("Ideas",$F33)))),$X33,NA()) | AH33: =IF(AND($V33<>"No",ISNUMBER(SEARCH("Mage",$C33)),NOT(ISNUMBER(SEARCH("Ideas",$F33)))),$X33,NA()) | AI33: =IF(AND($V33<>"No",ISNUMBER(SEARCH("Rogue",$C33)),NOT(ISNUMBER(SEARCH("Ideas",$F33)))),$X33,NA()) | AJ33: =IF($V33<>"No",$Y33,NA()) | AK33: =IF(AND($V33<>"No",ISNUMBER(SEARCH("Ideas",$F33))),$W33,NA()) | AL33: =IF(AND($V33<>"No",ISNUMBER(SEARCH("Cleric",$C33)),NOT(ISNUMBER(SEARCH("Ideas",$F33)))),$X33,NA())
A34: Sweeping Blow | B34: Sweeping Blow | C34: Knight | D34: 1 | E34: Uncommon | F34: Knight | G34: 3 | H34: 1 | I34: 7 | J34: 0 | K34: 0 | L34: 0 | M34: 0 | N34: 0 | O34: 0 | P34: 0 | Q34: 0 | R34: 0 | S34: 0 | V34: Yes | W34: =IF($V34="No","",ROUND((I34*w_Damage + N34*w_Poison + P34*w_Weaken*w_Horizon)*MIN(1+(G34-1)*w_OccEnemy,w_MaxEnemies) + (J34*w_Heal + K34*w_Shield + L34*w_Block + M34*w_Parry + O34*w_Strength*w_Horizon + S34*w_Combo)*MIN(1+(H34-1)*w_OccAlly,w_MaxAllies) + Q34*w_Draw + R34*w_Move,2)) | X34: =IF(W34="","",ROUND(W34/MAX(D34,1),2)) | Y34: =IF($V34="No","",ROUND((curve_Base+curve_Slope*D34)*IFERROR(VLOOKUP(E34,rarity_Mult,2,FALSE),1),2)) | Z34: =IF(OR(W34="",Y34=""),"",ROUND(W34-Y34,2)) | AA34: =IF(Z34="","",IF($V34="Partial","RIDER",IF(ABS(Z34)<=Y34*tol_Pct,"OK",IF(Z34>0,"OVER","UNDER")))) | AC34: =IF(AND($V34<>"No",$E34="Common",NOT(ISNUMBER(SEARCH("Ideas",$F34)))),$W34,NA()) | AD34: =IF(AND($V34<>"No",$E34="Uncommon",NOT(ISNUMBER(SEARCH("Ideas",$F34)))),$W34,NA()) | AE34: =IF(AND($V34<>"No",$E34="Rare",NOT(ISNUMBER(SEARCH("Ideas",$F34)))),$W34,NA()) | AF34: =IF(AND($V34<>"No",$E34="Legendary",NOT(ISNUMBER(SEARCH("Ideas",$F34)))),$W34,NA()) | AG34: =IF(AND($V34<>"No",ISNUMBER(SEARCH("Knight",$C34)),NOT(ISNUMBER(SEARCH("Ideas",$F34)))),$X34,NA()) | AH34: =IF(AND($V34<>"No",ISNUMBER(SEARCH("Mage",$C34)),NOT(ISNUMBER(SEARCH("Ideas",$F34)))),$X34,NA()) | AI34: =IF(AND($V34<>"No",ISNUMBER(SEARCH("Rogue",$C34)),NOT(ISNUMBER(SEARCH("Ideas",$F34)))),$X34,NA()) | AJ34: =IF($V34<>"No",$Y34,NA()) | AK34: =IF(AND($V34<>"No",ISNUMBER(SEARCH("Ideas",$F34))),$W34,NA()) | AL34: =IF(AND($V34<>"No",ISNUMBER(SEARCH("Cleric",$C34)),NOT(ISNUMBER(SEARCH("Ideas",$F34)))),$X34,NA())
